Workbook

Sheet Master Data 9-9-26
A1: Uniq-ID | B1: Kolom1 | C1: Name ID | D1: Account | E1: Period | F1: Period Date | G1: Period Status | H1: Productivity Range | I1: Total % Ach. | J1: Payment Coef. | K1: Document Category | L1: Document Type | M1: Source Data | N1: Baseline/Cycle | O1: Total Doc. | P1: % Achievement | Q1: Departemen | R1: Region | S1: Productivity | T1: QEHS Inspection (ONSITE) | U1: Compliance Check (TL) | V1: Training (Class) | W1: Baseline | X1: Achievement | Y1: M4 MOS (20%) | Z1: M5 Installation (30%) | AA1: On Air (20%) | AB1: ATP Submit (20%) | AC1: ATP Approve (20%) | AD1: Total Score
A2: DC-Document_Controller-017 | B2: =Master_Data_Productivity[[#This Row],[Uniq-ID]]&"-"&Master_Data_Productivity[[#This Row],[Period]] -> DC-Document_Controller-017-M1 | C2: Lidya Juwita Apriliani wx1504642 | D2: IOH | E2: M1 | F2: 2026-03-31 - 2026-04-29 | G2: Ended | H2: Excellent | I2: 2.093 | J2: 1.05 | K2: Implementation | L2: M-08b Inbound Done | M2: ISDP | N2: 154 | O2: 108 | P2: 0.7013 | Q2: DC
A3: DC-Document_Controller-017 | B3: =Master_Data_Productivity[[#This Row],[Uniq-ID]]&"-"&Master_Data_Productivity[[#This Row],[Period]] -> DC-Document_Controller-017-M1 | C3: Lidya Juwita Apriliani wx1504642 | D3: IOH | E3: M1 | F3: 2026-03-31 - 2026-04-29 | G3: Ended | H3: Excellent | I3: 2.093 | J3: 1.05 | K3: Implementation | L3: Netgear Tagging MOS & Movement | M3: ISDP | N3: 168 | O3: 140 | P3: 0.8333 | Q3: DC
A4: DC-Document_Controller-017 | B4: =Master_Data_Productivity[[#This Row],[Uniq-ID]]&"-"&Master_Data_Productivity[[#This Row],[Period]] -> DC-Document_Controller-017-M1 | C4: Lidya Juwita Apriliani wx1504642 | D4: IOH | E4: M1 | F4: 2026-03-31 - 2026-04-29 | G4: Ended | H4: Excellent | I4: 2.093 | J4: 1.05 | K4: Acceptance | L4: ATP Endorse - Wireless | M4: ISDP | N4: 616 | O4: 344 | P4: 0.5584 | Q4: DC
A5: DC-Document_Controller-017 | B5: =Master_Data_Productivity[[#This Row],[Uniq-ID]]&"-"&Master_Data_Productivity[[#This Row],[Period]] -> DC-Document_Controller-017-M2 | C5: Lidya Juwita Apriliani wx1504642 | D5: IOH | E5: M2 | F5: 2026-04-30 - 2026-05-30 | G5: Ended | H5: Excellent | I5: 2.347 | J5: 1.17 | K5: Implementation | L5: M-08b Inbound Done | M5: ISDP | N5: 154 | O5: 115 | P5: 0.7468 | Q5: DC
A6: DC-Document_Controller-017 | B6: =Master_Data_Productivity[[#This Row],[Uniq-ID]]&"-"&Master_Data_Productivity[[#This Row],[Period]] -> DC-Document_Controller-017-M2 | C6: Lidya Juwita Apriliani wx1504642 | D6: IOH | E6: M2 | F6: 2026-04-30 - 2026-05-30 | G6: Ended | H6: Excellent | I6: 2.347 | J6: 1.17 | K6: Implementation | L6: Netgear Tagging MOS & Movement | M6: ISDP | N6: 168 | O6: 180 | P6: 1.0714 | Q6: DC
A7: DC-Document_Controller-017 | B7: =Master_Data_Productivity[[#This Row],[Uniq-ID]]&"-"&Master_Data_Productivity[[#This Row],[Period]] -> DC-Document_Controller-017-M2 | C7: Lidya Juwita Apriliani wx1504642 | D7: IOH | E7: M2 | F7: 2026-04-30 - 2026-05-30 | G7: Ended | H7: Excellent | I7: 2.347 | J7: 1.17 | K7: Acceptance | L7: ATP Endorse - Wireless | M7: ISDP | N7: 616 | O7: 326 | P7: 0.5292 | Q7: DC
A8: DC-Document_Controller-017 | B8: =Master_Data_Productivity[[#This Row],[Uniq-ID]]&"-"&Master_Data_Productivity[[#This Row],[Period]] -> DC-Document_Controller-017-M3 | C8: Lidya Juwita Apriliani wx1504642 | D8: IOH | E8: M3 | F8: 2026-05-31 - 2026-06-29 | G8: Ended | H8: Excellent | I8: 3.241 | J8: 1.5 | K8: Acceptance | L8: ATP Endorse - Wireless | M8: ISDP | N8: 616 | O8: 72 | P8: 0.1169 | Q8: DC
A9: DC-Document_Controller-017 | B9: =Master_Data_Productivity[[#This Row],[Uniq-ID]]&"-"&Master_Data_Productivity[[#This Row],[Period]] -> DC-Document_Controller-017-M3 | C9: Lidya Juwita Apriliani wx1504642 | D9: IOH | E9: M3 | F9: 2026-05-31 - 2026-06-29 | G9: Ended | H9: Excellent | I9: 3.241 | J9: 1.5 | K9: Acceptance | L9: BAUT/BAMS PAC/BAMG FAC - Wireless | M9: Datalink | O9: 239 | Q9: DC
A10: DC-Document_Controller-017 | B10: =Master_Data_Productivity[[#This Row],[Uniq-ID]]&"-"&Master_Data_Productivity[[#This Row],[Period]] -> DC-Document_Controller-017-M3 | C10: Lidya Juwita Apriliani wx1504642 | D10: IOH | E10: M3 | F10: 2026-05-31 - 2026-06-29 | G10: Ended | H10: Excellent | I10: 3.241 | J10: 1.5 | K10: Acceptance | L10: Change Request (CR) | M10: Datalink | N10: 308 | O10: 6 | P10: 0.0195 | Q10: DC
A11: DC-Document_Controller-017 | B11: =Master_Data_Productivity[[#This Row],[Uniq-ID]]&"-"&Master_Data_Productivity[[#This Row],[Period]] -> DC-Document_Controller-017-M3 | C11: Lidya Juwita Apriliani wx1504642 | D11: IOH | E11: M3 | F11: 2026-05-31 - 2026-06-29 | G11: Ended | H11: Excellent | I11: 3.241 | J11: 1.5 | K11: Implementation | L11: M-08b Inbound Done | M11: ISDP | N11: 154 | O11: 151 | P11: 0.9805 | Q11: DC
A12: DC-Document_Controller-017 | B12: =Master_Data_Productivity[[#This Row],[Uniq-ID]]&"-"&Master_Data_Productivity[[#This Row],[Period]] -> DC-Document_Controller-017-M3 | C12: Lidya Juwita Apriliani wx1504642 | D12: IOH | E12: M3 | F12: 2026-05-31 - 2026-06-29 | G12: Ended | H12: Excellent | I12: 3.241 | J12: 1.5 | K12: Implementation | L12: Netgear Tagging MOS & Movement | M12: ISDP | N12: 168 | O12: 340 | P12: 2.0238 | Q12: DC
A13: DC-Document_Controller-017 | B13: =Master_Data_Productivity[[#This Row],[Uniq-ID]]&"-"&Master_Data_Productivity[[#This Row],[Period]] -> DC-Document_Controller-017-M3 | C13: Lidya Juwita Apriliani wx1504642 | D13: IOH | E13: M3 | F13: 2026-05-31 - 2026-06-29 | G13: Ended | H13: Excellent | I13: 3.241 | J13: 1.5 | K13: Pre-implementation | L13: Change Request (CR) | M13: Datalink | N13: 308 | O13: 31 | P13: 0.1006 | Q13: DC
A14: DC-Document_Controller-017 | B14: =Master_Data_Productivity[[#This Row],[Uniq-ID]]&"-"&Master_Data_Productivity[[#This Row],[Period]] -> DC-Document_Controller-017-M4 | C14: Lidya Juwita Apriliani wx1504642 | D14: IOH | E14: M4 | F14: 2026-06-30 - 2026-07-30 | G14: Ended | H14: Excellent | I14: 3.907 | J14: 1.5 | L14: BAUT/BAMS PAC/BAMG FAC - Wireless | M14: ISDP | O14: 695 | Q14: DC
A15: DC-Document_Controller-017 | B15: =Master_Data_Productivity[[#This Row],[Uniq-ID]]&"-"&Master_Data_Productivity[[#This Row],[Period]] -> DC-Document_Controller-017-M4 | C15: Lidya Juwita Apriliani wx1504642 | D15: IOH | E15: M4 | F15: 2026-06-30 - 2026-07-30 | G15: Ended | H15: Excellent | I15: 3.907 | J15: 1.5 | K15: Pre-implementation | L15: Change Request (CR) | M15: Datalink | N15: 308 | O15: 36 | P15: 0.1169 | Q15: DC
A16: DC-Document_Controller-017 | B16: =Master_Data_Productivity[[#This Row],[Uniq-ID]]&"-"&Master_Data_Productivity[[#This Row],[Period]] -> DC-Document_Controller-017-M4 | C16: Lidya Juwita Apriliani wx1504642 | D16: IOH | E16: M4 | F16: 2026-06-30 - 2026-07-30 | G16: Ended | H16: Excellent | I16: 3.907 | J16: 1.5 | K16: Implementation | L16: Netgear Tagging MOS & Movement | M16: ISDP | N16: 168 | O16: 154 | P16: 0.9167 | Q16: DC
A17: DC-Document_Controller-017 | B17: =Master_Data_Productivity[[#This Row],[Uniq-ID]]&"-"&Master_Data_Productivity[[#This Row],[Period]] -> DC-Document_Controller-017-M4 | C17: Lidya Juwita Apriliani wx1504642 | D17: IOH | E17: M4 | F17: 2026-06-30 - 2026-07-30 | G17: Ended | H17: Excellent | I17: 3.907 | J17: 1.5 | K17: Implementation | L17: M-08b Inbound Done | M17: ISDP | N17: 154 | O17: 189 | P17: 1.2273 | Q17: DC
A18: DC-Document_Controller-017 | B18: =Master_Data_Productivity[[#This Row],[Uniq-ID]]&"-"&Master_Data_Productivity[[#This Row],[Period]] -> DC-Document_Controller-017-M4 | C18: Lidya Juwita Apriliani wx1504642 | D18: IOH | E18: M4 | F18: 2026-06-30 - 2026-07-30 | G18: Ended | H18: Excellent | I18: 3.907 | J18: 1.5 | K18: Acceptance | L18: BAUT/BAMS PAC/BAMG FAC - Wireless | M18: ISDP | N18: 462 | O18: 544 | P18: 1.1775 | Q18: DC
A19: DC-Document_Controller-017 | B19: =Master_Data_Productivity[[#This Row],[Uniq-ID]]&"-"&Master_Data_Productivity[[#This Row],[Period]] -> DC-Document_Controller-017-M4 | C19: Lidya Juwita Apriliani wx1504642 | D19: IOH | E19: M4 | F19: 2026-06-30 - 2026-07-30 | G19: Ended | H19: Excellent | I19: 3.907 | J19: 1.5 | K19: Acceptance | L19: ATP Endorse - Wireless | M19: ISDP | N19: 616 | O19: 289 | P19: 0.4692 | Q19: DC
A20: DC-Document_Controller-017 | B20: =Master_Data_Productivity[[#This Row],[Uniq-ID]]&"-"&Master_Data_Productivity[[#This Row],[Period]] -> DC-Document_Controller-017-M5 | C20: Lidya Juwita Apriliani wx1504642 | D20: IOH | E20: M5 | F20: 2026-07-31 - 2026-08-30 | G20: Ended | H20: Normal | I20: 1.683 | J20: 1 | K20: Acceptance | L20: ATP Endorse - Wireless | M20: ISDP | N20: 616 | O20: 50 | P20: 0.0812 | Q20: DC
A21: DC-Document_Controller-017 | B21: =Master_Data_Productivity[[#This Row],[Uniq-ID]]&"-"&Master_Data_Productivity[[#This Row],[Period]] -> DC-Document_Controller-017-M5 | C21: Lidya Juwita Apriliani wx1504642 | D21: IOH | E21: M5 | F21: 2026-07-31 - 2026-08-30 | G21: Ended | H21: Normal | I21: 1.683 | J21: 1 | K21: Acceptance | L21: BAUT/BAMS PAC/BAMG FAC - Wireless | M21: ISDP | N21: 462 | O21: 533 | P21: 1.1537 | Q21: DC
A22: DC-Document_Controller-017 | B22: =Master_Data_Productivity[[#This Row],[Uniq-ID]]&"-"&Master_Data_Productivity[[#This Row],[Period]] -> DC-Document_Controller-017-M5 | C22: Lidya Juwita Apriliani wx1504642 | D22: IOH | E22: M5 | F22: 2026-07-31 - 2026-08-30 | G22: Ended | H22: Normal | I22: 1.683 | J22: 1 | K22: Implementation | L22: M-08b Inbound Done | M22: ISDP | N22: 154 | O22: 52 | P22: 0.3377 | Q22: DC
A23: DC-Document_Controller-017 | B23: =Master_Data_Productivity[[#This Row],[Uniq-ID]]&"-"&Master_Data_Productivity[[#This Row],[Period]] -> DC-Document_Controller-017-M5 | C23: Lidya Juwita Apriliani wx1504642 | D23: IOH | E23: M5 | F23: 2026-07-31 - 2026-08-30 | G23: Ended | H23: Normal | I23: 1.683 | J23: 1 | K23: Pre-implementation | L23: Change Request (CR) | M23: Datalink | N23: 308 | O23: 34 | P23: 0.1104 | Q23: DC
A24: DC-Document_Controller-017 | B24: =Master_Data_Productivity[[#This Row],[Uniq-ID]]&"-"&Master_Data_Productivity[[#This Row],[Period]] -> DC-Document_Controller-017-M5 | C24: Lidya Juwita Apriliani wx1504642 | D24: IOH | E24: M5 | F24: 2026-07-31 - 2026-08-30 | G24: Ended | H24: Normal | I24: 1.683 | J24: 1 | L24: BAUT/BAMS PAC/BAMG FAC - Wireless | M24: ISDP | O24: 421 | Q24: DC
A25: DC-Document_Controller-017 | B25: =Master_Data_Productivity[[#This Row],[Uniq-ID]]&"-"&Master_Data_Productivity[[#This Row],[Period]] -> DC-Document_Controller-017-M6 | C25: Lidya Juwita Apriliani wx1504642 | D25: IOH | E25: M6 | F25: 2026-08-31 - 2026-09-29 | G25: Ongoing | H25: Poor | I25: 0.013 | J25: 0.5 | K25: Implementation | L25: M-08b Inbound Done | M25: ISDP | N25: 154 | O25: 2 | P25: 0.013 | Q25: DC
A26: DC-Document_Controller-023 | B26: =Master_Data_Productivity[[#This Row],[Uniq-ID]]&"-"&Master_Data_Productivity[[#This Row],[Period]] -> DC-Document_Controller-023-M1 | C26: Ika Setianingsih wx1507364 | D26: XLSMART | E26: M1 | F26: 2026-04-01 - 2026-04-30 | G26: Ended | H26: Excellent | I26: 24.5 | J26: 1.5 | K26: Acceptance | L26: IPS Submit | M26: Datalink | N26: 4 | O26: 98 | P26: 24.5 | Q26: DC
A27: DC-Document_Controller-023 | B27: =Master_Data_Productivity[[#This Row],[Uniq-ID]]&"-"&Master_Data_Productivity[[#This Row],[Period]] -> DC-Document_Controller-023-M2 | C27: Ika Setianingsih wx1507364 | D27: XLSMART | E27: M2 | F27: 2026-05-01 - 2026-05-31 | G27: Ended | H27: Excellent | I27: 5.032 | J27: 1.5 | K27: PO Mapping Initial | L27: PO Mapping | M27: Datalink | N27: 31 | O27: 156 | P27: 5.0323 | Q27: DC
A28: DC-Document_Controller-023 | B28: =Master_Data_Productivity[[#This Row],[Uniq-ID]]&"-"&Master_Data_Productivity[[#This Row],[Period]] -> DC-Document_Controller-023-M3 | C28: Ika Setianingsih wx1507364 | D28: XLSMART | E28: M3 | F28: 2026-06-01 - 2026-06-30 | G28: Ended | H28: Normal | I28: 1.516 | J28: 1 | K28: PO Mapping Initial | L28: PO Mapping | M28: Datalink | O28: 47 | Q28: DC
A29: DC-Document_Controller-023 | B29: =Master_Data_Productivity[[#This Row],[Uniq-ID]]&"-"&Master_Data_Productivity[[#This Row],[Period]] -> DC-Document_Controller-023-M3 | C29: Ika Setianingsih wx1507364 | D29: XLSMART | E29: M3 | F29: 2026-06-01 - 2026-06-30 | G29: Ended | H29: Normal | I29: 1.516 | J29: 1 | K29: PO Mapping Initial | L29: PO Mapping | M29: Datalink | N29: 31 | O29: 47 | P29: 1.5161 | Q29: DC
A30: DC-Document_Controller-023 | B30: =Master_Data_Productivity[[#This Row],[Uniq-ID]]&"-"&Master_Data_Productivity[[#This Row],[Period]] -> DC-Document_Controller-023-M3 | C30: Ika Setianingsih wx1507364 | D30: XLSMART | E30: M3 | F30: 2026-06-01 - 2026-06-30 | G30: Ended | H30: Normal | I30: 1.516 | J30: 1 | K30: Acceptance | L30: PO Mapping | M30: Datalink | O30: 38 | Q30: DC
A31: DC-Document_Controller-023 | B31: =Master_Data_Productivity[[#This Row],[Uniq-ID]]&"-"&Master_Data_Productivity[[#This Row],[Period]] -> DC-Document_Controller-023-M4 | C31: Ika Setianingsih wx1507364 | D31: XLSMART | E31: M4 | F31: 2026-07-01 - 2026-07-31 | G31: Ended | H31: Excellent | I31: 43.25 | J31: 1.5 | K31: Acceptance | L31: IPS Submit | M31: Datalink | N31: 4 | O31: 173 | P31: 43.25 | Q31: DC
A32: DC-Document_Controller-023 | B32: =Master_Data_Productivity[[#This Row],[Uniq-ID]]&"-"&Master_Data_Productivity[[#This Row],[Period]] -> DC-Document_Controller-023-M5 | C32: Ika Setianingsih wx1507364 | D32: XLSMART | E32: M5 | F32: 2026-08-01 - 2026-08-31 | G32: Ended | H32: Excellent | I32: 3.097 | J32: 1.5 | K32: Pre-implementation | L32: PO Mapping | M32: Datalink | N32: 31 | O32: 96 | P32: 3.0968 | Q32: DC
A33: DC-Document_Controller-023 | B33: =Master_Data_Productivity[[#This Row],[Uniq-ID]]&"-"&Master_Data_Productivity[[#This Row],[Period]] -> DC-Document_Controller-023-M6 | C33: Ika Setianingsih wx1507364 | D33: XLSMART | E33: M6 | F33: 2026-09-01 - 2026-09-30 | G33: Ongoing | H33: Poor | I33: 0 | Q33: DC
A34: DC-Document_Controller-022 | B34: =Master_Data_Productivity[[#This Row],[Uniq-ID]]&"-"&Master_Data_Productivity[[#This Row],[Period]] -> DC-Document_Controller-022-M1 | C34: Alifya Rahma Asy Syaffa wx1504637 | D34: Surge | E34: M1 | F34: 2026-04-01 - 2026-04-30 | G34: Ended | H34: Excellent | I34: 2.018 | J34: 1.01 | K34: Pre-implementation | L34: Site Permit | M34: Datalink | N34: 308 | O34: 22 | P34: 0.0714 | Q34: DC
A35: DC-Document_Controller-022 | B35: =Master_Data_Productivity[[#This Row],[Uniq-ID]]&"-"&Master_Data_Productivity[[#This Row],[Period]] -> DC-Document_Controller-022-M1 | C35: Alifya Rahma Asy Syaffa wx1504637 | D35: Surge | E35: M1 | F35: 2026-04-01 - 2026-04-30 | G35: Ended | H35: Excellent | I35: 2.018 | J35: 1.01 | K35: Pre-implementation | L35: Site Permit | M35: Datalink | N35: 26 | O35: 22 | P35: 0.8462 | Q35: DC
A36: DC-Document_Controller-022 | B36: =Master_Data_Productivity[[#This Row],[Uniq-ID]]&"-"&Master_Data_Productivity[[#This Row],[Period]] -> DC-Document_Controller-022-M1 | C36: Alifya Rahma Asy Syaffa wx1504637 | D36: Surge | E36: M1 | F36: 2026-04-01 - 2026-04-30 | G36: Ended | H36: Excellent | I36: 2.018 | J36: 1.01 | K36: Pre-implementation | L36: Site Permit | M36: Datalink | N36: 20 | O36: 22 | P36: 1.1 | Q36: DC
A37: DC-Document_Controller-022 | B37: =Master_Data_Productivity[[#This Row],[Uniq-ID]]&"-"&Master_Data_Productivity[[#This Row],[Period]] -> DC-Document_Controller-022-M2 | C37: Alifya Rahma Asy Syaffa wx1504637 | D37: Surge | E37: M2 | F37: 2026-05-01 - 2026-05-31 | G37: Ended | H37: Normal | I37: 1.926 | J37: 1 | K37: Pre-implementation | L37: Site Permit | M37: Datalink | N37: 20 | O37: 21 | P37: 1.05 | Q37: DC
A38: DC-Document_Controller-022 | B38: =Master_Data_Productivity[[#This Row],[Uniq-ID]]&"-"&Master_Data_Productivity[[#This Row],[Period]] -> DC-Document_Controller-022-M2 | C38: Alifya Rahma Asy Syaffa wx1504637 | D38: Surge | E38: M2 | F38: 2026-05-01 - 2026-05-31 | G38: Ended | H38: Normal | I38: 1.926 | J38: 1 | K38: Pre-implementation | L38: Site Permit | M38: Datalink | N38: 26 | O38: 21 | P38: 0.8077 | Q38: DC
A39: DC-Document_Controller-022 | B39: =Master_Data_Productivity[[#This Row],[Uniq-ID]]&"-"&Master_Data_Productivity[[#This Row],[Period]] -> DC-Document_Controller-022-M2 | C39: Alifya Rahma Asy Syaffa wx1504637 | D39: Surge | E39: M2 | F39: 2026-05-01 - 2026-05-31 | G39: Ended | H39: Normal | I39: 1.926 | J39: 1 | K39: Pre-implementation | L39: Site Permit | M39: Datalink | N39: 308 | O39: 21 | P39: 0.0682 | Q39: DC
A40: DC-Document_Controller-022 | B40: =Master_Data_Productivity[[#This Row],[Uniq-ID]]&"-"&Master_Data_Productivity[[#This Row],[Period]] -> DC-Document_Controller-022-M3 | C40: Alifya Rahma Asy Syaffa wx1504637 | D40: Surge | E40: M3 | F40: 2026-06-01 - 2026-06-30 | G40: Ended | H40: Poor | I40: 0.825 | J40: 0.83 | K40: Pre-implementation | L40: Site Permit | M40: Datalink | N40: 26 | O40: 9 | P40: 0.3462 | Q40: DC
A41: DC-Document_Controller-022 | B41: =Master_Data_Productivity[[#This Row],[Uniq-ID]]&"-"&Master_Data_Productivity[[#This Row],[Period]] -> DC-Document_Controller-022-M3 | C41: Alifya Rahma Asy Syaffa wx1504637 | D41: Surge | E41: M3 | F41: 2026-06-01 - 2026-06-30 | G41: Ended | H41: Poor | I41: 0.825 | J41: 0.83 | K41: Pre-implementation | L41: Site Permit | M41: Datalink | N41: 20 | O41: 9 | P41: 0.45 | Q41: DC
A42: DC-Document_Controller-022 | B42: =Master_Data_Productivity[[#This Row],[Uniq-ID]]&"-"&Master_Data_Productivity[[#This Row],[Period]] -> DC-Document_Controller-022-M3 | C42: Alifya Rahma Asy Syaffa wx1504637 | D42: Surge | E42: M3 | F42: 2026-06-01 - 2026-06-30 | G42: Ended | H42: Poor | I42: 0.825 | J42: 0.83 | K42: Pre-implementation | L42: Site Permit | M42: Datalink | N42: 308 | O42: 9 | P42: 0.0292 | Q42: DC
A43: DC-Document_Controller-022 | B43: =Master_Data_Productivity[[#This Row],[Uniq-ID]]&"-"&Master_Data_Productivity[[#This Row],[Period]] -> DC-Document_Controller-022-M4 | C43: Alifya Rahma Asy Syaffa wx1504637 | D43: Surge | E43: M4 | F43: 2026-07-01 - 2026-07-31 | G43: Ended | H43: Excellent | I43: 3.301 | J43: 1.5 | K43: Pre-implementation | L43: Site Permit | M43: Datalink | N43: 20 | O43: 36 | P43: 1.8 | Q43: DC
A44: DC-Document_Controller-022 | B44: =Master_Data_Productivity[[#This Row],[Uniq-ID]]&"-"&Master_Data_Productivity[[#This Row],[Period]] -> DC-Document_Controller-022-M4 | C44: Alifya Rahma Asy Syaffa wx1504637 | D44: Surge | E44: M4 | F44: 2026-07-01 - 2026-07-31 | G44: Ended | H44: Excellent | I44: 3.301 | J44: 1.5 | K44: Pre-implementation | L44: Site Permit | M44: Datalink | N44: 26 | O44: 36 | P44: 1.3846 | Q44: DC
A45: DC-Document_Controller-022 | B45: =Master_Data_Productivity[[#This Row],[Uniq-ID]]&"-"&Master_Data_Productivity[[#This Row],[Period]] -> DC-Document_Controller-022-M4 | C45: Alifya Rahma Asy Syaffa wx1504637 | D45: Surge | E45: M4 | F45: 2026-07-01 - 2026-07-31 | G45: Ended | H45: Excellent | I45: 3.301 | J45: 1.5 | K45: Pre-implementation | L45: Site Permit | M45: Datalink | N45: 308 | O45: 36 | P45: 0.1169 | Q45: DC
A46: DC-Document_Controller-022 | B46: =Master_Data_Productivity[[#This Row],[Uniq-ID]]&"-"&Master_Data_Productivity[[#This Row],[Period]] -> DC-Document_Controller-022-M5 | C46: Alifya Rahma Asy Syaffa wx1504637 | D46: Surge | E46: M5 | F46: 2026-08-01 - 2026-08-31 | G46: Ended | H46: Poor | I46: 0 | Q46: DC
A47: DC-Document_Controller-022 | B47: =Master_Data_Productivity[[#This Row],[Uniq-ID]]&"-"&Master_Data_Productivity[[#This Row],[Period]] -> DC-Document_Controller-022-M6 | C47: Alifya Rahma Asy Syaffa wx1504637 | D47: Surge | E47: M6 | F47: 2026-09-01 - 2026-09-30 | G47: Ongoing | H47: Poor | I47: 0 | Q47: DC
A48: DC-Document_Controller-021 | B48: =Master_Data_Productivity[[#This Row],[Uniq-ID]]&"-"&Master_Data_Productivity[[#This Row],[Period]] -> DC-Document_Controller-021-M1 | C48: Winarsih wx1503649 | D48: TELKOMSEL | E48: M1 | F48: 2026-04-01 - 2026-04-30 | G48: Ended | H48: Excellent | I48: 2.723 | J48: 1.36 | K48: Implementation | L48: M-08 Dismantle | M48: ISDP | N48: 36 | O48: 2 | P48: 0.0556 | Q48: DC
A49: DC-Document_Controller-021 | B49: =Master_Data_Productivity[[#This Row],[Uniq-ID]]&"-"&Master_Data_Productivity[[#This Row],[Period]] -> DC-Document_Controller-021-M1 | C49: Winarsih wx1503649 | D49: TELKOMSEL | E49: M1 | F49: 2026-04-01 - 2026-04-30 | G49: Ended | H49: Excellent | I49: 2.723 | J49: 1.36 | K49: Implementation | L49: Tagging Dismantle Material | M49: ISDP | N49: 35 | O49: 2 | P49: 0.0571 | Q49: DC
A50: DC-Document_Controller-021 | B50: =Master_Data_Productivity[[#This Row],[Uniq-ID]]&"-"&Master_Data_Productivity[[#This Row],[Period]] -> DC-Document_Controller-021-M1 | C50: Winarsih wx1503649 | D50: TELKOMSEL | E50: M1 | F50: 2026-04-01 - 2026-04-30 | G50: Ended | H50: Excellent | I50: 2.723 | J50: 1.36 | K50: Implementation | L50: Tagging Installation | M50: ISDP | N50: 32 | O50: 54 | P50: 1.6875 | Q50: DC
A51: DC-Document_Controller-021 | B51: =Master_Data_Productivity[[#This Row],[Uniq-ID]]&"-"&Master_Data_Productivity[[#This Row],[Period]] -> DC-Document_Controller-021-M1 | C51: Winarsih wx1503649 | D51: TELKOMSEL | E51: M1 | F51: 2026-04-01 - 2026-04-30 | G51: Ended | H51: Excellent | I51: 2.723 | J51: 1.36 | K51: Pre-implementation | L51: Tenant Installation Report | M51: ISDP | N51: 13 | O51: 12 | P51: 0.9231 | Q51: DC
A52: DC-Document_Controller-021 | B52: =Master_Data_Productivity[[#This Row],[Uniq-ID]]&"-"&Master_Data_Productivity[[#This Row],[Period]] -> DC-Document_Controller-021-M2 | C52: Winarsih wx1503649 | D52: TELKOMSEL | E52: M2 | F52: 2026-05-01 - 2026-05-31 | G52: Ended | H52: Normal | I52: 1.951 | J52: 1 | K52: Implementation | L52: M-08 Dismantle | M52: ISDP | N52: 36 | O52: 19 | P52: 0.5278 | Q52: DC
A53: DC-Document_Controller-021 | B53: =Master_Data_Productivity[[#This Row],[Uniq-ID]]&"-"&Master_Data_Productivity[[#This Row],[Period]] -> DC-Document_Controller-021-M2 | C53: Winarsih wx1503649 | D53: TELKOMSEL | E53: M2 | F53: 2026-05-01 - 2026-05-31 | G53: Ended | H53: Normal | I53: 1.951 | J53: 1 | K53: Implementation | L53: Tagging Dismantle Material | M53: ISDP | N53: 35 | O53: 17 | P53: 0.4857 | Q53: DC
A54: DC-Document_Controller-021 | B54: =Master_Data_Productivity[[#This Row],[Uniq-ID]]&"-"&Master_Data_Productivity[[#This Row],[Period]] -> DC-Document_Controller-021-M2 | C54: Winarsih wx1503649 | D54: TELKOMSEL | E54: M2 | F54: 2026-05-01 - 2026-05-31 | G54: Ended | H54: Normal | I54: 1.951 | J54: 1 | K54: Implementation | L54: Tagging Installation | M54: ISDP | N54: 32 | O54: 30 | P54: 0.9375 | Q54: DC
A55: DC-Document_Controller-021 | B55: =Master_Data_Productivity[[#This Row],[Uniq-ID]]&"-"&Master_Data_Productivity[[#This Row],[Period]] -> DC-Document_Controller-021-M3 | C55: Winarsih wx1503649 | D55: TELKOMSEL | E55: M3 | F55: 2026-06-01 - 2026-06-30 | G55: Ended | H55: Excellent | I55: 8.879 | J55: 1.5 | K55: Pre-implementation | L55: CAF Application | M55: ISDP | N55: 26 | O55: 3 | P55: 0.1154 | Q55: DC
A56: DC-Document_Controller-021 | B56: =Master_Data_Productivity[[#This Row],[Uniq-ID]]&"-"&Master_Data_Productivity[[#This Row],[Period]] -> DC-Document_Controller-021-M3 | C56: Winarsih wx1503649 | D56: TELKOMSEL | E56: M3 | F56: 2026-06-01 - 2026-06-30 | G56: Ended | H56: Excellent | I56: 8.879 | J56: 1.5 | K56: Acceptance | L56: BAUT (AC1) | M56: ISDP | N56: 205 | O56: 537 | P56: 2.6195 | Q56: DC
A57: DC-Document_Controller-021 | B57: =Master_Data_Productivity[[#This Row],[Uniq-ID]]&"-"&Master_Data_Productivity[[#This Row],[Period]] -> DC-Document_Controller-021-M3 | C57: Winarsih wx1503649 | D57: TELKOMSEL | E57: M3 | F57: 2026-06-01 - 2026-06-30 | G57: Ended | H57: Excellent | I57: 8.879 | J57: 1.5 | K57: Acceptance | L57: BAST (AC1) | M57: ISDP | N57: 205 | O57: 537 | P57: 2.6195 | Q57: DC
A58: DC-Document_Controller-021 | B58: =Master_Data_Productivity[[#This Row],[Uniq-ID]]&"-"&Master_Data_Productivity[[#This Row],[Period]] -> DC-Document_Controller-021-M3 | C58: Winarsih wx1503649 | D58: TELKOMSEL | E58: M3 | F58: 2026-06-01 - 2026-06-30 | G58: Ended | H58: Excellent | I58: 8.879 | J58: 1.5 | K58: Implementation | L58: M-08 Dismantle | M58: ISDP | N58: 36 | O58: 9 | P58: 0.25 | Q58: DC
A59: DC-Document_Controller-021 | B59: =Master_Data_Productivity[[#This Row],[Uniq-ID]]&"-"&Master_Data_Productivity[[#This Row],[Period]] -> DC-Document_Controller-021-M3 | C59: Winarsih wx1503649 | D59: TELKOMSEL | E59: M3 | F59: 2026-06-01 - 2026-06-30 | G59: Ended | H59: Excellent | I59: 8.879 | J59: 1.5 | K59: Implementation | L59: Tagging Dismantle Material | M59: ISDP | N59: 35 | O59: 14 | P59: 0.4 | Q59: DC
... A92: DC-Document_Controller-066 | B92: =Master_Data_Productivity[[#This Row],[Uniq-ID]]&"-"&Master_Data_Productivity[[#This Row],[Period]] -> DC-Document_Controller-066-M2 | C92: Rezicha Maulana Azazi wx1533627 | D92: XLSMART | E92: M2 | F92: 2026-08-08 - 2026-09-07 | G92: Ended | H92: Excellent | I92: 64.5 | J92: 1.5 | K92: Acceptance | L92: IPS Submit | M92: Datalink | N92: 4 | O92: 258 | P92: 64.5 | Q92: DC
A93: DC-Document_Controller-066 | B93: =Master_Data_Productivity[[#This Row],[Uniq-ID]]&"-"&Master_Data_Productivity[[#This Row],[Period]] -> DC-Document_Controller-066-M3 | C93: Rezicha Maulana Azazi wx1533627 | D93: XLSMART | E93: M3 | F93: 2026-09-08 - 2026-10-07 | G93: Ongoing | H93: Poor | I93: 0 | Q93: DC
A94: DC-Document_Controller-004 | B94: =Master_Data_Productivity[[#This Row],[Uniq-ID]]&"-"&Master_Data_Productivity[[#This Row],[Period]] -> DC-Document_Controller-004-M1 | C94: Hyang Iman Kinasih Gusti wx1503650 | D94: IOH | E94: M1 | F94: 2026-03-23 - 2026-04-22 | G94: Ended | H94: Excellent | I94: 9.171 | J94: 1.5 | K94: Pre-implementation | L94: Site Permit | M94: Datalink | N94: 20 | O94: 100 | P94: 5 | Q94: DC
A95: DC-Document_Controller-004 | B95: =Master_Data_Productivity[[#This Row],[Uniq-ID]]&"-"&Master_Data_Productivity[[#This Row],[Period]] -> DC-Document_Controller-004-M1 | C95: Hyang Iman Kinasih Gusti wx1503650 | D95: IOH | E95: M1 | F95: 2026-03-23 - 2026-04-22 | G95: Ended | H95: Excellent | I95: 9.171 | J95: 1.5 | K95: Pre-implementation | L95: Site Permit | M95: Datalink | N95: 26 | O95: 100 | P95: 3.8462 | Q95: DC
A96: DC-Document_Controller-004 | B96: =Master_Data_Productivity[[#This Row],[Uniq-ID]]&"-"&Master_Data_Productivity[[#This Row],[Period]] -> DC-Document_Controller-004-M1 | C96: Hyang Iman Kinasih Gusti wx1503650 | D96: IOH | E96: M1 | F96: 2026-03-23 - 2026-04-22 | G96: Ended | H96: Excellent | I96: 9.171 | J96: 1.5 | K96: Pre-implementation | L96: Site Permit | M96: Datalink | N96: 308 | O96: 100 | P96: 0.3247 | Q96: DC
A97: DC-Document_Controller-004 | B97: =Master_Data_Productivity[[#This Row],[Uniq-ID]]&"-"&Master_Data_Productivity[[#This Row],[Period]] -> DC-Document_Controller-004-M2 | C97: Hyang Iman Kinasih Gusti wx1503650 | D97: IOH | E97: M2 | F97: 2026-04-23 - 2026-05-22 | G97: Ended | H97: Excellent | I97: 9.171 | J97: 1.5 | K97: Pre-implementation | L97: Site Permit | M97: Datalink | N97: 20 | O97: 100 | P97: 5 | Q97: DC
A98: DC-Document_Controller-004 | B98: =Master_Data_Productivity[[#This Row],[Uniq-ID]]&"-"&Master_Data_Productivity[[#This Row],[Period]] -> DC-Document_Controller-004-M2 | C98: Hyang Iman Kinasih Gusti wx1503650 | D98: IOH | E98: M2 | F98: 2026-04-23 - 2026-05-22 | G98: Ended | H98: Excellent | I98: 9.171 | J98: 1.5 | K98: Pre-implementation | L98: Site Permit | M98: Datalink | N98: 26 | O98: 100 | P98: 3.8462 | Q98: DC
A99: DC-Document_Controller-004 | B99: =Master_Data_Productivity[[#This Row],[Uniq-ID]]&"-"&Master_Data_Productivity[[#This Row],[Period]] -> DC-Document_Controller-004-M2 | C99: Hyang Iman Kinasih Gusti wx1503650 | D99: IOH | E99: M2 | F99: 2026-04-23 - 2026-05-22 | G99: Ended | H99: Excellent | I99: 9.171 | J99: 1.5 | K99: Pre-implementation | L99: Site Permit | M99: Datalink | N99: 308 | O99: 100 | P99: 0.3247 | Q99: DC
A100: DC-Document_Controller-004 | B100: =Master_Data_Productivity[[#This Row],[Uniq-ID]]&"-"&Master_Data_Productivity[[#This Row],[Period]] -> DC-Document_Controller-004-M3 | C100: Hyang Iman Kinasih Gusti wx1503650 | D100: IOH | E100: M3 | F100: 2026-05-23 - 2026-06-22 | G100: Ended | H100: Excellent | I100: 16.141 | J100: 1.5 | K100: Pre-implementation | L100: Site Permit | M100: Datalink | N100: 26 | O100: 176 | P100: 6.7692 | Q100: DC
A101: DC-Document_Controller-004 | B101: =Master_Data_Productivity[[#This Row],[Uniq-ID]]&"-"&Master_Data_Productivity[[#This Row],[Period]] -> DC-Document_Controller-004-M3 | C101: Hyang Iman Kinasih Gusti wx1503650 | D101: IOH | E101: M3 | F101: 2026-05-23 - 2026-06-22 | G101: Ended | H101: Excellent | I101: 16.141 | J101: 1.5 | K101: Pre-implementation | L101: Site Permit | M101: Datalink | N101: 308 | O101: 176 | P101: 0.5714 | Q101: DC
A102: DC-Document_Controller-004 | B102: =Master_Data_Productivity[[#This Row],[Uniq-ID]]&"-"&Master_Data_Productivity[[#This Row],[Period]] -> DC-Document_Controller-004-M3 | C102: Hyang Iman Kinasih Gusti wx1503650 | D102: IOH | E102: M3 | F102: 2026-05-23 - 2026-06-22 | G102: Ended | H102: Excellent | I102: 16.141 | J102: 1.5 | K102: Pre-implementation | L102: Site Permit | M102: Datalink | N102: 20 | O102: 176 | P102: 8.8 | Q102: DC
A103: DC-Document_Controller-004 | B103: =Master_Data_Productivity[[#This Row],[Uniq-ID]]&"-"&Master_Data_Productivity[[#This Row],[Period]] -> DC-Document_Controller-004-M4 | C103: Hyang Iman Kinasih Gusti wx1503650 | D103: IOH | E103: M4 | F103: 2026-06-23 - 2026-07-22 | G103: Ended | H103: Excellent | I103: 10.455 | J103: 1.5 | K103: Pre-implementation | L103: Site Permit | M103: Datalink | N103: 308 | O103: 114 | P103: 0.3701 | Q103: DC
A104: DC-Document_Controller-004 | B104: =Master_Data_Productivity[[#This Row],[Uniq-ID]]&"-"&Master_Data_Productivity[[#This Row],[Period]] -> DC-Document_Controller-004-M4 | C104: Hyang Iman Kinasih Gusti wx1503650 | D104: IOH | E104: M4 | F104: 2026-06-23 - 2026-07-22 | G104: Ended | H104: Excellent | I104: 10.455 | J104: 1.5 | K104: Pre-implementation | L104: Site Permit | M104: Datalink | N104: 26 | O104: 114 | P104: 4.3846 | Q104: DC
A105: DC-Document_Controller-004 | B105: =Master_Data_Productivity[[#This Row],[Uniq-ID]]&"-"&Master_Data_Productivity[[#This Row],[Period]] -> DC-Document_Controller-004-M4 | C105: Hyang Iman Kinasih Gusti wx1503650 | D105: IOH | E105: M4 | F105: 2026-06-23 - 2026-07-22 | G105: Ended | H105: Excellent | I105: 10.455 | J105: 1.5 | K105: Pre-implementation | L105: Site Permit | M105: Datalink | N105: 20 | O105: 114 | P105: 5.7 | Q105: DC
... A108: DC-Document_Controller-004 | B108: =Master_Data_Productivity[[#This Row],[Uniq-ID]]&"-"&Master_Data_Productivity[[#This Row],[Period]] -> DC-Document_Controller-004-M5 | C108: Hyang Iman Kinasih Gusti wx1503650 | D108: IOH | E108: M5 | F108: 2026-07-23 - 2026-08-22 | G108: Ended | H108: Excellent | I108: 9.171 | J108: 1.5 | K108: Pre-implementation | L108: Site Permit | M108: Datalink | N108: 308 | O108: 100 | P108: 0.3247 | Q108: DC
A109: DC-Document_Controller-004 | B109: =Master_Data_Productivity[[#This Row],[Uniq-ID]]&"-"&Master_Data_Productivity[[#This Row],[Period]] -> DC-Document_Controller-004-M6 | C109: Hyang Iman Kinasih Gusti wx1503650 | D109: IOH | E109: M6 | F109: 2026-08-23 - 2026-09-22 | G109: Ongoing | H109: Poor | I109: 0 | Q109: DC
A110: DC-Document_Controller-064 | B110: =Master_Data_Productivity[[#This Row],[Uniq-ID]]&"-"&Master_Data_Productivity[[#This Row],[Period]] -> DC-Document_Controller-064-M1 | C110: Suhendar wx1533628 | D110: XLSMART | E110: M1 | F110: 2026-07-07 - 2026-08-06 | G110: Ended | H110: Excellent | I110: 49.5 | J110: 1.5 | K110: Acceptance | L110: IPS Submit | M110: Datalink | N110: 4 | O110: 198 | P110: 49.5 | Q110: DC
A111: DC-Document_Controller-064 | B111: =Master_Data_Productivity[[#This Row],[Uniq-ID]]&"-"&Master_Data_Productivity[[#This Row],[Period]] -> DC-Document_Controller-064-M2 | C111: Suhendar wx1533628 | D111: XLSMART | E111: M2 | F111: 2026-08-07 - 2026-09-06 | G111: Ended | H111: Poor | I111: 0 | Q111: DC
A112: DC-Document_Controller-064 | B112: =Master_Data_Productivity[[#This Row],[Uniq-ID]]&"-"&Master_Data_Productivity[[#This Row],[Period]] -> DC-Document_Controller-064-M3 | C112: Suhendar wx1533628 | D112: XLSMART | E112: M3 | F112: 2026-09-07 - 2026-10-06 | G112: Ongoing | H112: Poor | I112: 0 | Q112: DC
A113: DC-Document_Controller-058 | B113: =Master_Data_Productivity[[#This Row],[Uniq-ID]]&"-"&Master_Data_Productivity[[#This Row],[Period]] -> DC-Document_Controller-058-M1 | C113: Nancy Febrila Eko wx1524066 | D113: TELKOMSEL | E113: M1 | F113: 2026-06-02 - 2026-07-01 | G113: Ended | H113: Excellent | I113: 3.648 | J113: 1.5 | K113: Pre-implementation | L113: CAF Application | M113: ISDP | N113: 26 | O113: 2 | P113: 0.0769 | Q113: DC
A114: DC-Document_Controller-058 | B114: =Master_Data_Productivity[[#This Row],[Uniq-ID]]&"-"&Master_Data_Productivity[[#This Row],[Period]] -> DC-Document_Controller-058-M1 | C114: Nancy Febrila Eko wx1524066 | D114: TELKOMSEL | E114: M1 | F114: 2026-06-02 - 2026-07-01 | G114: Ended | H114: Excellent | I114: 3.648 | J114: 1.5 | K114: Implementation | L114: Tagging Dismantle Material | M114: ISDP | N114: 35 | O114: 20 | P114: 0.5714 | Q114: DC
A115: DC-Document_Controller-058 | B115: =Master_Data_Productivity[[#This Row],[Uniq-ID]]&"-"&Master_Data_Productivity[[#This Row],[Period]] -> DC-Document_Controller-058-M1 | C115: Nancy Febrila Eko wx1524066 | D115: TELKOMSEL | E115: M1 | F115: 2026-06-02 - 2026-07-01 | G115: Ended | H115: Excellent | I115: 3.648 | J115: 1.5 | K115: Implementation | L115: M-08 Dismantle | M115: ISDP | N115: 36 | O115: 108 | P115: 3 | Q115: DC
A116: DC-Document_Controller-058 | B116: =Master_Data_Productivity[[#This Row],[Uniq-ID]]&"-"&Master_Data_Productivity[[#This Row],[Period]] -> DC-Document_Controller-058-M2 | C116: Nancy Febrila Eko wx1524066 | D116: TELKOMSEL | E116: M2 | F116: 2026-07-02 - 2026-08-01 | G116: Ended | H116: Excellent | I116: 3.575 | J116: 1.5 | K116: Implementation | L116: Tagging Dismantle Material | M116: ISDP | N116: 35 | O116: 24 | P116: 0.6857 | Q116: DC
A117: DC-Document_Controller-058 | B117: =Master_Data_Productivity[[#This Row],[Uniq-ID]]&"-"&Master_Data_Productivity[[#This Row],[Period]] -> DC-Document_Controller-058-M2 | C117: Nancy Febrila Eko wx1524066 | D117: TELKOMSEL | E117: M2 | F117: 2026-07-02 - 2026-08-01 | G117: Ended | H117: Excellent | I117: 3.575 | J117: 1.5 | K117: Implementation | L117: M-08 Dismantle | M117: ISDP | N117: 36 | O117: 104 | P117: 2.8889 | Q117: DC
A118: DC-Document_Controller-058 | B118: =Master_Data_Productivity[[#This Row],[Uniq-ID]]&"-"&Master_Data_Productivity[[#This Row],[Period]] -> DC-Document_Controller-058-M3 | C118: Nancy Febrila Eko wx1524066 | D118: TELKOMSEL | E118: M3 | F118: 2026-08-02 - 2026-09-01 | G118: Ended | H118: Normal | I118: 1.837 | J118: 1 | K118: Implementation | L118: Tagging Dismantle Material | M118: ISDP | N118: 35 | O118: 4 | P118: 0.1143 | Q118: DC
A119: DC-Document_Controller-058 | B119: =Master_Data_Productivity[[#This Row],[Uniq-ID]]&"-"&Master_Data_Productivity[[#This Row],[Period]] -> DC-Document_Controller-058-M3 | C119: Nancy Febrila Eko wx1524066 | D119: TELKOMSEL | E119: M3 | F119: 2026-08-02 - 2026-09-01 | G119: Ended | H119: Normal | I119: 1.837 | J119: 1 | K119: Implementation | L119: M-08 Dismantle | M119: ISDP | N119: 36 | O119: 62 | P119: 1.7222 | Q119: DC
A120: DC-Document_Controller-058 | B120: =Master_Data_Productivity[[#This Row],[Uniq-ID]]&"-"&Master_Data_Productivity[[#This Row],[Period]] -> DC-Document_Controller-058-M4 | C120: Nancy Febrila Eko wx1524066 | D120: TELKOMSEL | E120: M4 | F120: 2026-09-02 - 2026-10-01 | G120: Ongoing | H120: Poor | I120: 0.251 | J120: 0.5 | K120: Implementation | L120: Tagging Dismantle Material | M120: ISDP | N120: 35 | O120: 1 | P120: 0.0286 | Q120: DC
A121: DC-Document_Controller-058 | B121: =Master_Data_Productivity[[#This Row],[Uniq-ID]]&"-"&Master_Data_Productivity[[#This Row],[Period]] -> DC-Document_Controller-058-M4 | C121: Nancy Febrila Eko wx1524066 | D121: TELKOMSEL | E121: M4 | F121: 2026-09-02 - 2026-10-01 | G121: Ongoing | H121: Poor | I121: 0.251 | J121: 0.5 | K121: Implementation | L121: M-08 Dismantle | M121: ISDP | N121: 36 | O121: 8 | P121: 0.2222 | Q121: DC
A122: DC-Document_Controller-054 | B122: =Master_Data_Productivity[[#This Row],[Uniq-ID]]&"-"&Master_Data_Productivity[[#This Row],[Period]] -> DC-Document_Controller-054-M1 | C122: Dwi Nofianti wx1524844 | D122: IOH | E122: M1 | F122: 2026-06-03 - 2026-07-02 | G122: Ended | H122: Excellent | I122: 10.088 | J122: 1.5 | K122: Pre-implementation | L122: Site Permit | M122: Datalink | O122: 110 | Q122: DC
A123: DC-Document_Controller-054 | B123: =Master_Data_Productivity[[#This Row],[Uniq-ID]]&"-"&Master_Data_Productivity[[#This Row],[Period]] -> DC-Document_Controller-054-M1 | C123: Dwi Nofianti wx1524844 | D123: IOH | E123: M1 | F123: 2026-06-03 - 2026-07-02 | G123: Ended | H123: Excellent | I123: 10.088 | J123: 1.5 | K123: Pre-implementation | L123: Site Permit | M123: Datalink | N123: 308 | O123: 110 | P123: 0.3571 | Q123: DC
A124: DC-Document_Controller-054 | B124: =Master_Data_Productivity[[#This Row],[Uniq-ID]]&"-"&Master_Data_Productivity[[#This Row],[Period]] -> DC-Document_Controller-054-M1 | C124: Dwi Nofianti wx1524844 | D124: IOH | E124: M1 | F124: 2026-06-03 - 2026-07-02 | G124: Ended | H124: Excellent | I124: 10.088 | J124: 1.5 | K124: Pre-implementation | L124: Site Permit | M124: Datalink | N124: 26 | O124: 110 | P124: 4.2308 | Q124: DC
A125: DC-Document_Controller-054 | B125: =Master_Data_Productivity[[#This Row],[Uniq-ID]]&"-"&Master_Data_Productivity[[#This Row],[Period]] -> DC-Document_Controller-054-M1 | C125: Dwi Nofianti wx1524844 | D125: IOH | E125: M1 | F125: 2026-06-03 - 2026-07-02 | G125: Ended | H125: Excellent | I125: 10.088 | J125: 1.5 | K125: Pre-implementation | L125: Site Permit | M125: Datalink | N125: 20 | O125: 110 | P125: 5.5 | Q125: DC
A126: DC-Document_Controller-054 | B126: =Master_Data_Productivity[[#This Row],[Uniq-ID]]&"-"&Master_Data_Productivity[[#This Row],[Period]] -> DC-Document_Controller-054-M2 | C126: Dwi Nofianti wx1524844 | D126: IOH | E126: M2 | F126: 2026-07-03 - 2026-08-02 | G126: Ended | H126: Excellent | I126: 13.756 | J126: 1.5 | K126: Pre-implementation | L126: Site Permit | M126: Datalink | N126: 308 | O126: 150 | P126: 0.487 | Q126: DC
A127: DC-Document_Controller-054 | B127: =Master_Data_Productivity[[#This Row],[Uniq-ID]]&"-"&Master_Data_Productivity[[#This Row],[Period]] -> DC-Document_Controller-054-M2 | C127: Dwi Nofianti wx1524844 | D127: IOH | E127: M2 | F127: 2026-07-03 - 2026-08-02 | G127: Ended | H127: Excellent | I127: 13.756 | J127: 1.5 | K127: Pre-implementation | L127: Site Permit | M127: Datalink | N127: 26 | O127: 150 | P127: 5.7692 | Q127: DC
A128: DC-Document_Controller-054 | B128: =Master_Data_Productivity[[#This Row],[Uniq-ID]]&"-"&Master_Data_Productivity[[#This Row],[Period]] -> DC-Document_Controller-054-M2 | C128: Dwi Nofianti wx1524844 | D128: IOH | E128: M2 | F128: 2026-07-03 - 2026-08-02 | G128: Ended | H128: Excellent | I128: 13.756 | J128: 1.5 | K128: Pre-implementation | L128: Site Permit | M128: Datalink | N128: 20 | O128: 150 | P128: 7.5 | Q128: DC
A129: DC-Document_Controller-054 | B129: =Master_Data_Productivity[[#This Row],[Uniq-ID]]&"-"&Master_Data_Productivity[[#This Row],[Period]] -> DC-Document_Controller-054-M3 | C129: Dwi Nofianti wx1524844 | D129: IOH | E129: M3 | F129: 2026-08-03 - 2026-09-02 | G129: Ended | H129: Excellent | I129: 4.585 | J129: 1.5 | K129: Pre-implementation | L129: Site Permit | M129: Datalink | N129: 308 | O129: 50 | P129: 0.1623 | Q129: DC
A130: DC-Document_Controller-054 | B130: =Master_Data_Productivity[[#This Row],[Uniq-ID]]&"-"&Master_Data_Productivity[[#This Row],[Period]] -> DC-Document_Controller-054-M3 | C130: Dwi Nofianti wx1524844 | D130: IOH | E130: M3 | F130: 2026-08-03 - 2026-09-02 | G130: Ended | H130: Excellent | I130: 4.585 | J130: 1.5 | K130: Pre-implementation | L130: Site Permit | M130: Datalink | N130: 26 | O130: 50 | P130: 1.9231 | Q130: DC
A131: DC-Document_Controller-054 | B131: =Master_Data_Productivity[[#This Row],[Uniq-ID]]&"-"&Master_Data_Productivity[[#This Row],[Period]] -> DC-Document_Controller-054-M3 | C131: Dwi Nofianti wx1524844 | D131: IOH | E131: M3 | F131: 2026-08-03 - 2026-09-02 | G131: Ended | H131: Excellent | I131: 4.585 | J131: 1.5 | K131: Pre-implementation | L131: Site Permit | M131: Datalink | N131: 20 | O131: 50 | P131: 2.5 | Q131: DC
A132: DC-Document_Controller-054 | B132: =Master_Data_Productivity[[#This Row],[Uniq-ID]]&"-"&Master_Data_Productivity[[#This Row],[Period]] -> DC-Document_Controller-054-M4 | C132: Dwi Nofianti wx1524844 | D132: IOH | E132: M4 | F132: 2026-09-03 - 2026-10-02 | G132: Ongoing | H132: Poor | I132: 0 | Q132: DC
A133: DC-Document_Controller-049 | B133: =Master_Data_Productivity[[#This Row],[Uniq-ID]]&"-"&Master_Data_Productivity[[#This Row],[Period]] -> DC-Document_Controller-049-M1 | C133: Akmal wx1524119 | D133: XLSMART | E133: M1 | F133: 2026-06-02 - 2026-07-01 | G133: Ended | H133: Excellent | I133: 8.62 | J133: 1.5 | K133: Pre-Implementation | L133: Survey - TSSR | M133: ISDP | N133: 110 | O133: 33 | P133: 0.3 | Q133: DC
A134: DC-Document_Controller-049 | B134: =Master_Data_Productivity[[#This Row],[Uniq-ID]]&"-"&Master_Data_Productivity[[#This Row],[Period]] -> DC-Document_Controller-049-M1 | C134: Akmal wx1524119 | D134: XLSMART | E134: M1 | F134: 2026-06-02 - 2026-07-01 | G134: Ended | H134: Excellent | I134: 8.62 | J134: 1.5 | K134: Implementation | L134: PLN Termination | M134: ISDP | N134: 88 | O134: 163 | P134: 1.8523 | Q134: DC
...

Sheet Master Data 14-9-2026
A1: Role | B1: Uniq-ID | C1: Column1 | D1: Name ID | E1: Account | F1: Region | G1: Period | H1: Period Date | I1: Period Status | J1: Productivity Range | K1: Productivity | L1: Payment Coef. | M1: Total % Ach. | N1: Document Category | O1: Document Type | P1: Source Data | Q1: Baseline/Cycle | R1: Total Doc. | S1: % Achievement | T1: QEHS Inspection (ONSITE) | U1: Compliance Check (TL) | V1: Training (Class) | W1: Baseline | X1: Achievement | Y1: Onsite Clock-In | Z1: M-06 Integrated | AA1: M-04 MOS (20%) | AB1: M-05 Installation (30%) | AC1: On Air (20%) | AD1: ATP Submit (20%) | AE1: ATP Approve (20%) | AF1: Total Score
A2: DC | B2: DC-Document_Controller-001 | C2: =Data_Master[[#This Row],[Uniq-ID]]&"-"&Data_Master[[#This Row],[Period]] -> DC-Document_Controller-001-M1 | D2: Sri Hardianti Purnamasari wx1503627 | E2: TELKOMSEL | G2: M1 | H2: 2026-03-23 - 2026-04-22 | I2: Ended | J2: Excellent | L2: 1.05 | M2: 2.109 | N2: Implementation | O2: Tagging Dismantle Material | P2: ISDP | Q2: 35 | R2: 28 | S2: 0.8
A3: DC | B3: DC-Document_Controller-001 | C3: =Data_Master[[#This Row],[Uniq-ID]]&"-"&Data_Master[[#This Row],[Period]] -> DC-Document_Controller-001-M1 | D3: Sri Hardianti Purnamasari wx1503627 | E3: TELKOMSEL | G3: M1 | H3: 2026-03-23 - 2026-04-22 | I3: Ended | J3: Excellent | L3: 1.05 | M3: 2.109 | N3: Implementation | O3: Tagging Installation | P3: ISDP | Q3: 32 | R3: 41 | S3: 1.2813
A4: DC | B4: DC-Document_Controller-001 | C4: =Data_Master[[#This Row],[Uniq-ID]]&"-"&Data_Master[[#This Row],[Period]] -> DC-Document_Controller-001-M1 | D4: Sri Hardianti Purnamasari wx1503627 | E4: TELKOMSEL | G4: M1 | H4: 2026-03-23 - 2026-04-22 | I4: Ended | J4: Excellent | L4: 1.05 | M4: 2.109 | N4: Implementation | O4: M-08 Dismantle | P4: ISDP | Q4: 36 | R4: 1 | S4: 0.0278
A5: DC | B5: DC-Document_Controller-001 | C5: =Data_Master[[#This Row],[Uniq-ID]]&"-"&Data_Master[[#This Row],[Period]] -> DC-Document_Controller-001-M2 | D5: Sri Hardianti Purnamasari wx1503627 | E5: TELKOMSEL | G5: M2 | H5: 2026-04-23 - 2026-05-22 | I5: Ended | J5: Excellent | L5: 1.09 | M5: 2.179 | N5: Implementation | O5: M-08 Dismantle | P5: ISDP | Q5: 36 | R5: 12 | S5: 0.3333
A6: DC | B6: DC-Document_Controller-001 | C6: =Data_Master[[#This Row],[Uniq-ID]]&"-"&Data_Master[[#This Row],[Period]] -> DC-Document_Controller-001-M2 | D6: Sri Hardianti Purnamasari wx1503627 | E6: TELKOMSEL | G6: M2 | H6: 2026-04-23 - 2026-05-22 | I6: Ended | J6: Excellent | L6: 1.09 | M6: 2.179 | N6: Implementation | O6: Tagging Dismantle Material | P6: ISDP | Q6: 35 | R6: 18 | S6: 0.5143
A7: DC | B7: DC-Document_Controller-001 | C7: =Data_Master[[#This Row],[Uniq-ID]]&"-"&Data_Master[[#This Row],[Period]] -> DC-Document_Controller-001-M2 | D7: Sri Hardianti Purnamasari wx1503627 | E7: TELKOMSEL | G7: M2 | H7: 2026-04-23 - 2026-05-22 | I7: Ended | J7: Excellent | L7: 1.09 | M7: 2.179 | N7: Implementation | O7: Tagging Installation | P7: ISDP | Q7: 32 | R7: 18 | S7: 0.5625
A8: DC | B8: DC-Document_Controller-001 | C8: =Data_Master[[#This Row],[Uniq-ID]]&"-"&Data_Master[[#This Row],[Period]] -> DC-Document_Controller-001-M2 | D8: Sri Hardianti Purnamasari wx1503627 | E8: TELKOMSEL | G8: M2 | H8: 2026-04-23 - 2026-05-22 | I8: Ended | J8: Excellent | L8: 1.09 | M8: 2.179 | N8: Pre-implementation | O8: CAF Application | P8: ISDP | Q8: 26 | R8: 20 | S8: 0.7692
A9: DC | B9: DC-Document_Controller-001 | C9: =Data_Master[[#This Row],[Uniq-ID]]&"-"&Data_Master[[#This Row],[Period]] -> DC-Document_Controller-001-M3 | D9: Sri Hardianti Purnamasari wx1503627 | E9: TELKOMSEL | G9: M3 | H9: 2026-05-23 - 2026-06-22 | I9: Ended | J9: Normal | L9: 1 | M9: 1.888 | N9: Implementation | O9: Tagging Installation | P9: ISDP | Q9: 32 | R9: 44 | S9: 1.375
A10: DC | B10: DC-Document_Controller-001 | C10: =Data_Master[[#This Row],[Uniq-ID]]&"-"&Data_Master[[#This Row],[Period]] -> DC-Document_Controller-001-M3 | D10: Sri Hardianti Purnamasari wx1503627 | E10: TELKOMSEL | G10: M3 | H10: 2026-05-23 - 2026-06-22 | I10: Ended | J10: Normal | L10: 1 | M10: 1.888 | N10: Implementation | O10: Tagging Dismantle Material | P10: ISDP | Q10: 35 | R10: 16 | S10: 0.4571
A11: DC | B11: DC-Document_Controller-001 | C11: =Data_Master[[#This Row],[Uniq-ID]]&"-"&Data_Master[[#This Row],[Period]] -> DC-Document_Controller-001-M3 | D11: Sri Hardianti Purnamasari wx1503627 | E11: TELKOMSEL | G11: M3 | H11: 2026-05-23 - 2026-06-22 | I11: Ended | J11: Normal | L11: 1 | M11: 1.888 | N11: Implementation | O11: M-08 Dismantle | P11: ISDP | Q11: 36 | R11: 2 | S11: 0.0556
A12: DC | B12: DC-Document_Controller-001 | C12: =Data_Master[[#This Row],[Uniq-ID]]&"-"&Data_Master[[#This Row],[Period]] -> DC-Document_Controller-001-M4 | D12: Sri Hardianti Purnamasari wx1503627 | E12: TELKOMSEL | G12: M4 | H12: 2026-06-23 - 2026-07-22 | I12: Ended | J12: Excellent | L12: 1.5 | M12: 3.856 | N12: Implementation | O12: Tagging Installation | P12: ISDP | Q12: 32 | R12: 32 | S12: 1
A13: DC | B13: DC-Document_Controller-001 | C13: =Data_Master[[#This Row],[Uniq-ID]]&"-"&Data_Master[[#This Row],[Period]] -> DC-Document_Controller-001-M4 | D13: Sri Hardianti Purnamasari wx1503627 | E13: TELKOMSEL | G13: M4 | H13: 2026-06-23 - 2026-07-22 | I13: Ended | J13: Excellent | L13: 1.5 | M13: 3.856 | N13: Implementation | O13: M-08 Dismantle | P13: ISDP | Q13: 36 | R13: 38 | S13: 1.0556
... A19: DC | B19: DC-Document_Controller-001 | C19: =Data_Master[[#This Row],[Uniq-ID]]&"-"&Data_Master[[#This Row],[Period]] -> DC-Document_Controller-001-M6 | D19: Sri Hardianti Purnamasari wx1503627 | E19: TELKOMSEL | G19: M6 | H19: 2026-08-23 - 2026-09-22 | I19: Ongoing | J19: Poor | L19: 0.53 | M19: 0.535 | N19: Implementation | O19: Tagging Dismantle Material | P19: ISDP | Q19: 35 | R19: 9 | S19: 0.2571
A20: DC | B20: DC-Document_Controller-002 | C20: =Data_Master[[#This Row],[Uniq-ID]]&"-"&Data_Master[[#This Row],[Period]] -> DC-Document_Controller-002-M1 | D20: Rifan Azkia wx1504665 | E20: XLSMART | G20: M1 | H20: 2026-03-23 - 2026-04-22 | I20: Ended | J20: Poor | M20: 0
A21: DC | B21: DC-Document_Controller-002 | C21: =Data_Master[[#This Row],[Uniq-ID]]&"-"&Data_Master[[#This Row],[Period]] -> DC-Document_Controller-002-M2 | D21: Rifan Azkia wx1504665 | E21: XLSMART | G21: M2 | H21: 2026-04-23 - 2026-05-22 | I21: Ended | J21: Poor | M21: 0
A22: DC | B22: DC-Document_Controller-002 | C22: =Data_Master[[#This Row],[Uniq-ID]]&"-"&Data_Master[[#This Row],[Period]] -> DC-Document_Controller-002-M3 | D22: Rifan Azkia wx1504665 | E22: XLSMART | G22: M3 | H22: 2026-05-23 - 2026-06-22 | I22: Ended | J22: Poor | M22: 0
A23: DC | B23: DC-Document_Controller-002 | C23: =Data_Master[[#This Row],[Uniq-ID]]&"-"&Data_Master[[#This Row],[Period]] -> DC-Document_Controller-002-M4 | D23: Rifan Azkia wx1504665 | E23: XLSMART | G23: M4 | H23: 2026-06-23 - 2026-07-22 | I23: Ended | J23: Poor | L23: 0.5 | M23: 0.015 | N23: Implementation | O23: PLN Upgrade | P23: ISDP | Q23: 66 | R23: 1 | S23: 0.0152
A24: DC | B24: DC-Document_Controller-002 | C24: =Data_Master[[#This Row],[Uniq-ID]]&"-"&Data_Master[[#This Row],[Period]] -> DC-Document_Controller-002-M5 | D24: Rifan Azkia wx1504665 | E24: XLSMART | G24: M5 | H24: 2026-07-23 - 2026-08-22 | I24: Ended | J24: Poor | M24: 0
A25: DC | B25: DC-Document_Controller-002 | C25: =Data_Master[[#This Row],[Uniq-ID]]&"-"&Data_Master[[#This Row],[Period]] -> DC-Document_Controller-002-M6 | D25: Rifan Azkia wx1504665 | E25: XLSMART | G25: M6 | H25: 2026-08-23 - 2026-09-22 | I25: Ongoing | J25: Poor | L25: 0.5 | M25: 0.005 | N25: Implementation | O25: Dismantle Inbound | P25: ISDP | Q25: 220 | R25: 1 | S25: 0.0045
A26: DC | B26: DC-Document_Controller-003 | C26: =Data_Master[[#This Row],[Uniq-ID]]&"-"&Data_Master[[#This Row],[Period]] -> DC-Document_Controller-003-M1 | D26: Gigih Dharma Sulistya wx1503511 | E26: TELKOMSEL | G26: M1 | H26: 2026-03-23 - 2026-04-22 | I26: Ended | J26: Normal | L26: 1 | M26: 1.744 | N26: Implementation | O26: M-08 Dismantle | P26: ISDP | Q26: 36 | R26: 35 | S26: 0.9722
A27: DC | B27: DC-Document_Controller-003 | C27: =Data_Master[[#This Row],[Uniq-ID]]&"-"&Data_Master[[#This Row],[Period]] -> DC-Document_Controller-003-M1 | D27: Gigih Dharma Sulistya wx1503511 | E27: TELKOMSEL | G27: M1 | H27: 2026-03-23 - 2026-04-22 | I27: Ended | J27: Normal | L27: 1 | M27: 1.744 | N27: Implementation | O27: Tagging Dismantle Material | P27: ISDP | Q27: 35 | R27: 27 | S27: 0.7714
A28: DC | B28: DC-Document_Controller-003 | C28: =Data_Master[[#This Row],[Uniq-ID]]&"-"&Data_Master[[#This Row],[Period]] -> DC-Document_Controller-003-M2 | D28: Gigih Dharma Sulistya wx1503511 | E28: TELKOMSEL | G28: M2 | H28: 2026-04-23 - 2026-05-22 | I28: Ended | J28: Normal | L28: 1 | M28: 1.864 | N28: Implementation | O28: M-08 Dismantle | P28: ISDP | Q28: 36 | R28: 27 | S28: 0.75
A29: DC | B29: DC-Document_Controller-003 | C29: =Data_Master[[#This Row],[Uniq-ID]]&"-"&Data_Master[[#This Row],[Period]] -> DC-Document_Controller-003-M2 | D29: Gigih Dharma Sulistya wx1503511 | E29: TELKOMSEL | G29: M2 | H29: 2026-04-23 - 2026-05-22 | I29: Ended | J29: Normal | L29: 1 | M29: 1.864 | N29: Implementation | O29: Tagging Dismantle Material | P29: ISDP | Q29: 35 | R29: 39 | S29: 1.1143
A30: DC | B30: DC-Document_Controller-003 | C30: =Data_Master[[#This Row],[Uniq-ID]]&"-"&Data_Master[[#This Row],[Period]] -> DC-Document_Controller-003-M3 | D30: Gigih Dharma Sulistya wx1503511 | E30: TELKOMSEL | G30: M3 | H30: 2026-05-23 - 2026-06-22 | I30: Ended | J30: Excellent | L30: 1.5 | M30: 4.173 | N30: Implementation | O30: M-08 Dismantle | P30: ISDP | Q30: 36 | R30: 71 | S30: 1.9722
A31: DC | B31: DC-Document_Controller-003 | C31: =Data_Master[[#This Row],[Uniq-ID]]&"-"&Data_Master[[#This Row],[Period]] -> DC-Document_Controller-003-M3 | D31: Gigih Dharma Sulistya wx1503511 | E31: TELKOMSEL | G31: M3 | H31: 2026-05-23 - 2026-06-22 | I31: Ended | J31: Excellent | L31: 1.5 | M31: 4.173 | N31: Implementation | O31: Tagging Dismantle Material | P31: ISDP | Q31: 35 | R31: 73 | S31: 2.0857
A32: DC | B32: DC-Document_Controller-003 | C32: =Data_Master[[#This Row],[Uniq-ID]]&"-"&Data_Master[[#This Row],[Period]] -> DC-Document_Controller-003-M3 | D32: Gigih Dharma Sulistya wx1503511 | E32: TELKOMSEL | G32: M3 | H32: 2026-05-23 - 2026-06-22 | I32: Ended | J32: Excellent | L32: 1.5 | M32: 4.173 | N32: Pre-implementation | O32: CAF Application | P32: ISDP | Q32: 26 | R32: 3 | S32: 0.1154
A33: DC | B33: DC-Document_Controller-003 | C33: =Data_Master[[#This Row],[Uniq-ID]]&"-"&Data_Master[[#This Row],[Period]] -> DC-Document_Controller-003-M4 | D33: Gigih Dharma Sulistya wx1503511 | E33: TELKOMSEL | G33: M4 | H33: 2026-06-23 - 2026-07-22 | I33: Ended | J33: Excellent | L33: 1.5 | M33: 4.171 | N33: Implementation | O33: M-08 Dismantle | P33: ISDP | Q33: 36 | R33: 48 | S33: 1.3333
A34: DC | B34: DC-Document_Controller-003 | C34: =Data_Master[[#This Row],[Uniq-ID]]&"-"&Data_Master[[#This Row],[Period]] -> DC-Document_Controller-003-M4 | D34: Gigih Dharma Sulistya wx1503511 | E34: TELKOMSEL | G34: M4 | H34: 2026-06-23 - 2026-07-22 | I34: Ended | J34: Excellent | L34: 1.5 | M34: 4.171 | N34: Implementation | O34: Tagging Dismantle Material | P34: ISDP | Q34: 35 | R34: 32 | S34: 0.9143
A35: DC | B35: DC-Document_Controller-003 | C35: =Data_Master[[#This Row],[Uniq-ID]]&"-"&Data_Master[[#This Row],[Period]] -> DC-Document_Controller-003-M4 | D35: Gigih Dharma Sulistya wx1503511 | E35: TELKOMSEL | G35: M4 | H35: 2026-06-23 - 2026-07-22 | I35: Ended | J35: Excellent | L35: 1.5 | M35: 4.171 | N35: Pre-implementation | O35: CAF Application | P35: ISDP | Q35: 26 | R35: 50 | S35: 1.9231
A36: DC | B36: DC-Document_Controller-003 | C36: =Data_Master[[#This Row],[Uniq-ID]]&"-"&Data_Master[[#This Row],[Period]] -> DC-Document_Controller-003-M5 | D36: Gigih Dharma Sulistya wx1503511 | E36: TELKOMSEL | G36: M5 | H36: 2026-07-23 - 2026-08-22 | I36: Ended | J36: Excellent | L36: 1.5 | M36: 3.606 | N36: Implementation | O36: Tagging Dismantle Material | P36: ISDP | Q36: 35 | R36: 64 | S36: 1.8286
... A54: DC | B54: DC-Document_Controller-004 | C54: =Data_Master[[#This Row],[Uniq-ID]]&"-"&Data_Master[[#This Row],[Period]] -> DC-Document_Controller-004-M5 | D54: Hyang Iman Kinasih Gusti wx1503650 | E54: IOH | G54: M5 | H54: 2026-07-23 - 2026-08-22 | I54: Ended | J54: Excellent | L54: 1.5 | M54: 9.171 | N54: Pre-implementation | O54: Site Permit | P54: Datalink | Q54: 20 | R54: 100 | S54: 5
A55: DC | B55: DC-Document_Controller-004 | C55: =Data_Master[[#This Row],[Uniq-ID]]&"-"&Data_Master[[#This Row],[Period]] -> DC-Document_Controller-004-M6 | D55: Hyang Iman Kinasih Gusti wx1503650 | E55: IOH | G55: M6 | H55: 2026-08-23 - 2026-09-22 | I55: Ongoing | J55: Poor | M55: 0
A56: DC | B56: DC-Document_Controller-005 | C56: =Data_Master[[#This Row],[Uniq-ID]]&"-"&Data_Master[[#This Row],[Period]] -> DC-Document_Controller-005-M1 | D56: F Albert Jacob wx1504717 | E56: TELKOMSEL | G56: M1 | H56: 2026-03-23 - 2026-04-22 | I56: Ended | J56: Normal | L56: 1 | M56: 1.525 | N56: Implementation | O56: M-08 Dismantle | P56: ISDP | Q56: 36 | R56: 2 | S56: 0.0556
A57: DC | B57: DC-Document_Controller-005 | C57: =Data_Master[[#This Row],[Uniq-ID]]&"-"&Data_Master[[#This Row],[Period]] -> DC-Document_Controller-005-M1 | D57: F Albert Jacob wx1504717 | E57: TELKOMSEL | G57: M1 | H57: 2026-03-23 - 2026-04-22 | I57: Ended | J57: Normal | L57: 1 | M57: 1.525 | N57: Implementation | O57: Tagging Dismantle Material | P57: ISDP | Q57: 35 | R57: 7 | S57: 0.2
A58: DC | B58: DC-Document_Controller-005 | C58: =Data_Master[[#This Row],[Uniq-ID]]&"-"&Data_Master[[#This Row],[Period]] -> DC-Document_Controller-005-M1 | D58: F Albert Jacob wx1504717 | E58: TELKOMSEL | G58: M1 | H58: 2026-03-23 - 2026-04-22 | I58: Ended | J58: Normal | L58: 1 | M58: 1.525 | N58: Pre-implementation | O58: CAF Application | P58: ISDP | Q58: 26 | R58: 33 | S58: 1.2692
A59: DC | B59: DC-Document_Controller-005 | C59: =Data_Master[[#This Row],[Uniq-ID]]&"-"&Data_Master[[#This Row],[Period]] -> DC-Document_Controller-005-M2 | D59: F Albert Jacob wx1504717 | E59: TELKOMSEL | G59: M2 | H59: 2026-04-23 - 2026-05-22 | I59: Ended | J59: Excellent | L59: 1.28 | M59: 2.551 | N59: Implementation | O59: M-08 Dismantle | P59: ISDP | Q59: 36 | R59: 5 | S59: 0.1389
A60: DC | B60: DC-Document_Controller-005 | C60: =Data_Master[[#This Row],[Uniq-ID]]&"-"&Data_Master[[#This Row],[Period]] -> DC-Document_Controller-005-M2 | D60: F Albert Jacob wx1504717 | E60: TELKOMSEL | G60: M2 | H60: 2026-04-23 - 2026-05-22 | I60: Ended | J60: Excellent | L60: 1.28 | M60: 2.551 | N60: Implementation | O60: Tagging Dismantle Material | P60: ISDP | Q60: 35 | R60: 5 | S60: 0.1429
A61: DC | B61: DC-Document_Controller-005 | C61: =Data_Master[[#This Row],[Uniq-ID]]&"-"&Data_Master[[#This Row],[Period]] -> DC-Document_Controller-005-M2 | D61: F Albert Jacob wx1504717 | E61: TELKOMSEL | G61: M2 | H61: 2026-04-23 - 2026-05-22 | I61: Ended | J61: Excellent | L61: 1.28 | M61: 2.551 | N61: Pre-implementation | O61: CAF Application | P61: ISDP | Q61: 26 | R61: 59 | S61: 2.2692
A62: DC | B62: DC-Document_Controller-005 | C62: =Data_Master[[#This Row],[Uniq-ID]]&"-"&Data_Master[[#This Row],[Period]] -> DC-Document_Controller-005-M3 | D62: F Albert Jacob wx1504717 | E62: TELKOMSEL | G62: M3 | H62: 2026-05-23 - 2026-06-22 | I62: Ended | J62: Normal | L62: 1 | M62: 1.23 | N62: Implementation | O62: Tagging Dismantle Material | P62: ISDP | Q62: 35 | R62: 2 | S62: 0.0571
A63: DC | B63: DC-Document_Controller-005 | C63: =Data_Master[[#This Row],[Uniq-ID]]&"-"&Data_Master[[#This Row],[Period]] -> DC-Document_Controller-005-M3 | D63: F Albert Jacob wx1504717 | E63: TELKOMSEL | G63: M3 | H63: 2026-05-23 - 2026-06-22 | I63: Ended | J63: Normal | L63: 1 | M63: 1.23 | N63: Implementation | O63: M-08 Dismantle | P63: ISDP | Q63: 36 | R63: 27 | S63: 0.75
A64: DC | B64: DC-Document_Controller-005 | C64: =Data_Master[[#This Row],[Uniq-ID]]&"-"&Data_Master[[#This Row],[Period]] -> DC-Document_Controller-005-M3 | D64: F Albert Jacob wx1504717 | E64: TELKOMSEL | G64: M3 | H64: 2026-05-23 - 2026-06-22 | I64: Ended | J64: Normal | L64: 1 | M64: 1.23 | N64: Pre-implementation | O64: CAF Application | P64: ISDP | Q64: 26 | R64: 11 | S64: 0.4231
A65: DC | B65: DC-Document_Controller-005 | C65: =Data_Master[[#This Row],[Uniq-ID]]&"-"&Data_Master[[#This Row],[Period]] -> DC-Document_Controller-005-M4 | D65: F Albert Jacob wx1504717 | E65: TELKOMSEL | G65: M4 | H65: 2026-06-23 - 2026-07-22 | I65: Ended | J65: Excellent | L65: 1.5 | M65: 5.126 | N65: Implementation | O65: M-08 Dismantle | P65: ISDP | Q65: 36 | R65: 44 | S65: 1.2222
A66: DC | B66: DC-Document_Controller-005 | C66: =Data_Master[[#This Row],[Uniq-ID]]&"-"&Data_Master[[#This Row],[Period]] -> DC-Document_Controller-005-M4 | D66: F Albert Jacob wx1504717 | E66: TELKOMSEL | G66: M4 | H66: 2026-06-23 - 2026-07-22 | I66: Ended | J66: Excellent | L66: 1.5 | M66: 5.126 | N66: Implementation | O66: Tagging Dismantle Material | P66: ISDP | Q66: 35 | R66: 2 | S66: 0.0571
A67: DC | B67: DC-Document_Controller-005 | C67: =Data_Master[[#This Row],[Uniq-ID]]&"-"&Data_Master[[#This Row],[Period]] -> DC-Document_Controller-005-M4 | D67: F Albert Jacob wx1504717 | E67: TELKOMSEL | G67: M4 | H67: 2026-06-23 - 2026-07-22 | I67: Ended | J67: Excellent | L67: 1.5 | M67: 5.126 | N67: Pre-implementation | O67: CAF Application | P67: ISDP | Q67: 26 | R67: 100 | S67: 3.8462
... A73: DC | B73: DC-Document_Controller-005 | C73: =Data_Master[[#This Row],[Uniq-ID]]&"-"&Data_Master[[#This Row],[Period]] -> DC-Document_Controller-005-M6 | D73: F Albert Jacob wx1504717 | E73: TELKOMSEL | G73: M6 | H73: 2026-08-23 - 2026-09-22 | I73: Ongoing | J73: Normal | L73: 1 | M73: 1.395 | N73: Implementation | O73: M-08 Dismantle | P73: ISDP | Q73: 36 | R73: 6 | S73: 0.1667
A74: DC | B74: DC-Document_Controller-006 | C74: =Data_Master[[#This Row],[Uniq-ID]]&"-"&Data_Master[[#This Row],[Period]] -> DC-Document_Controller-006-M1 | D74: Devi Dyah Palupi wx1503645 | E74: IOH | G74: M1 | H74: 2026-03-23 - 2026-04-22 | I74: Ended | J74: Poor | M74: 0
A75: DC | B75: DC-Document_Controller-006 | C75: =Data_Master[[#This Row],[Uniq-ID]]&"-"&Data_Master[[#This Row],[Period]] -> DC-Document_Controller-006-M2 | D75: Devi Dyah Palupi wx1503645 | E75: IOH | G75: M2 | H75: 2026-04-23 - 2026-05-22 | I75: Ended | J75: Poor | M75: 0
A76: DC | B76: DC-Document_Controller-006 | C76: =Data_Master[[#This Row],[Uniq-ID]]&"-"&Data_Master[[#This Row],[Period]] -> DC-Document_Controller-006-M3 | D76: Devi Dyah Palupi wx1503645 | E76: IOH | G76: M3 | H76: 2026-05-23 - 2026-06-22 | I76: Ended | J76: Poor | M76: 0
A77: DC | B77: DC-Document_Controller-006 | C77: =Data_Master[[#This Row],[Uniq-ID]]&"-"&Data_Master[[#This Row],[Period]] -> DC-Document_Controller-006-M4 | D77: Devi Dyah Palupi wx1503645 | E77: IOH | G77: M4 | H77: 2026-06-23 - 2026-07-22 | I77: Ended | J77: Excellent | L77: 1.5 | M77: 12.289 | N77: Pre-implementation | O77: Site Permit | P77: Datalink | Q77: 308 | R77: 134 | S77: 0.4351
A78: DC | B78: DC-Document_Controller-006 | C78: =Data_Master[[#This Row],[Uniq-ID]]&"-"&Data_Master[[#This Row],[Period]] -> DC-Document_Controller-006-M4 | D78: Devi Dyah Palupi wx1503645 | E78: IOH | G78: M4 | H78: 2026-06-23 - 2026-07-22 | I78: Ended | J78: Excellent | L78: 1.5 | M78: 12.289 | N78: Pre-implementation | O78: Site Permit | P78: Datalink | Q78: 26 | R78: 134 | S78: 5.1538
A79: DC | B79: DC-Document_Controller-006 | C79: =Data_Master[[#This Row],[Uniq-ID]]&"-"&Data_Master[[#This Row],[Period]] -> DC-Document_Controller-006-M4 | D79: Devi Dyah Palupi wx1503645 | E79: IOH | G79: M4 | H79: 2026-06-23 - 2026-07-22 | I79: Ended | J79: Excellent | L79: 1.5 | M79: 12.289 | N79: Pre-implementation | O79: Site Permit | P79: Datalink | Q79: 20 | R79: 134 | S79: 6.7
A80: DC | B80: DC-Document_Controller-006 | C80: =Data_Master[[#This Row],[Uniq-ID]]&"-"&Data_Master[[#This Row],[Period]] -> DC-Document_Controller-006-M5 | D80: Devi Dyah Palupi wx1503645 | E80: IOH | G80: M5 | H80: 2026-07-23 - 2026-08-22 | I80: Ended | J80: Excellent | L80: 1.5 | M80: 10.088 | N80: Pre-implementation | O80: Site Permit | P80: Datalink | Q80: 308 | R80: 110 | S80: 0.3571
A81: DC | B81: DC-Document_Controller-006 | C81: =Data_Master[[#This Row],[Uniq-ID]]&"-"&Data_Master[[#This Row],[Period]] -> DC-Document_Controller-006-M5 | D81: Devi Dyah Palupi wx1503645 | E81: IOH | G81: M5 | H81: 2026-07-23 - 2026-08-22 | I81: Ended | J81: Excellent | L81: 1.5 | M81: 10.088 | N81: Pre-implementation | O81: Site Permit | P81: Datalink | Q81: 26 | R81: 110 | S81: 4.2308
A82: DC | B82: DC-Document_Controller-006 | C82: =Data_Master[[#This Row],[Uniq-ID]]&"-"&Data_Master[[#This Row],[Period]] -> DC-Document_Controller-006-M5 | D82: Devi Dyah Palupi wx1503645 | E82: IOH | G82: M5 | H82: 2026-07-23 - 2026-08-22 | I82: Ended | J82: Excellent | L82: 1.5 | M82: 10.088 | N82: Pre-implementation | O82: Site Permit | P82: Datalink | Q82: 20 | R82: 110 | S82: 5.5
A83: DC | B83: DC-Document_Controller-006 | C83: =Data_Master[[#This Row],[Uniq-ID]]&"-"&Data_Master[[#This Row],[Period]] -> DC-Document_Controller-006-M6 | D83: Devi Dyah Palupi wx1503645 | E83: IOH | G83: M6 | H83: 2026-08-23 - 2026-09-22 | I83: Ongoing | J83: Poor | M83: 0
A84: DC | B84: DC-Document_Controller-007 | C84: =Data_Master[[#This Row],[Uniq-ID]]&"-"&Data_Master[[#This Row],[Period]] -> DC-Document_Controller-007-M1 | D84: Mauli Rizki Amelia wx1504666 | E84: XLSMART | G84: M1 | H84: 2026-03-26 - 2026-04-25 | I84: Ended | J84: Poor | L84: 0.5 | M84: 0.086 | N84: Implementation | O84: List Dismantle Material | P84: Datalink | Q84: 220 | R84: 19 | S84: 0.0864
A85: DC | B85: DC-Document_Controller-007 | C85: =Data_Master[[#This Row],[Uniq-ID]]&"-"&Data_Master[[#This Row],[Period]] -> DC-Document_Controller-007-M2 | D85: Mauli Rizki Amelia wx1504666 | E85: XLSMART | G85: M2 | H85: 2026-04-26 - 2026-05-25 | I85: Ended | J85: Poor | L85: 0.5 | M85: 0.1 | N85: Implementation | O85: List Dismantle Material | P85: Datalink | Q85: 220 | R85: 22 | S85: 0.1
A86: DC | B86: DC-Document_Controller-007 | C86: =Data_Master[[#This Row],[Uniq-ID]]&"-"&Data_Master[[#This Row],[Period]] -> DC-Document_Controller-007-M3 | D86: Mauli Rizki Amelia wx1504666 | E86: XLSMART | G86: M3 | H86: 2026-05-26 - 2026-06-25 | I86: Ended | J86: Poor | M86: 0
A87: DC | B87: DC-Document_Controller-007 | C87: =Data_Master[[#This Row],[Uniq-ID]]&"-"&Data_Master[[#This Row],[Period]] -> DC-Document_Controller-007-M4 | D87: Mauli Rizki Amelia wx1504666 | E87: XLSMART | G87: M4 | H87: 2026-06-26 - 2026-07-25 | I87: Ended | J87: Poor | M87: 0
A88: DC | B88: DC-Document_Controller-007 | C88: =Data_Master[[#This Row],[Uniq-ID]]&"-"&Data_Master[[#This Row],[Period]] -> DC-Document_Controller-007-M5 | D88: Mauli Rizki Amelia wx1504666 | E88: XLSMART | G88: M5 | H88: 2026-07-26 - 2026-08-25 | I88: Ended | J88: Poor | M88: 0
A89: DC | B89: DC-Document_Controller-007 | C89: =Data_Master[[#This Row],[Uniq-ID]]&"-"&Data_Master[[#This Row],[Period]] -> DC-Document_Controller-007-M6 | D89: Mauli Rizki Amelia wx1504666 | E89: XLSMART | G89: M6 | H89: 2026-08-26 - 2026-09-25 | I89: Ongoing | J89: Poor | M89: 0
A90: DC | B90: DC-Document_Controller-008 | C90: =Data_Master[[#This Row],[Uniq-ID]]&"-"&Data_Master[[#This Row],[Period]] -> DC-Document_Controller-008-M1 | D90: Nurmawaty wx1504714 | E90: XLSMART | G90: M1 | H90: 2026-03-28 - 2026-04-27 | I90: Ended | J90: Excellent | L90: 1.5 | M90: 16.129 | N90: Pre-implementation | O90: PO Mapping | P90: Datalink | Q90: 31 | R90: 500 | S90: 16.129
A91: DC | B91: DC-Document_Controller-008 | C91: =Data_Master[[#This Row],[Uniq-ID]]&"-"&Data_Master[[#This Row],[Period]] -> DC-Document_Controller-008-M2 | D91: Nurmawaty wx1504714 | E91: XLSMART | G91: M2 | H91: 2026-04-28 - 2026-05-27 | I91: Ended | J91: Excellent | L91: 1.5 | M91: 10 | N91: Pre-implementation | O91: PO Mapping | P91: Datalink | Q91: 31 | R91: 310 | S91: 10
A92: DC | B92: DC-Document_Controller-008 | C92: =Data_Master[[#This Row],[Uniq-ID]]&"-"&Data_Master[[#This Row],[Period]] -> DC-Document_Controller-008-M3 | D92: Nurmawaty wx1504714 | E92: XLSMART | G92: M3 | H92: 2026-05-28 - 2026-06-27 | I92: Ended | J92: Excellent | L92: 1.5 | M92: 6.484 | N92: PO Mapping Initial | O92: PO Mapping | P92: Datalink | Q92: 31 | R92: 201 | S92: 6.4839
A93: DC | B93: DC-Document_Controller-008 | C93: =Data_Master[[#This Row],[Uniq-ID]]&"-"&Data_Master[[#This Row],[Period]] -> DC-Document_Controller-008-M4 | D93: Nurmawaty wx1504714 | E93: XLSMART | G93: M4 | H93: 2026-06-28 - 2026-07-27 | I93: Ended | J93: Excellent | L93: 1.5 | M93: 41 | N93: Acceptance | O93: IPS Submit | P93: Datalink | Q93: 4 | R93: 164 | S93: 41
A94: DC | B94: DC-Document_Controller-008 | C94: =Data_Master[[#This Row],[Uniq-ID]]&"-"&Data_Master[[#This Row],[Period]] -> DC-Document_Controller-008-M5 | D94: Nurmawaty wx1504714 | E94: XLSMART | G94: M5 | H94: 2026-07-28 - 2026-08-27 | I94: Ended | J94: Poor | M94: 0
A95: DC | B95: DC-Document_Controller-008 | C95: =Data_Master[[#This Row],[Uniq-ID]]&"-"&Data_Master[[#This Row],[Period]] -> DC-Document_Controller-008-M6 | D95: Nurmawaty wx1504714 | E95: XLSMART | G95: M6 | H95: 2026-08-28 - 2026-09-27 | I95: Ongoing | J95: Poor | M95: 0
A96: DC | B96: DC-Document_Controller-009 | C96: =Data_Master[[#This Row],[Uniq-ID]]&"-"&Data_Master[[#This Row],[Period]] -> DC-Document_Controller-009-M1 | D96: Febryyanti Nawang Wulan wx1503626 | E96: TELKOMSEL | G96: M1 | H96: 2026-03-30 - 2026-04-29 | I96: Ended | J96: Excellent | L96: 1.43 | M96: 2.851 | N96: Implementation | O96: M-08 Dismantle | P96: ISDP | Q96: 36 | R96: 56 | S96: 1.5556
A97: DC | B97: DC-Document_Controller-009 | C97: =Data_Master[[#This Row],[Uniq-ID]]&"-"&Data_Master[[#This Row],[Period]] -> DC-Document_Controller-009-M1 | D97: Febryyanti Nawang Wulan wx1503626 | E97: TELKOMSEL | G97: M1 | H97: 2026-03-30 - 2026-04-29 | I97: Ended | J97: Excellent | L97: 1.43 | M97: 2.851 | N97: Implementation | O97: Tagging Dismantle Material | P97: ISDP | Q97: 35 | R97: 44 | S97: 1.2571
A98: DC | B98: DC-Document_Controller-009 | C98: =Data_Master[[#This Row],[Uniq-ID]]&"-"&Data_Master[[#This Row],[Period]] -> DC-Document_Controller-009-M1 | D98: Febryyanti Nawang Wulan wx1503626 | E98: TELKOMSEL | G98: M1 | H98: 2026-03-30 - 2026-04-29 | I98: Ended | J98: Excellent | L98: 1.43 | M98: 2.851 | N98: Pre-implementation | O98: CAF Application | P98: ISDP | Q98: 26 | R98: 1 | S98: 0.0385
A99: DC | B99: DC-Document_Controller-009 | C99: =Data_Master[[#This Row],[Uniq-ID]]&"-"&Data_Master[[#This Row],[Period]] -> DC-Document_Controller-009-M2 | D99: Febryyanti Nawang Wulan wx1503626 | E99: TELKOMSEL | G99: M2 | H99: 2026-04-30 - 2026-05-29 | I99: Ended | J99: Excellent | L99: 1.5 | M99: 3.155 | N99: Implementation | O99: M-08 Dismantle | P99: ISDP | Q99: 36 | R99: 57 | S99: 1.5833
A100: DC | B100: DC-Document_Controller-009 | C100: =Data_Master[[#This Row],[Uniq-ID]]&"-"&Data_Master[[#This Row],[Period]] -> DC-Document_Controller-009-M2 | D100: Febryyanti Nawang Wulan wx1503626 | E100: TELKOMSEL | G100: M2 | H100: 2026-04-30 - 2026-05-29 | I100: Ended | J100: Excellent | L100: 1.5 | M100: 3.155 | N100: Implementation | O100: Tagging Dismantle Material | P100: ISDP | Q100: 35 | R100: 55 | S100: 1.5714
A101: DC | B101: DC-Document_Controller-009 | C101: =Data_Master[[#This Row],[Uniq-ID]]&"-"&Data_Master[[#This Row],[Period]] -> DC-Document_Controller-009-M3 | D101: Febryyanti Nawang Wulan wx1503626 | E101: TELKOMSEL | G101: M3 | H101: 2026-05-30 - 2026-06-29 | I101: Ended | J101: Excellent | L101: 1.5 | M101: 5.784 | N101: Implementation | O101: Tagging Dismantle Material | P101: ISDP | Q101: 35 | R101: 113 | S101: 3.2286
A102: DC | B102: DC-Document_Controller-009 | C102: =Data_Master[[#This Row],[Uniq-ID]]&"-"&Data_Master[[#This Row],[Period]] -> DC-Document_Controller-009-M3 | D102: Febryyanti Nawang Wulan wx1503626 | E102: TELKOMSEL | G102: M3 | H102: 2026-05-30 - 2026-06-29 | I102: Ended | J102: Excellent | L102: 1.5 | M102: 5.784 | N102: Implementation | O102: M-08 Dismantle | P102: ISDP | Q102: 36 | R102: 92 | S102: 2.5556
A103: DC | B103: DC-Document_Controller-009 | C103: =Data_Master[[#This Row],[Uniq-ID]]&"-"&Data_Master[[#This Row],[Period]] -> DC-Document_Controller-009-M4 | D103: Febryyanti Nawang Wulan wx1503626 | E103: TELKOMSEL | G103: M4 | H103: 2026-06-30 - 2026-07-29 | I103: Ended | J103: Excellent | L103: 1.5 | M103: 3.536 | N103: Implementation | O103: Tagging Installation | P103: ISDP | Q103: 32 | R103: 47 | S103: 1.4688
A104: DC | B104: DC-Document_Controller-009 | C104: =Data_Master[[#This Row],[Uniq-ID]]&"-"&Data_Master[[#This Row],[Period]] -> DC-Document_Controller-009-M4 | D104: Febryyanti Nawang Wulan wx1503626 | E104: TELKOMSEL | G104: M4 | H104: 2026-06-30 - 2026-07-29 | I104: Ended | J104: Excellent | L104: 1.5 | M104: 3.536 | N104: Implementation | O104: Tagging Dismantle Material | P104: ISDP | Q104: 35 | R104: 50 | S104: 1.4286
A105: DC | B105: DC-Document_Controller-009 | C105: =Data_Master[[#This Row],[Uniq-ID]]&"-"&Data_Master[[#This Row],[Period]] -> DC-Document_Controller-009-M4 | D105: Febryyanti Nawang Wulan wx1503626 | E105: TELKOMSEL | G105: M4 | H105: 2026-06-30 - 2026-07-29 | I105: Ended | J105: Excellent | L105: 1.5 | M105: 3.536 | N105: Implementation | O105: M-08 Dismantle | P105: ISDP | Q105: 36 | R105: 23 | S105: 0.6389
A106: DC | B106: DC-Document_Controller-009 | C106: =Data_Master[[#This Row],[Uniq-ID]]&"-"&Data_Master[[#This Row],[Period]] -> DC-Document_Controller-009-M5 | D106: Febryyanti Nawang Wulan wx1503626 | E106: TELKOMSEL | G106: M5 | H106: 2026-07-30 - 2026-08-29 | I106: Ended | J106: Excellent | L106: 1.24 | M106: 2.471 | N106: Implementation | O106: Tagging Installation | P106: ISDP | Q106: 32 | R106: 42 | S106: 1.3125
A107: DC | B107: DC-Document_Controller-009 | C107: =Data_Master[[#This Row],[Uniq-ID]]&"-"&Data_Master[[#This Row],[Period]] -> DC-Document_Controller-009-M5 | D107: Febryyanti Nawang Wulan wx1503626 | E107: TELKOMSEL | G107: M5 | H107: 2026-07-30 - 2026-08-29 | I107: Ended | J107: Excellent | L107: 1.24 | M107: 2.471 | N107: Implementation | O107: Tagging Dismantle Material | P107: ISDP | Q107: 35 | R107: 25 | S107: 0.7143
... A119: DC | B119: DC-Document_Controller-011 | C119: =Data_Master[[#This Row],[Uniq-ID]]&"-"&Data_Master[[#This Row],[Period]] -> DC-Document_Controller-011-M1 | D119: Fitra Faradilla wx1504702 | E119: IOH | G119: M1 | H119: 2026-03-30 - 2026-04-29 | I119: Ended | J119: Normal | L119: 1 | M119: 1.173 | N119: Implementation | O119: Netgear Tagging MOS & Movement | P119: ISDP | Q119: 168 | R119: 109 | S119: 0.6488
A120: DC | B120: DC-Document_Controller-011 | C120: =Data_Master[[#This Row],[Uniq-ID]]&"-"&Data_Master[[#This Row],[Period]] -> DC-Document_Controller-011-M1 | D120: Fitra Faradilla wx1504702 | E120: IOH | G120: M1 | H120: 2026-03-30 - 2026-04-29 | I120: Ended | J120: Normal | L120: 1 | M120: 1.173 | O120: Site Key HO | P120: Datalink | Q120: 924 | R120: 2 | S120: 0.0022
A121: DC | B121: DC-Document_Controller-011 | C121: =Data_Master[[#This Row],[Uniq-ID]]&"-"&Data_Master[[#This Row],[Period]] -> DC-Document_Controller-011-M1 | D121: Fitra Faradilla wx1504702 | E121: IOH | G121: M1 | H121: 2026-03-30 - 2026-04-29 | I121: Ended | J121: Normal | L121: 1 | M121: 1.173 | N121: Acceptance | O121: ATP Endorse - Wireless | P121: ISDP | Q121: 616 | R121: 34 | S121: 0.0552
A122: DC | B122: DC-Document_Controller-011 | C122: =Data_Master[[#This Row],[Uniq-ID]]&"-"&Data_Master[[#This Row],[Period]] -> DC-Document_Controller-011-M2 | D122: Fitra Faradilla wx1504702 | E122: IOH | G122: M2 | H122: 2026-04-30 - 2026-05-29 | I122: Ended | J122: Poor | L122: 0.75 | M122: 0.755 | N122: Acceptance | O122: ATP Endorse - Wireless | P122: ISDP | Q122: 616 | R122: 66 | S122: 0.1071
A123: DC | B123: DC-Document_Controller-011 | C123: =Data_Master[[#This Row],[Uniq-ID]]&"-"&Data_Master[[#This Row],[Period]] -> DC-Document_Controller-011-M2 | D123: Fitra Faradilla wx1504702 | E123: IOH | G123: M2 | H123: 2026-04-30 - 2026-05-29 | I123: Ended | J123: Poor | L123: 0.75 | M123: 0.755 | N123: Implementation | O123: M-08b Inbound Done | P123: ISDP | Q123: 154 | R123: 48 | S123: 0.3117
A124: DC | B124: DC-Document_Controller-011 | C124: =Data_Master[[#This Row],[Uniq-ID]]&"-"&Data_Master[[#This Row],[Period]] -> DC-Document_Controller-011-M2 | D124: Fitra Faradilla wx1504702 | E124: IOH | G124: M2 | H124: 2026-04-30 - 2026-05-29 | I124: Ended | J124: Poor | L124: 0.75 | M124: 0.755 | N124: Implementation | O124: Netgear Tagging MOS & Movement | P124: ISDP | Q124: 168 | R124: 55 | S124: 0.3274
A125: DC | B125: DC-Document_Controller-011 | C125: =Data_Master[[#This Row],[Uniq-ID]]&"-"&Data_Master[[#This Row],[Period]] -> DC-Document_Controller-011-M2 | D125: Fitra Faradilla wx1504702 | E125: IOH | G125: M2 | H125: 2026-04-30 - 2026-05-29 | I125: Ended | J125: Poor | L125: 0.75 | M125: 0.755 | N125: Implementation | O125: Site Key HO | P125: Datalink | Q125: 924 | R125: 8 | S125: 0.0087
A126: DC | B126: DC-Document_Controller-011 | C126: =Data_Master[[#This Row],[Uniq-ID]]&"-"&Data_Master[[#This Row],[Period]] -> DC-Document_Controller-011-M3 | D126: Fitra Faradilla wx1504702 | E126: IOH | G126: M3 | H126: 2026-05-30 - 2026-06-29 | I126: Ended | J126: Normal | L126: 1 | M126: 1.697 | N126: Implementation | O126: M-08b Inbound Done | P126: ISDP | Q126: 154 | R126: 69 | S126: 0.4481
A127: DC | B127: DC-Document_Controller-011 | C127: =Data_Master[[#This Row],[Uniq-ID]]&"-"&Data_Master[[#This Row],[Period]] -> DC-Document_Controller-011-M3 | D127: Fitra Faradilla wx1504702 | E127: IOH | G127: M3 | H127: 2026-05-30 - 2026-06-29 | I127: Ended | J127: Normal | L127: 1 | M127: 1.697 | N127: Implementation | O127: Netgear Tagging MOS & Movement | P127: ISDP | Q127: 168 | R127: 194 | S127: 1.1548
A128: DC | B128: DC-Document_Controller-011 | C128: =Data_Master[[#This Row],[Uniq-ID]]&"-"&Data_Master[[#This Row],[Period]] -> DC-Document_Controller-011-M3 | D128: Fitra Faradilla wx1504702 | E128: IOH | G128: M3 | H128: 2026-05-30 - 2026-06-29 | I128: Ended | J128: Normal | L128: 1 | M128: 1.697 | N128: Acceptance | O128: ATP Endorse - Wireless | P128: ISDP | Q128: 616 | R128: 58 | S128: 0.0942
A129: DC | B129: DC-Document_Controller-011 | C129: =Data_Master[[#This Row],[Uniq-ID]]&"-"&Data_Master[[#This Row],[Period]] -> DC-Document_Controller-011-M4 | D129: Fitra Faradilla wx1504702 | E129: IOH | G129: M4 | H129: 2026-06-30 - 2026-07-29 | I129: Ended | J129: Excellent | L129: 1.44 | M129: 2.879 | N129: Implementation | O129: Netgear Tagging MOS & Movement | P129: ISDP | Q129: 168 | R129: 214 | S129: 1.2738
A130: DC | B130: DC-Document_Controller-011 | C130: =Data_Master[[#This Row],[Uniq-ID]]&"-"&Data_Master[[#This Row],[Period]] -> DC-Document_Controller-011-M4 | D130: Fitra Faradilla wx1504702 | E130: IOH | G130: M4 | H130: 2026-06-30 - 2026-07-29 | I130: Ended | J130: Excellent | L130: 1.44 | M130: 2.879 | N130: Implementation | O130: M-08b Inbound Done | P130: ISDP | Q130: 154 | R130: 206 | S130: 1.3377
A131: DC | B131: DC-Document_Controller-011 | C131: =Data_Master[[#This Row],[Uniq-ID]]&"-"&Data_Master[[#This Row],[Period]] -> DC-Document_Controller-011-M4 | D131: Fitra Faradilla wx1504702 | E131: IOH | G131: M4 | H131: 2026-06-30 - 2026-07-29 | I131: Ended | J131: Excellent | L131: 1.44 | M131: 2.879 | N131: Acceptance | O131: BAUT/BAMS PAC/BAMG FAC - Wireless | P131: ISDP | Q131: 462 | R131: 14 | S131: 0.0303
A132: DC | B132: DC-Document_Controller-011 | C132: =Data_Master[[#This Row],[Uniq-ID]]&"-"&Data_Master[[#This Row],[Period]] -> DC-Document_Controller-011-M4 | D132: Fitra Faradilla wx1504702 | E132: IOH | G132: M4 | H132: 2026-06-30 - 2026-07-29 | I132: Ended | J132: Excellent | L132: 1.44 | M132: 2.879 | N132: Acceptance | O132: ATP Endorse - Wireless | P132: ISDP | Q132: 616 | R132: 146 | S132: 0.237
... A160: DC | B160: DC-Document_Controller-012 | C160: =Data_Master[[#This Row],[Uniq-ID]]&"-"&Data_Master[[#This Row],[Period]] -> DC-Document_Controller-012-M6 | D160: Yosephine Yudianto wx1503656 | E160: TELKOMSEL | G160: M6 | H160: 2026-08-30 - 2026-09-29 | I160: Ongoing | J160: Normal | L160: 1 | M160: 1.189 | N160: Implementation | O160: Tagging Installation | P160: ISDP | Q160: 32 | R160: 29 | S160: 0.9063
A161: DC | B161: DC-Document_Controller-013 | C161: =Data_Master[[#This Row],[Uniq-ID]]&"-"&Data_Master[[#This Row],[Period]] -> DC-Document_Controller-013-M1 | D161: Eka Maudyna Isdyanti wx1504640 | E161: IOH | G161: M1 | H161: 2026-03-30 - 2026-04-29 | I161: Ended | J161: Poor | M161: 0
A162: DC | B162: DC-Document_Controller-013 | C162: =Data_Master[[#This Row],[Uniq-ID]]&"-"&Data_Master[[#This Row],[Period]] -> DC-Document_Controller-013-M2 | D162: Eka Maudyna Isdyanti wx1504640 | E162: IOH | G162: M2 | H162: 2026-04-30 - 2026-05-29 | I162: Ended | J162: Poor | M162: 0
A163: DC | B163: DC-Document_Controller-013 | C163: =Data_Master[[#This Row],[Uniq-ID]]&"-"&Data_Master[[#This Row],[Period]] -> DC-Document_Controller-013-M3 | D163: Eka Maudyna Isdyanti wx1504640 | E163: IOH | G163: M3 | H163: 2026-05-30 - 2026-06-29 | I163: Ended | J163: Poor | M163: 0
A164: DC | B164: DC-Document_Controller-013 | C164: =Data_Master[[#This Row],[Uniq-ID]]&"-"&Data_Master[[#This Row],[Period]] -> DC-Document_Controller-013-M4 | D164: Eka Maudyna Isdyanti wx1504640 | E164: IOH | G164: M4 | H164: 2026-06-30 - 2026-07-29 | I164: Ended | J164: Poor | M164: 0
A165: DC | B165: DC-Document_Controller-013 | C165: =Data_Master[[#This Row],[Uniq-ID]]&"-"&Data_Master[[#This Row],[Period]] -> DC-Document_Controller-013-M5 | D165: Eka Maudyna Isdyanti wx1504640 | E165: IOH | G165: M5 | H165: 2026-07-30 - 2026-08-29 | I165: Ended | J165: Poor | M165: 0
...

Sheet Tagihan
X1: =SUBTOTAL(9,X3:X1149) -> 1938556000
A2: Site Code | B2: Name | C2: Project before | D2: Project Assign | E2: New Project | G2: Period Tagih | H2: Join Date | I2: Join Month | J2: Site Code.1 | K2: Site Name | L2: Regional | M2: Site ID | N2: Sub Contract NO. | O2: PR NO. | P2: PO NO. | Q2: PO Line NO. | R2: Shipment NO. | S2: Item Code | T2: Item Description | U2: Unit Price | V2: Requested Qty | W2: Payment Coef | X2: Total Price | Y2: Acceptance Date | Z2: Status | AA2: ISDP Status | AB2: Remarks | AC2: Action | AD2: Ibuy Status | AE2: ID Project | AF2: SO Number | AG2: Invoice Number | AH2: Invoice Date | AI2: Invoice Month
A3: PE-Project_Engineer-006 | B3: =_xlfn.XLOOKUP(J3,'Master Data 14-9-2026'!C:C,'Master Data 14-9-2026'!D:D) -> Viona Yose Ariani wx1504713 | D3: =_xlfn.XLOOKUP(J3,'Master Data 14-9-2026'!C:C,'Master Data 14-9-2026'!E:E) -> Enterprise | G3: M1 | H3: =_xlfn.XLOOKUP(J3,'Master Data 14-9-2026'!C:C,'Master Data 14-9-2026'!H:H) -> 2026-03-26 - 2026-04-25 | I3: =TEXT(DATEVALUE(LEFT(H3,10)),"mmmm") -> March | J3: PE-Project_Engineer-006-M1 | K3: PE-Project_Engineer-006-M1 | L3: Jabodetabek | M3: 200003104075020 | N3: FPA1091IDN26031710640667 | O3: 1.0912026e+17 | P3: 1091HG3728823-1 | Q3: 1 | R3: 1 | S3: 8828132635 | T3: Project Delivery Monitoring Services - Project Engineer | U3: 34220600 | V3: 1 | W3: =_xlfn.XLOOKUP(J3,'Master Data 14-9-2026'!C:C,'Master Data 14-9-2026'!L:L) -> 0 | X3: 34220600 | Y3: 2026-05-08 | Z3: Ended | AA3: Eror | AB3: PO associated item tidak ada | AE3: =_xlfn.XLOOKUP(L3,'[1]ID PROJECT'!E:E,'[1]ID PROJECT'!F:F) -> PRJ-KUT-KPU-TPED-2026-04-00071
A4: QC-Quality_Control-017 | B4: =_xlfn.XLOOKUP(J4,'Master Data 14-9-2026'!C:C,'Master Data 14-9-2026'!D:D) -> Arsetyo wx1507094 | D4: =_xlfn.XLOOKUP(J4,'Master Data 14-9-2026'!C:C,'Master Data 14-9-2026'!E:E) -> TELKOM | G4: M1 | H4: =_xlfn.XLOOKUP(J4,'Master Data 14-9-2026'!C:C,'Master Data 14-9-2026'!H:H) -> 2026-04-01 - 2026-04-30 | I4: =TEXT(DATEVALUE(LEFT(H4,10)),"mmmm") -> April | J4: QC-Quality_Control-017-M1 | K4: Enhancement NeutraDC | L4: Jabodetabek | M4: 200003102755020 | N4: FPA1091IDN26031710640667 | O4: 1.0912026e+17 | P4: 1091HG3728823-2 | Q4: 1 | R4: 1 | S4: 8828132636 | T4: QEHS Onsite Monitoring and Inspection - QC | U4: 36992000 | V4: 1 | W4: =_xlfn.XLOOKUP(J4,'Master Data 14-9-2026'!C:C,'Master Data 14-9-2026'!L:L) -> 1.1 | X4: 36992000 | Y4: 2026-05-08 | Z4: Ended | AA4: Approved | AD4: Invoice | AE4: =_xlfn.XLOOKUP(L4,'[1]ID PROJECT'!E:E,'[1]ID PROJECT'!F:F) -> PRJ-KUT-KPU-TPED-2026-04-00071 | AF4: SSO-KUT-KPU-NIUT-2026-07-03643 | AG4: 313/INV/KUT-PST/VII/2026 | AH4: 46230 | AI4: Juli
A5: QC-Quality_Control-018 | B5: =_xlfn.XLOOKUP(J5,'Master Data 14-9-2026'!C:C,'Master Data 14-9-2026'!D:D) -> Rifqi Adytia Fauzan wx1507719 | D5: =_xlfn.XLOOKUP(J5,'Master Data 14-9-2026'!C:C,'Master Data 14-9-2026'!E:E) -> TELKOM | G5: M1 | H5: =_xlfn.XLOOKUP(J5,'Master Data 14-9-2026'!C:C,'Master Data 14-9-2026'!H:H) -> 2026-04-01 - 2026-04-30 | I5: =TEXT(DATEVALUE(LEFT(H5,10)),"mmmm") -> April | J5: QC-Quality_Control-018-M1 | K5: Enhancement NeutraDC | L5: Jabodetabek | M5: 200003102756020 | N5: FPA1091IDN26031710640667 | O5: 1.0912026e+17 | P5: 1091HG3728823-2 | Q5: 2 | R5: 1 | S5: 8828132636 | T5: QEHS Onsite Monitoring and Inspection - QC | U5: 36992000 | V5: 1 | W5: =_xlfn.XLOOKUP(J5,'Master Data 14-9-2026'!C:C,'Master Data 14-9-2026'!L:L) -> 0.65 | X5: 36992000 | Y5: 2026-05-08 | Z5: Ended | AA5: Approved | AD5: Invoice | AE5: =_xlfn.XLOOKUP(L5,'[1]ID PROJECT'!E:E,'[1]ID PROJECT'!F:F) -> PRJ-KUT-KPU-TPED-2026-04-00071 | AF5: SSO-KUT-KPU-NIUT-2026-07-03643 | AG5: 313/INV/KUT-PST/VII/2026 | AH5: 46230 | AI5: Juli
A6: PE-Project_Engineer-018 | B6: =_xlfn.XLOOKUP(J6,'Master Data 14-9-2026'!C:C,'Master Data 14-9-2026'!D:D) -> Qudsiyah Zahra Ilham Naseela wx1507281 | D6: =_xlfn.XLOOKUP(J6,'Master Data 14-9-2026'!C:C,'Master Data 14-9-2026'!E:E) -> XLSMART | G6: M1 | H6: =_xlfn.XLOOKUP(J6,'Master Data 14-9-2026'!C:C,'Master Data 14-9-2026'!H:H) -> 2026-04-01 - 2026-04-30 | I6: =TEXT(DATEVALUE(LEFT(H6,10)),"mmmm") -> April | J6: PE-Project_Engineer-018-M1 | K6: Wisma Mulia | L6: Jabodetabek | M6: 200003104094020 | N6: FPA1091IDN26031710640667 | O6: 1.0912026e+17 | P6: 1091HG3728823-3 | Q6: 1 | R6: 1 | S6: 8828132635 | T6: Project Delivery Monitoring Services - Project Engineer | U6: 34220600 | V6: 1 | W6: =_xlfn.XLOOKUP(J6,'Master Data 14-9-2026'!C:C,'Master Data 14-9-2026'!L:L) -> 1.32 | X6: 34220600 | Y6: 2026-05-08 | Z6: Ended | AA6: Approved | AD6: Invoice | AE6: =_xlfn.XLOOKUP(L6,'[1]ID PROJECT'!E:E,'[1]ID PROJECT'!F:F) -> PRJ-KUT-KPU-TPED-2026-04-00071 | AF6: SSO-KUT-KPU-NIUT-2026-06-03073 | AG6: 261/INV/KUT-PST/VI/2026 | AH6: 46197 | AI6: Juni
A7: PE-Project_Engineer-021 | B7: =_xlfn.XLOOKUP(J7,'Master Data 14-9-2026'!C:C,'Master Data 14-9-2026'!D:D) -> Agus Hendra wx1506946 | D7: =_xlfn.XLOOKUP(J7,'Master Data 14-9-2026'!C:C,'Master Data 14-9-2026'!E:E) -> XLSMART | G7: M1 | H7: =_xlfn.XLOOKUP(J7,'Master Data 14-9-2026'!C:C,'Master Data 14-9-2026'!H:H) -> 2026-04-01 - 2026-04-30 | I7: =TEXT(DATEVALUE(LEFT(H7,10)),"mmmm") -> April | J7: PE-Project_Engineer-021-M1 | K7: Wisma Mulia | L7: Jabodetabek | M7: 200003104095020 | N7: FPA1091IDN26031710640667 | O7: 1.0912026e+17 | P7: 1091HG3728823-3 | Q7: 2 | R7: 1 | S7: 8828132635 | T7: Project Delivery Monitoring Services - Project Engineer | U7: 34220600 | V7: 1 | W7: =_xlfn.XLOOKUP(J7,'Master Data 14-9-2026'!C:C,'Master Data 14-9-2026'!L:L) -> 1 | X7: 34220600 | Y7: 2026-05-08 | Z7: =_xlfn.XLOOKUP(J7,'Master Data 14-9-2026'!C:C,'Master Data 14-9-2026'!I:I) -> Ended | AA7: Approved | AD7: Invoice | AE7: =_xlfn.XLOOKUP(L7,'[1]ID PROJECT'!E:E,'[1]ID PROJECT'!F:F) -> PRJ-KUT-KPU-TPED-2026-04-00071 | AF7: SSO-KUT-KPU-NIUT-2026-06-03073 | AG7: 261/INV/KUT-PST/VI/2026 | AH7: 46197 | AI7: Juni
A8: QC-Quality_Control-001 | B8: =_xlfn.XLOOKUP(J8,'Master Data 14-9-2026'!C:C,'Master Data 14-9-2026'!D:D) -> Leonard Ricardo Hutabarat wx1503633 | D8: =_xlfn.XLOOKUP(J8,'Master Data 14-9-2026'!C:C,'Master Data 14-9-2026'!E:E) -> XLSMART | G8: M1 | H8: =_xlfn.XLOOKUP(J8,'Master Data 14-9-2026'!C:C,'Master Data 14-9-2026'!H:H) -> 2026-03-23 - 2026-04-22 | I8: =TEXT(DATEVALUE(LEFT(H8,10)),"mmmm") -> March | J8: QC-Quality_Control-001-M1 | K8: Wisma Mulia | L8: Sumatera | M8: 200003104096020 | N8: FPA1091IDN26031710640667 | O8: 1.0912026e+17 | P8: 1091HG3728823-3 | Q8: 3 | R8: 1 | S8: 8828132636 | T8: QEHS Onsite Monitoring and Inspection - QC | U8: 36992000 | V8: 1 | W8: =_xlfn.XLOOKUP(J8,'Master Data 14-9-2026'!C:C,'Master Data 14-9-2026'!L:L) -> 1.5 | X8: 36992000 | Y8: 2026-05-08 | Z8: Ended | AA8: Approved | AD8: Invoice | AE8: =_xlfn.XLOOKUP(L8,'[1]ID PROJECT'!E:E,'[1]ID PROJECT'!F:F) -> PRJ-KUT-KPU-TPED-2026-04-00078 | AF8: SSO-KUT-KPU-NIUT-2026-06-03073 | AG8: 261/INV/KUT-PST/VI/2026 | AH8: 46197 | AI8: Juni
A9: QC-Quality_Control-002 | B9: =_xlfn.XLOOKUP(J9,'Master Data 14-9-2026'!C:C,'Master Data 14-9-2026'!D:D) -> Risman Nurjaman wx1503969 | D9: =_xlfn.XLOOKUP(J9,'Master Data 14-9-2026'!C:C,'Master Data 14-9-2026'!E:E) -> XLSMART | G9: M1 | H9: =_xlfn.XLOOKUP(J9,'Master Data 14-9-2026'!C:C,'Master Data 14-9-2026'!H:H) -> 2026-03-23 - 2026-04-22 | I9: =TEXT(DATEVALUE(LEFT(H9,10)),"mmmm") -> March | J9: QC-Quality_Control-002-M1 | K9: Wisma Mulia | L9: West Java | M9: 200003104097020 | N9: FPA1091IDN26031710640667 | O9: 1.0912026e+17 | P9: 1091HG3728823-3 | Q9: 4 | R9: 1 | S9: 8828132636 | T9: QEHS Onsite Monitoring and Inspection - QC | U9: 36992000 | V9: 1 | W9: =_xlfn.XLOOKUP(J9,'Master Data 14-9-2026'!C:C,'Master Data 14-9-2026'!L:L) -> 1.5 | X9: 36992000 | Y9: 2026-05-08 | Z9: Ended | AA9: Approved | AD9: Invoice | AE9: =_xlfn.XLOOKUP(L9,'[1]ID PROJECT'!E:E,'[1]ID PROJECT'!F:F) -> PRJ-KUT-KPU-TPED-2026-04-00074 | AF9: SSO-KUT-KPU-NIUT-2026-06-03073 | AG9: 261/INV/KUT-PST/VI/2026 | AH9: 46197 | AI9: Juni
A10: DC-Document_Controller-002 | B10: =_xlfn.XLOOKUP(J10,'Master Data 14-9-2026'!C:C,'Master Data 14-9-2026'!D:D) -> Rifan Azkia wx1504665 | D10: =_xlfn.XLOOKUP(J10,'Master Data 14-9-2026'!C:C,'Master Data 14-9-2026'!E:E) -> XLSMART | G10: M1 | H10: =_xlfn.XLOOKUP(J10,'Master Data 14-9-2026'!C:C,'Master Data 14-9-2026'!H:H) -> 2026-03-23 - 2026-04-22 | I10: =TEXT(DATEVALUE(LEFT(H10,10)),"mmmm") -> March | J10: DC-Document_Controller-002-M1 | K10: Wisma Mulia | L10: Sumbagsel | M10: 200003104079020 | N10: FPA1091IDN26031710640667 | O10: 1.0912026e+17 | P10: 1091HG3728823-3 | Q10: 5 | R10: 1 | S10: 8828132633 | T10: Project Delivery Monitoring Services - Document Control | U10: 28881900 | V10: 1 | W10: =_xlfn.XLOOKUP(J10,'Master Data 14-9-2026'!C:C,'Master Data 14-9-2026'!L:L) -> 0 | X10: 28881900 | Y10: 2026-05-08 | Z10: Ended | AA10: Approved | AD10: Invoice | AE10: =_xlfn.XLOOKUP(L10,'[1]ID PROJECT'!E:E,'[1]ID PROJECT'!F:F) -> PRJ-KUT-KPU-TPED-2026-04-00078 | AF10: SSO-KUT-KPU-NIUT-2026-06-03073 | AG10: 261/INV/KUT-PST/VI/2026 | AH10: 46197 | AI10: Juni
A11: DC-Document_Controller-006 | B11: =_xlfn.XLOOKUP(J11,'Master Data 14-9-2026'!C:C,'Master Data 14-9-2026'!D:D) -> Devi Dyah Palupi wx1503645 | D11: =_xlfn.XLOOKUP(J11,'Master Data 14-9-2026'!C:C,'Master Data 14-9-2026'!E:E) -> IOH | G11: M1 | H11: =_xlfn.XLOOKUP(J11,'Master Data 14-9-2026'!C:C,'Master Data 14-9-2026'!H:H) -> 2026-03-23 - 2026-04-22 | I11: =TEXT(DATEVALUE(LEFT(H11,10)),"mmmm") -> March | J11: DC-Document_Controller-006-M1 | K11: Wisma Mulia | L11: Bali Nusra | M11: 200003104080020 | N11: FPA1091IDN26031710640667 | O11: 1.0912026e+17 | P11: 1091HG3728823-3 | Q11: 6 | R11: 1 | S11: 8828132633 | T11: Project Delivery Monitoring Services - Document Control | U11: 28881900 | V11: 1 | W11: =_xlfn.XLOOKUP(J11,'Master Data 14-9-2026'!C:C,'Master Data 14-9-2026'!L:L) -> 0 | X11: 28881900 | Y11: 2026-05-08 | Z11: Ended | AA11: Approved | AD11: Invoice | AE11: =_xlfn.XLOOKUP(L11,'[1]ID PROJECT'!E:E,'[1]ID PROJECT'!F:F) -> PRJ-KUT-KPU-TPED-2026-04-00077 | AF11: SSO-KUT-KPU-NIUT-2026-06-03073 | AG11: 261/INV/KUT-PST/VI/2026 | AH11: 46197 | AI11: Juni
A12: DC-Document_Controller-007 | B12: =_xlfn.XLOOKUP(J12,'Master Data 14-9-2026'!C:C,'Master Data 14-9-2026'!D:D) -> Mauli Rizki Amelia wx1504666 | D12: =_xlfn.XLOOKUP(J12,'Master Data 14-9-2026'!C:C,'Master Data 14-9-2026'!E:E) -> XLSMART | G12: M1 | H12: =_xlfn.XLOOKUP(J12,'Master Data 14-9-2026'!C:C,'Master Data 14-9-2026'!H:H) -> 2026-03-26 - 2026-04-25 | I12: =TEXT(DATEVALUE(LEFT(H12,10)),"mmmm") -> March | J12: DC-Document_Controller-007-M1 | K12: Wisma Mulia | L12: Sumbagsel | M12: 200003104081020 | N12: FPA1091IDN26031710640667 | O12: 1.0912026e+17 | P12: 1091HG3728823-3 | Q12: 7 | R12: 1 | S12: 8828132633 | T12: Project Delivery Monitoring Services - Document Control | U12: 28881900 | V12: 1 | W12: =_xlfn.XLOOKUP(J12,'Master Data 14-9-2026'!C:C,'Master Data 14-9-2026'!L:L) -> 0.5 | X12: 28881900 | Y12: 2026-05-08 | Z12: Ended | AA12: Approved | AD12: Invoice | AE12: =_xlfn.XLOOKUP(L12,'[1]ID PROJECT'!E:E,'[1]ID PROJECT'!F:F) -> PRJ-KUT-KPU-TPED-2026-04-00078 | AF12: SSO-KUT-KPU-NIUT-2026-06-03073 | AG12: 261/INV/KUT-PST/VI/2026 | AH12: 46197 | AI12: Juni
A13: DC-Document_Controller-008 | B13: =_xlfn.XLOOKUP(J13,'Master Data 14-9-2026'!C:C,'Master Data 14-9-2026'!D:D) -> Nurmawaty wx1504714 | D13: =_xlfn.XLOOKUP(J13,'Master Data 14-9-2026'!C:C,'Master Data 14-9-2026'!E:E) -> XLSMART | G13: M1 | H13: =_xlfn.XLOOKUP(J13,'Master Data 14-9-2026'!C:C,'Master Data 14-9-2026'!H:H) -> 2026-03-28 - 2026-04-27 | I13: =TEXT(DATEVALUE(LEFT(H13,10)),"mmmm") -> March | J13: DC-Document_Controller-008-M1 | K13: Wisma Mulia | L13: Jabodetabek | M13: 200003104082020 | N13: FPA1091IDN26031710640667 | O13: 1.0912026e+17 | P13: 1091HG3728823-3 | Q13: 8 | R13: 1 | S13: 8828132633 | T13: Project Delivery Monitoring Services - Document Control | U13: 28881900 | V13: 1 | W13: =_xlfn.XLOOKUP(J13,'Master Data 14-9-2026'!C:C,'Master Data 14-9-2026'!L:L) -> 1.5 | X13: 28881900 | Y13: 2026-05-08 | Z13: Ended | AA13: Approved | AD13: Invoice | AE13: =_xlfn.XLOOKUP(L13,'[1]ID PROJECT'!E:E,'[1]ID PROJECT'!F:F) -> PRJ-KUT-KPU-TPED-2026-04-00071 | AF13: SSO-KUT-KPU-NIUT-2026-06-03073 | AG13: 261/INV/KUT-PST/VI/2026 | AH13: 46197 | AI13: Juni
A14: DC-Document_Controller-014 | B14: =_xlfn.XLOOKUP(J14,'Master Data 14-9-2026'!C:C,'Master Data 14-9-2026'!D:D) -> Didit Irawan wx1504645 | D14: =_xlfn.XLOOKUP(J14,'Master Data 14-9-2026'!C:C,'Master Data 14-9-2026'!E:E) -> XLSMART | G14: M1 | H14: =_xlfn.XLOOKUP(J14,'Master Data 14-9-2026'!C:C,'Master Data 14-9-2026'!H:H) -> 2026-03-30 - 2026-04-29 | I14: =TEXT(DATEVALUE(LEFT(H14,10)),"mmmm") -> March | J14: DC-Document_Controller-014-M1 | K14: Wisma Mulia | L14: Jabodetabek | M14: 200003104083020 | N14: FPA1091IDN26031710640667 | O14: 1.0912026e+17 | P14: 1091HG3728823-3 | Q14: 9 | R14: 1 | S14: 8828132633 | T14: Project Delivery Monitoring Services - Document Control | U14: 28881900 | V14: 1 | W14: =_xlfn.XLOOKUP(J14,'Master Data 14-9-2026'!C:C,'Master Data 14-9-2026'!L:L) -> 0.5 | X14: 28881900 | Y14: 2026-05-08 | Z14: Ended | AA14: Approved | AD14: Invoice | AE14: =_xlfn.XLOOKUP(L14,'[1]ID PROJECT'!E:E,'[1]ID PROJECT'!F:F) -> PRJ-KUT-KPU-TPED-2026-04-00071 | AF14: SSO-KUT-KPU-NIUT-2026-06-03073 | AG14: 261/INV/KUT-PST/VI/2026 | AH14: 46197 | AI14: Juni
A15: PE-Project_Engineer-001 | B15: =_xlfn.XLOOKUP(J15,'Master Data 14-9-2026'!C:C,'Master Data 14-9-2026'!D:D) -> Rizqy Ramadhan Pramono wx1503632 | D15: =_xlfn.XLOOKUP(J15,'Master Data 14-9-2026'!C:C,'Master Data 14-9-2026'!E:E) -> XLSMART | G15: M1 | H15: =_xlfn.XLOOKUP(J15,'Master Data 14-9-2026'!C:C,'Master Data 14-9-2026'!H:H) -> 2026-03-23 - 2026-04-22 | I15: =TEXT(DATEVALUE(LEFT(H15,10)),"mmmm") -> March | J15: PE-Project_Engineer-001-M1 | K15: Wisma Mulia | L15: Sumatera | M15: 200003104088020 | N15: FPA1091IDN26031710640667 | O15: 1.0912026e+17 | P15: 1091HG3728823-3 | Q15: 10 | R15: 1 | S15: 8828132635 | T15: Project Delivery Monitoring Services - Project Engineer | U15: 34220600 | V15: 1 | W15: =_xlfn.XLOOKUP(J15,'Master Data 14-9-2026'!C:C,'Master Data 14-9-2026'!L:L) -> 1 | X15: 34220600 | Y15: 2026-05-08 | Z15: =_xlfn.XLOOKUP(J15,'Master Data 14-9-2026'!C:C,'Master Data 14-9-2026'!I:I) -> Ended | AA15: Approved | AD15: Invoice | AE15: =_xlfn.XLOOKUP(L15,'[1]ID PROJECT'!E:E,'[1]ID PROJECT'!F:F) -> PRJ-KUT-KPU-TPED-2026-04-00078 | AF15: SSO-KUT-KPU-NIUT-2026-06-03073 | AG15: 261/INV/KUT-PST/VI/2026 | AH15: 46197 | AI15: Juni
A16: DC-Document_Controller-023 | B16: =_xlfn.XLOOKUP(J16,'Master Data 14-9-2026'!C:C,'Master Data 14-9-2026'!D:D) -> Ika Setianingsih wx1507364 | D16: =_xlfn.XLOOKUP(J16,'Master Data 14-9-2026'!C:C,'Master Data 14-9-2026'!E:E) -> XLSMART | G16: M1 | H16: =_xlfn.XLOOKUP(J16,'Master Data 14-9-2026'!C:C,'Master Data 14-9-2026'!H:H) -> 2026-04-01 - 2026-04-30 | I16: =TEXT(DATEVALUE(LEFT(H16,10)),"mmmm") -> April | J16: DC-Document_Controller-023-M1 | K16: Wisma Mulia | L16: Jabodetabek | M16: 200003104084020 | N16: FPA1091IDN26031710640667 | O16: 1.0912026e+17 | P16: 1091HG3728823-3 | Q16: 11 | R16: 1 | S16: 8828132633 | T16: Project Delivery Monitoring Services - Document Control | U16: 28881900 | V16: 1 | W16: =_xlfn.XLOOKUP(J16,'Master Data 14-9-2026'!C:C,'Master Data 14-9-2026'!L:L) -> 1.5 | X16: 28881900 | Y16: 2026-05-08 | Z16: Ended | AA16: Approved | AD16: Invoice | AE16: =_xlfn.XLOOKUP(L16,'[1]ID PROJECT'!E:E,'[1]ID PROJECT'!F:F) -> PRJ-KUT-KPU-TPED-2026-04-00071 | AF16: SSO-KUT-KPU-NIUT-2026-06-03073 | AG16: 261/INV/KUT-PST/VI/2026 | AH16: 46197 | AI16: Juni
A17: DC-Document_Controller-025 | B17: =_xlfn.XLOOKUP(J17,'Master Data 14-9-2026'!C:C,'Master Data 14-9-2026'!D:D) -> Aliyah wx1507137 | D17: =_xlfn.XLOOKUP(J17,'Master Data 14-9-2026'!C:C,'Master Data 14-9-2026'!E:E) -> XLSMART | G17: M1 | H17: =_xlfn.XLOOKUP(J17,'Master Data 14-9-2026'!C:C,'Master Data 14-9-2026'!H:H) -> 2026-04-01 - 2026-04-30 | I17: =TEXT(DATEVALUE(LEFT(H17,10)),"mmmm") -> April | J17: DC-Document_Controller-025-M1 | K17: Wisma Mulia | L17: Kalimantan | M17: 200003104085020 | N17: FPA1091IDN26031710640667 | O17: 1.0912026e+17 | P17: 1091HG3728823-3 | Q17: 12 | R17: 1 | S17: 8828132633 | T17: Project Delivery Monitoring Services - Document Control | U17: 28881900 | V17: 1 | W17: =_xlfn.XLOOKUP(J17,'Master Data 14-9-2026'!C:C,'Master Data 14-9-2026'!L:L) -> 1.05 | X17: 28881900 | Y17: 2026-05-08 | Z17: Ended | AA17: Approved | AD17: Invoice | AE17: =_xlfn.XLOOKUP(L17,'[1]ID PROJECT'!E:E,'[1]ID PROJECT'!F:F) -> PRJ-KUT-KPU-TPED-2026-04-00079 | AF17: SSO-KUT-KPU-NIUT-2026-06-03073 | AG17: 261/INV/KUT-PST/VI/2026 | AH17: 46197 | AI17: Juni
A18: PE-Project_Engineer-004 | B18: =_xlfn.XLOOKUP(J18,'Master Data 14-9-2026'!C:C,'Master Data 14-9-2026'!D:D) -> Rayza Mayga Pratama wx1504644 | D18: =_xlfn.XLOOKUP(J18,'Master Data 14-9-2026'!C:C,'Master Data 14-9-2026'!E:E) -> XLSMART | G18: M1 | H18: =_xlfn.XLOOKUP(J18,'Master Data 14-9-2026'!C:C,'Master Data 14-9-2026'!H:H) -> 2026-03-23 - 2026-04-22 | I18: =TEXT(DATEVALUE(LEFT(H18,10)),"mmmm") -> March | J18: PE-Project_Engineer-004-M1 | K18: Wisma Mulia | L18: Jabodetabek | M18: 200003104089020 | N18: FPA1091IDN26031710640667 | O18: 1.0912026e+17 | P18: 1091HG3728823-3 | Q18: 13 | R18: 1 | S18: 8828132635 | T18: Project Delivery Monitoring Services - Project Engineer | U18: 34220600 | V18: 1 | W18: =_xlfn.XLOOKUP(J18,'Master Data 14-9-2026'!C:C,'Master Data 14-9-2026'!L:L) -> 1.01 | X18: 34220600 | Y18: 2026-05-08 | Z18: Ended | AA18: Approved | AD18: Invoice | AE18: =_xlfn.XLOOKUP(L18,'[1]ID PROJECT'!E:E,'[1]ID PROJECT'!F:F) -> PRJ-KUT-KPU-TPED-2026-04-00071 | AF18: SSO-KUT-KPU-NIUT-2026-06-03073 | AG18: 261/INV/KUT-PST/VI/2026 | AH18: 46197 | AI18: Juni
A19: DC-Document_Controller-026 | B19: =_xlfn.XLOOKUP(J19,'Master Data 14-9-2026'!C:C,'Master Data 14-9-2026'!D:D) -> Salsabila Ulya Nabilah Fuad wx1507138 | D19: =_xlfn.XLOOKUP(J19,'Master Data 14-9-2026'!C:C,'Master Data 14-9-2026'!E:E) -> XLSMART | G19: M1 | H19: =_xlfn.XLOOKUP(J19,'Master Data 14-9-2026'!C:C,'Master Data 14-9-2026'!H:H) -> 2026-04-01 - 2026-04-30 | I19: =TEXT(DATEVALUE(LEFT(H19,10)),"mmmm") -> April | J19: DC-Document_Controller-026-M1 | K19: Wisma Mulia | L19: Kalimantan | M19: 200003104086020 | N19: FPA1091IDN26031710640667 | O19: 1.0912026e+17 | P19: 1091HG3728823-3 | Q19: 14 | R19: 1 | S19: 8828132633 | T19: Project Delivery Monitoring Services - Document Control | U19: 28881900 | V19: 1 | W19: =_xlfn.XLOOKUP(J19,'Master Data 14-9-2026'!C:C,'Master Data 14-9-2026'!L:L) -> 0.5 | X19: 28881900 | Y19: 2026-05-08 | Z19: Ended | AA19: Approved | AD19: Invoice | AE19: =_xlfn.XLOOKUP(L19,'[1]ID PROJECT'!E:E,'[1]ID PROJECT'!F:F) -> PRJ-KUT-KPU-TPED-2026-04-00079 | AF19: SSO-KUT-KPU-NIUT-2026-06-03073 | AG19: 261/INV/KUT-PST/VI/2026 | AH19: 46197 | AI19: Juni
A20: DC-Document_Controller-028 | B20: =_xlfn.XLOOKUP(J20,'Master Data 14-9-2026'!C:C,'Master Data 14-9-2026'!D:D) -> Cahyo Suryo Bhuwono Winarso wx1507283 | D20: =_xlfn.XLOOKUP(J20,'Master Data 14-9-2026'!C:C,'Master Data 14-9-2026'!E:E) -> XLSMART | G20: M1 | H20: =_xlfn.XLOOKUP(J20,'Master Data 14-9-2026'!C:C,'Master Data 14-9-2026'!H:H) -> 2026-04-01 - 2026-04-30 | I20: =TEXT(DATEVALUE(LEFT(H20,10)),"mmmm") -> April | J20: DC-Document_Controller-028-M1 | K20: Wisma Mulia | L20: West Java | M20: 200003104087020 | N20: FPA1091IDN26031710640667 | O20: 1.0912026e+17 | P20: 1091HG3728823-3 | Q20: 15 | R20: 1 | S20: 8828132633 | T20: Project Delivery Monitoring Services - Document Control | U20: 28881900 | V20: 1 | W20: =_xlfn.XLOOKUP(J20,'Master Data 14-9-2026'!C:C,'Master Data 14-9-2026'!L:L) -> 0 | X20: 28881900 | Y20: 2026-05-08 | Z20: Ended | AA20: Approved | AD20: Invoice | AE20: =_xlfn.XLOOKUP(L20,'[1]ID PROJECT'!E:E,'[1]ID PROJECT'!F:F) -> PRJ-KUT-KPU-TPED-2026-04-00074 | AF20: SSO-KUT-KPU-NIUT-2026-06-03073 | AG20: 261/INV/KUT-PST/VI/2026 | AH20: 46197 | AI20: Juni
A21: PE-Project_Engineer-009 | B21: =_xlfn.XLOOKUP(J21,'Master Data 14-9-2026'!C:C,'Master Data 14-9-2026'!D:D) -> Sugeng Andrianto wx1504668 | D21: =_xlfn.XLOOKUP(J21,'Master Data 14-9-2026'!C:C,'Master Data 14-9-2026'!E:E) -> XLSMART | G21: M1 | H21: =_xlfn.XLOOKUP(J21,'Master Data 14-9-2026'!C:C,'Master Data 14-9-2026'!H:H) -> 2026-03-30 - 2026-04-29 | I21: =TEXT(DATEVALUE(LEFT(H21,10)),"mmmm") -> March | J21: PE-Project_Engineer-009-M1 | K21: Wisma Mulia | L21: Sumatera | M21: 200003104090020 | N21: FPA1091IDN26031710640667 | O21: 1.0912026e+17 | P21: 1091HG3728823-3 | Q21: 16 | R21: 1 | S21: 8828132635 | T21: Project Delivery Monitoring Services - Project Engineer | U21: 34220600 | V21: 1 | W21: =_xlfn.XLOOKUP(J21,'Master Data 14-9-2026'!C:C,'Master Data 14-9-2026'!L:L) -> 1.05 | X21: 34220600 | Y21: 2026-05-08 | Z21: Ended | AA21: Approved | AD21: Invoice | AE21: =_xlfn.XLOOKUP(L21,'[1]ID PROJECT'!E:E,'[1]ID PROJECT'!F:F) -> PRJ-KUT-KPU-TPED-2026-04-00078 | AF21: SSO-KUT-KPU-NIUT-2026-06-03073 | AG21: 261/INV/KUT-PST/VI/2026 | AH21: 46197 | AI21: Juni
A22: DC-Document_Controller-033 | B22: =_xlfn.XLOOKUP(J22,'Master Data 14-9-2026'!C:C,'Master Data 14-9-2026'!D:D) -> Gema Marhayen wx1506940 | D22: =_xlfn.XLOOKUP(J22,'Master Data 14-9-2026'!C:C,'Master Data 14-9-2026'!E:E) -> XLSMART | E22: XL DC033 | G22: M1 | H22: =_xlfn.XLOOKUP(J22,'Master Data 14-9-2026'!C:C,'Master Data 14-9-2026'!H:H) -> 2026-04-01 - 2026-04-30 | I22: =TEXT(DATEVALUE(LEFT(H22,10)),"mmmm") -> April | J22: DC-Document_Controller-033-M1 | K22: Wisma Mulia | L22: Jabodetabek | M22: 200003104077020 | N22: FPA1091IDN26031710640667 | O22: 1.0912026e+17 | P22: 1091HG3728823-3 | Q22: 17 | R22: 1 | S22: 8828132633 | T22: Project Delivery Monitoring Services - Document Control | U22: 28881900 | V22: 1 | W22: =_xlfn.XLOOKUP(J22,'Master Data 14-9-2026'!C:C,'Master Data 14-9-2026'!L:L) -> 1.06 | X22: 28881900 | Y22: 2026-05-08 | Z22: Ended | AA22: Approved | AC22: Confirm dean | AD22: Invoice | AE22: =_xlfn.XLOOKUP(L22,'[1]ID PROJECT'!E:E,'[1]ID PROJECT'!F:F) -> PRJ-KUT-KPU-TPED-2026-04-00071 | AF22: SSO-KUT-KPU-NIUT-2026-09-04608 | AG22: 392/INV/KUT-PST/IX/2026 | AH22: 46267 | AI22: September
A23: QC-Quality_Control-004 | B23: =_xlfn.XLOOKUP(J23,'Master Data 14-9-2026'!C:C,'Master Data 14-9-2026'!D:D) -> Dewi Nur Annisa wx1503631 | D23: =_xlfn.XLOOKUP(J23,'Master Data 14-9-2026'!C:C,'Master Data 14-9-2026'!E:E) -> XLSMART | G23: M1 | H23: =_xlfn.XLOOKUP(J23,'Master Data 14-9-2026'!C:C,'Master Data 14-9-2026'!H:H) -> 2026-03-25 - 2026-04-24 | I23: =TEXT(DATEVALUE(LEFT(H23,10)),"mmmm") -> March | J23: QC-Quality_Control-004-M1 | K23: Wisma Mulia | L23: Sumatera | M23: 200003104098020 | N23: FPA1091IDN26031710640667 | O23: 1.0912026e+17 | P23: 1091HG3728823-3 | Q23: 18 | R23: 1 | S23: 8828132636 | T23: QEHS Onsite Monitoring and Inspection - QC | U23: 36992000 | V23: 1 | W23: =_xlfn.XLOOKUP(J23,'Master Data 14-9-2026'!C:C,'Master Data 14-9-2026'!L:L) -> 1.3 | X23: 36992000 | Y23: 2026-05-08 | Z23: Ended | AA23: Approved | AD23: Invoice | AE23: =_xlfn.XLOOKUP(L23,'[1]ID PROJECT'!E:E,'[1]ID PROJECT'!F:F) -> PRJ-KUT-KPU-TPED-2026-04-00078 | AF23: SSO-KUT-KPU-NIUT-2026-06-03073 | AG23: 261/INV/KUT-PST/VI/2026 | AH23: 46197 | AI23: Juni
A24: PE-Project_Engineer-010 | B24: =_xlfn.XLOOKUP(J24,'Master Data 14-9-2026'!C:C,'Master Data 14-9-2026'!D:D) -> Fauzan Fathoni wx1504667 | D24: =_xlfn.XLOOKUP(J24,'Master Data 14-9-2026'!C:C,'Master Data 14-9-2026'!E:E) -> XLSMART | G24: M1 | H24: =_xlfn.XLOOKUP(J24,'Master Data 14-9-2026'!C:C,'Master Data 14-9-2026'!H:H) -> 2026-03-30 - 2026-04-29 | I24: =TEXT(DATEVALUE(LEFT(H24,10)),"mmmm") -> March | J24: PE-Project_Engineer-010-M1 | K24: Wisma Mulia | L24: Sumatera | M24: 200003104091020 | N24: FPA1091IDN26031710640667 | O24: 1.0912026e+17 | P24: 1091HG3728823-3 | Q24: 19 | R24: 1 | S24: 8828132635 | T24: Project Delivery Monitoring Services - Project Engineer | U24: 34220600 | V24: 1 | W24: =_xlfn.XLOOKUP(J24,'Master Data 14-9-2026'!C:C,'Master Data 14-9-2026'!L:L) -> 1.5 | X24: 34220600 | Y24: 2026-05-08 | Z24: Ended | AA24: Approved | AD24: Invoice | AE24: =_xlfn.XLOOKUP(L24,'[1]ID PROJECT'!E:E,'[1]ID PROJECT'!F:F) -> PRJ-KUT-KPU-TPED-2026-04-00078 | AF24: SSO-KUT-KPU-NIUT-2026-06-03073 | AG24: 261/INV/KUT-PST/VI/2026 | AH24: 46197 | AI24: Juni
A25: QC-Quality_Control-005 | B25: =_xlfn.XLOOKUP(J25,'Master Data 14-9-2026'!C:C,'Master Data 14-9-2026'!D:D) -> Febby Ramadhan Ahmad Suhandi wx1503968 | D25: =_xlfn.XLOOKUP(J25,'Master Data 14-9-2026'!C:C,'Master Data 14-9-2026'!E:E) -> XLSMART | G25: M1 | H25: =_xlfn.XLOOKUP(J25,'Master Data 14-9-2026'!C:C,'Master Data 14-9-2026'!H:H) -> 2026-03-25 - 2026-04-24 | I25: =TEXT(DATEVALUE(LEFT(H25,10)),"mmmm") -> March | J25: QC-Quality_Control-005-M1 | K25: Wisma Mulia | L25: Jabodetabek | M25: 200003104099020 | N25: FPA1091IDN26031710640667 | O25: 1.0912026e+17 | P25: 1091HG3728823-3 | Q25: 20 | R25: 1 | S25: 8828132636 | T25: QEHS Onsite Monitoring and Inspection - QC | U25: 36992000 | V25: 1 | W25: =_xlfn.XLOOKUP(J25,'Master Data 14-9-2026'!C:C,'Master Data 14-9-2026'!L:L) -> 1.5 | X25: 36992000 | Y25: 2026-05-08 | Z25: Ended | AA25: Approved | AD25: Invoice | AE25: =_xlfn.XLOOKUP(L25,'[1]ID PROJECT'!E:E,'[1]ID PROJECT'!F:F) -> PRJ-KUT-KPU-TPED-2026-04-00071 | AF25: SSO-KUT-KPU-NIUT-2026-06-03073 | AG25: 261/INV/KUT-PST/VI/2026 | AH25: 46197 | AI25: Juni | AJ25: reklas revenue
A26: PE-Project_Engineer-015 | B26: =_xlfn.XLOOKUP(J26,'Master Data 14-9-2026'!C:C,'Master Data 14-9-2026'!D:D) -> Yonathan Janmorga wx1507284 | D26: =_xlfn.XLOOKUP(J26,'Master Data 14-9-2026'!C:C,'Master Data 14-9-2026'!E:E) -> XLSMART | G26: M1 | H26: =_xlfn.XLOOKUP(J26,'Master Data 14-9-2026'!C:C,'Master Data 14-9-2026'!H:H) -> 2026-04-01 - 2026-04-30 | I26: =TEXT(DATEVALUE(LEFT(H26,10)),"mmmm") -> April | J26: PE-Project_Engineer-015-M1 | K26: Wisma Mulia | L26: West Java | M26: 200003104092020 | N26: FPA1091IDN26031710640667 | O26: 1.0912026e+17 | P26: 1091HG3728823-3 | Q26: 21 | R26: 1 | S26: 8828132635 | T26: Project Delivery Monitoring Services - Project Engineer | U26: 34220600 | V26: 1 | W26: =_xlfn.XLOOKUP(J26,'Master Data 14-9-2026'!C:C,'Master Data 14-9-2026'!L:L) -> 1.5 | X26: 34220600 | Y26: 2026-05-08 | Z26: Ended | AA26: Approved | AD26: Invoice | AE26: =_xlfn.XLOOKUP(L26,'[1]ID PROJECT'!E:E,'[1]ID PROJECT'!F:F) -> PRJ-KUT-KPU-TPED-2026-04-00074 | AF26: SSO-KUT-KPU-NIUT-2026-06-03073 | AG26: 261/INV/KUT-PST/VI/2026 | AH26: 46197 | AI26: Juni
A27: QC-Quality_Control-006 | B27: =_xlfn.XLOOKUP(J27,'Master Data 14-9-2026'!C:C,'Master Data 14-9-2026'!D:D) -> Heri Kusnanto wx1503971 | D27: =_xlfn.XLOOKUP(J27,'Master Data 14-9-2026'!C:C,'Master Data 14-9-2026'!E:E) -> XLSMART | G27: M1 | H27: =_xlfn.XLOOKUP(J27,'Master Data 14-9-2026'!C:C,'Master Data 14-9-2026'!H:H) -> 2026-03-26 - 2026-04-25 | I27: =TEXT(DATEVALUE(LEFT(H27,10)),"mmmm") -> March | J27: QC-Quality_Control-006-M1 | K27: Wisma Mulia | L27: Jabodetabek | M27: 200003104100020 | N27: FPA1091IDN26031710640667 | O27: 1.0912026e+17 | P27: 1091HG3728823-3 | Q27: 22 | R27: 1 | S27: 8828132636 | T27: QEHS Onsite Monitoring and Inspection - QC | U27: 36992000 | V27: 1 | W27: =_xlfn.XLOOKUP(J27,'Master Data 14-9-2026'!C:C,'Master Data 14-9-2026'!L:L) -> 1.5 | X27: 36992000 | Y27: 2026-05-08 | Z27: Ended | AA27: Approved | AD27: Invoice | AE27: =_xlfn.XLOOKUP(L27,'[1]ID PROJECT'!E:E,'[1]ID PROJECT'!F:F) -> PRJ-KUT-KPU-TPED-2026-04-00071 | AF27: SSO-KUT-KPU-NIUT-2026-06-03073 | AG27: 261/INV/KUT-PST/VI/2026 | AH27: 46197 | AI27: Juni
A28: QC-Quality_Control-007 | B28: =_xlfn.XLOOKUP(J28,'Master Data 14-9-2026'!C:C,'Master Data 14-9-2026'!D:D) -> Herni Peruzi wx1503973 | D28: =_xlfn.XLOOKUP(J28,'Master Data 14-9-2026'!C:C,'Master Data 14-9-2026'!E:E) -> XLSMART | G28: M1 | H28: =_xlfn.XLOOKUP(J28,'Master Data 14-9-2026'!C:C,'Master Data 14-9-2026'!H:H) -> 2026-03-30 - 2026-04-29 | I28: =TEXT(DATEVALUE(LEFT(H28,10)),"mmmm") -> March | J28: QC-Quality_Control-007-M1 | K28: Wisma Mulia | L28: Jabodetabek | M28: 200003104101020 | N28: FPA1091IDN26031710640667 | O28: 1.0912026e+17 | P28: 1091HG3728823-3 | Q28: 23 | R28: 1 | S28: 8828132636 | T28: QEHS Onsite Monitoring and Inspection - QC | U28: 36992000 | V28: 1 | W28: =_xlfn.XLOOKUP(J28,'Master Data 14-9-2026'!C:C,'Master Data 14-9-2026'!L:L) -> 1.5 | X28: 36992000 | Y28: 2026-05-08 | Z28: Ended | AA28: Approved | AD28: Invoice | AE28: =_xlfn.XLOOKUP(L28,'[1]ID PROJECT'!E:E,'[1]ID PROJECT'!F:F) -> PRJ-KUT-KPU-TPED-2026-04-00071 | AF28: SSO-KUT-KPU-NIUT-2026-06-03073 | AG28: 261/INV/KUT-PST/VI/2026 | AH28: 46197 | AI28: Juni
A29: QC-Quality_Control-011 | B29: =_xlfn.XLOOKUP(J29,'Master Data 14-9-2026'!C:C,'Master Data 14-9-2026'!D:D) -> Julham Hamid wx1507139 | D29: =_xlfn.XLOOKUP(J29,'Master Data 14-9-2026'!C:C,'Master Data 14-9-2026'!E:E) -> XLSMART | G29: M1 | H29: =_xlfn.XLOOKUP(J29,'Master Data 14-9-2026'!C:C,'Master Data 14-9-2026'!H:H) -> 2026-04-01 - 2026-04-30 | I29: =TEXT(DATEVALUE(LEFT(H29,10)),"mmmm") -> April | J29: QC-Quality_Control-011-M1 | K29: Wisma Mulia | L29: Sulawesi | M29: 200003104102020 | N29: FPA1091IDN26031710640667 | O29: 1.0912026e+17 | P29: 1091HG3728823-3 | Q29: 24 | R29: 1 | S29: 8828132636 | T29: QEHS Onsite Monitoring and Inspection - QC | U29: 36992000 | V29: 1 | W29: =_xlfn.XLOOKUP(J29,'Master Data 14-9-2026'!C:C,'Master Data 14-9-2026'!L:L) -> 1.5 | X29: 36992000 | Y29: 2026-05-08 | Z29: Ended | AA29: Approved | AD29: Invoice | AE29: =_xlfn.XLOOKUP(L29,'[1]ID PROJECT'!E:E,'[1]ID PROJECT'!F:F) -> PRJ-KUT-KPU-TPED-2026-04-00080 | AF29: SSO-KUT-KPU-NIUT-2026-06-03073 | AG29: 261/INV/KUT-PST/VI/2026 | AH29: 46197 | AI29: Juni
A30: QC-Quality_Control-012 | B30: =_xlfn.XLOOKUP(J30,'Master Data 14-9-2026'!C:C,'Master Data 14-9-2026'!D:D) -> Muh Haidir Haswan wx1507136 | D30: =_xlfn.XLOOKUP(J30,'Master Data 14-9-2026'!C:C,'Master Data 14-9-2026'!E:E) -> XLSMART | G30: M1 | H30: =_xlfn.XLOOKUP(J30,'Master Data 14-9-2026'!C:C,'Master Data 14-9-2026'!H:H) -> 2026-04-01 - 2026-04-30 | I30: =TEXT(DATEVALUE(LEFT(H30,10)),"mmmm") -> April | J30: QC-Quality_Control-012-M1 | K30: Wisma Mulia | L30: Kalimantan | M30: 200003104103020 | N30: FPA1091IDN26031710640667 | O30: 1.0912026e+17 | P30: 1091HG3728823-3 | Q30: 25 | R30: 1 | S30: 8828132636 | T30: QEHS Onsite Monitoring and Inspection - QC | U30: 36992000 | V30: 1 | W30: =_xlfn.XLOOKUP(J30,'Master Data 14-9-2026'!C:C,'Master Data 14-9-2026'!L:L) -> 1.5 | X30: 36992000 | Y30: 2026-05-08 | Z30: Ended | AA30: Approved | AD30: Invoice | AE30: =_xlfn.XLOOKUP(L30,'[1]ID PROJECT'!E:E,'[1]ID PROJECT'!F:F) -> PRJ-KUT-KPU-TPED-2026-04-00079 | AF30: SSO-KUT-KPU-NIUT-2026-06-03073 | AG30: 261/INV/KUT-PST/VI/2026 | AH30: 46197 | AI30: Juni
A31: SE-Site_Engineer-002 | B31: =_xlfn.XLOOKUP(J31,'Master Data 14-9-2026'!C:C,'Master Data 14-9-2026'!D:D) -> Jepri Hamonangan Saragih wx1504646 | D31: =_xlfn.XLOOKUP(J31,'Master Data 14-9-2026'!C:C,'Master Data 14-9-2026'!E:E) -> XLSMART | G31: M1 | H31: =_xlfn.XLOOKUP(J31,'Master Data 14-9-2026'!C:C,'Master Data 14-9-2026'!H:H) -> 2026-03-23 - 2026-04-22 | I31: =TEXT(DATEVALUE(LEFT(H31,10)),"mmmm") -> March | J31: SE-Site_Engineer-002-M1 | K31: Wisma Mulia | L31: Sumatera | M31: 200003104104020 | N31: FPA1091IDN26031710640667 | O31: 1.0912026e+17 | P31: 1091HG3728823-3 | Q31: 26 | R31: 1 | S31: 8828132634 | T31: Project Delivery Monitoring Services - Site Engineer | U31: 32542400 | V31: 1 | W31: =_xlfn.XLOOKUP(J31,'Master Data 14-9-2026'!C:C,'Master Data 14-9-2026'!L:L) -> 0 | X31: 32542400 | Y31: 2026-05-08 | Z31: Ended | AA31: Approved | AD31: Invoice | AE31: =_xlfn.XLOOKUP(L31,'[1]ID PROJECT'!E:E,'[1]ID PROJECT'!F:F) -> PRJ-KUT-KPU-TPED-2026-04-00078 | AF31: SSO-KUT-KPU-NIUT-2026-06-03073 | AG31: 261/INV/KUT-PST/VI/2026 | AH31: 46197 | AI31: Juni
A32: SE-Site_Engineer-003 | B32: =_xlfn.XLOOKUP(J32,'Master Data 14-9-2026'!C:C,'Master Data 14-9-2026'!D:D) -> Anggie Bayu Setyawan wx1503644 | D32: =_xlfn.XLOOKUP(J32,'Master Data 14-9-2026'!C:C,'Master Data 14-9-2026'!E:E) -> XLSMART | G32: M1 | H32: =_xlfn.XLOOKUP(J32,'Master Data 14-9-2026'!C:C,'Master Data 14-9-2026'!H:H) -> 2026-03-23 - 2026-04-22 | I32: =TEXT(DATEVALUE(LEFT(H32,10)),"mmmm") -> March | J32: SE-Site_Engineer-003-M1 | K32: Wisma Mulia | L32: Bali Nusra | M32: 200003104105020 | N32: FPA1091IDN26031710640667 | O32: 1.0912026e+17 | P32: 1091HG3728823-3 | Q32: 27 | R32: 1 | S32: 8828132634 | T32: Project Delivery Monitoring Services - Site Engineer | U32: 32542400 | V32: 1 | W32: =_xlfn.XLOOKUP(J32,'Master Data 14-9-2026'!C:C,'Master Data 14-9-2026'!L:L) -> 0 | X32: 32542400 | Y32: 2026-05-08 | Z32: Ended | AA32: Approved | AD32: Invoice | AE32: =_xlfn.XLOOKUP(L32,'[1]ID PROJECT'!E:E,'[1]ID PROJECT'!F:F) -> PRJ-KUT-KPU-TPED-2026-04-00077 | AF32: SSO-KUT-KPU-NIUT-2026-06-03073 | AG32: 261/INV/KUT-PST/VI/2026 | AH32: 46197 | AI32: Juni
A33: SE-Site_Engineer-006 | B33: =_xlfn.XLOOKUP(J33,'Master Data 14-9-2026'!C:C,'Master Data 14-9-2026'!D:D) -> I Nyoman Satriya Wibawa wx1503651 | D33: =_xlfn.XLOOKUP(J33,'Master Data 14-9-2026'!C:C,'Master Data 14-9-2026'!E:E) -> IOH | G33: M1 | H33: =_xlfn.XLOOKUP(J33,'Master Data 14-9-2026'!C:C,'Master Data 14-9-2026'!H:H) -> 2026-03-30 - 2026-04-29 | I33: =TEXT(DATEVALUE(LEFT(H33,10)),"mmmm") -> March | J33: SE-Site_Engineer-006-M1 | K33: Wisma Mulia | L33: Bali Nusra | M33: 200003104106020 | N33: FPA1091IDN26031710640667 | O33: 1.0912026e+17 | P33: 1091HG3728823-3 | Q33: 28 | R33: 1 | S33: 8828132634 | T33: Project Delivery Monitoring Services - Site Engineer | U33: 32542400 | V33: 1 | W33: =_xlfn.XLOOKUP(J33,'Master Data 14-9-2026'!C:C,'Master Data 14-9-2026'!L:L) -> 0 | X33: 32542400 | Y33: 2026-05-08 | Z33: Ended | AA33: Approved | AD33: Invoice | AE33: =_xlfn.XLOOKUP(L33,'[1]ID PROJECT'!E:E,'[1]ID PROJECT'!F:F) -> PRJ-KUT-KPU-TPED-2026-04-00077 | AF33: SSO-KUT-KPU-NIUT-2026-06-03073 | AG33: 261/INV/KUT-PST/VI/2026 | AH33: 46197 | AI33: Juni
A34: SE-Site_Engineer-007 | B34: =_xlfn.XLOOKUP(J34,'Master Data 14-9-2026'!C:C,'Master Data 14-9-2026'!D:D) -> Ferry Anggriawan wx1503648 | D34: =_xlfn.XLOOKUP(J34,'Master Data 14-9-2026'!C:C,'Master Data 14-9-2026'!E:E) -> XLSMART | G34: M1 | H34: =_xlfn.XLOOKUP(J34,'Master Data 14-9-2026'!C:C,'Master Data 14-9-2026'!H:H) -> 2026-03-31 - 2026-04-29 | I34: =TEXT(DATEVALUE(LEFT(H34,10)),"mmmm") -> March | J34: SE-Site_Engineer-007-M1 | K34: Wisma Mulia | L34: Bali Nusra | M34: 200003104107020 | N34: FPA1091IDN26031710640667 | O34: 1.0912026e+17 | P34: 1091HG3728823-3 | Q34: 29 | R34: 1 | S34: 8828132634 | T34: Project Delivery Monitoring Services - Site Engineer | U34: 32542400 | V34: 1 | W34: =_xlfn.XLOOKUP(J34,'Master Data 14-9-2026'!C:C,'Master Data 14-9-2026'!L:L) -> 0 | X34: 32542400 | Y34: 2026-05-08 | Z34: Ended | AA34: Approved | AD34: Invoice | AE34: =_xlfn.XLOOKUP(L34,'[1]ID PROJECT'!E:E,'[1]ID PROJECT'!F:F) -> PRJ-KUT-KPU-TPED-2026-04-00077 | AF34: SSO-KUT-KPU-NIUT-2026-06-03073 | AG34: 261/INV/KUT-PST/VI/2026 | AH34: 46197 | AI34: Juni
A35: SE-Site_Engineer-009 | B35: =_xlfn.XLOOKUP(J35,'Master Data 14-9-2026'!C:C,'Master Data 14-9-2026'!D:D) -> #N/A | D35: =_xlfn.XLOOKUP(J35,'Master Data 14-9-2026'!C:C,'Master Data 14-9-2026'!E:E) -> #N/A | G35: M1 | H35: =_xlfn.XLOOKUP(J35,'Master Data 14-9-2026'!C:C,'Master Data 14-9-2026'!H:H) -> #N/A | I35: =TEXT(DATEVALUE(LEFT(H35,10)),"mmmm") -> #N/A | J35: SE-Site_Engineer-009-M1 | K35: Wisma Mulia | M35: 200003104108020 | N35: FPA1091IDN26031710640667 | O35: 1.0912026e+17 | P35: 1091HG3728823-3 | Q35: 30 | R35: 1 | S35: 8828132634 | T35: Project Delivery Monitoring Services - Site Engineer | U35: 32542400 | V35: 0 | W35: =_xlfn.XLOOKUP(J35,'Master Data 14-9-2026'!C:C,'Master Data 14-9-2026'!L:L) -> #N/A | X35: 0 | Y35: 2026-05-08 | Z35: Tidak ditemukan | AA35: Eror | AB35: Line tidak ada di Dashboard (email open task dashboard) | AE35: =_xlfn.XLOOKUP(L35,'[1]ID PROJECT'!E:E,'[1]ID PROJECT'!F:F) -> #N/A
A36: SE-Site_Engineer-010 | B36: =_xlfn.XLOOKUP(J36,'Master Data 14-9-2026'!C:C,'Master Data 14-9-2026'!D:D) -> Eko Syambudi Deviyanto wx1507285 | C36: SE010 XLFTTH CANCEL | D36: =_xlfn.XLOOKUP(J36,'Master Data 14-9-2026'!C:C,'Master Data 14-9-2026'!E:E) -> XL-FTTH | E36: XLSMART - SE010 | G36: M1 | H36: =_xlfn.XLOOKUP(J36,'Master Data 14-9-2026'!C:C,'Master Data 14-9-2026'!H:H) -> 2026-04-01 - 2026-04-30 | I36: =TEXT(DATEVALUE(LEFT(H36,10)),"mmmm") -> April | J36: SE-Site_Engineer-010-M1 | K36: Wisma Mulia | L36: Jabodetabek | M36: 200003104078020 | N36: FPA1091IDN26031710640667 | O36: 1.0912026e+17 | P36: 1091HG3728823-3 | Q36: 31 | R36: 1 | S36: 8828132634 | T36: Project Delivery Monitoring Services - Site Engineer | U36: 32542400 | V36: 1 | W36: =_xlfn.XLOOKUP(J36,'Master Data 14-9-2026'!C:C,'Master Data 14-9-2026'!L:L) -> 0 | X36: 32542400 | Y36: 2026-05-08 | Z36: Ended | AA36: Eror | AB36: Project assign tidak update (FTTH to XLSmart) | AC36: Confirm dean | AE36: =_xlfn.XLOOKUP(L36,'[1]ID PROJECT'!E:E,'[1]ID PROJECT'!F:F) -> PRJ-KUT-KPU-TPED-2026-04-00071
A37: PE-Project_Engineer-017 | B37: =_xlfn.XLOOKUP(J37,'Master Data 14-9-2026'!C:C,'Master Data 14-9-2026'!D:D) -> Dheanera Fairuz Hasna wx1507280 | D37: =_xlfn.XLOOKUP(J37,'Master Data 14-9-2026'!C:C,'Master Data 14-9-2026'!E:E) -> XLSMART | G37: M1 | H37: =_xlfn.XLOOKUP(J37,'Master Data 14-9-2026'!C:C,'Master Data 14-9-2026'!H:H) -> 2026-04-01 - 2026-04-30 | I37: =TEXT(DATEVALUE(LEFT(H37,10)),"mmmm") -> April | J37: PE-Project_Engineer-017-M1 | K37: Wisma Mulia | L37: Jabodetabek | M37: 200003104093020 | N37: FPA1091IDN26031710640667 | O37: 1.0912026e+17 | P37: 1091HG3728823-3 | Q37: 32 | R37: 1 | S37: 8828132635 | T37: Project Delivery Monitoring Services - Project Engineer | U37: 34220600 | V37: 1 | W37: =_xlfn.XLOOKUP(J37,'Master Data 14-9-2026'!C:C,'Master Data 14-9-2026'!L:L) -> 1.5 | X37: 34220600 | Y37: 2026-05-08 | Z37: Ended | AA37: Approved | AD37: Invoice | AE37: =_xlfn.XLOOKUP(L37,'[1]ID PROJECT'!E:E,'[1]ID PROJECT'!F:F) -> PRJ-KUT-KPU-TPED-2026-04-00071 | AF37: SSO-KUT-KPU-NIUT-2026-06-03073 | AG37: 261/INV/KUT-PST/VI/2026 | AH37: 46197 | AI37: Juni
A38: DC-Document_Controller-034 | B38: =_xlfn.XLOOKUP(J38,'Master Data 14-9-2026'!C:C,'Master Data 14-9-2026'!D:D) -> Raden Inna Rachmasetia wx1506939 | D38: =_xlfn.XLOOKUP(J38,'Master Data 14-9-2026'!C:C,'Master Data 14-9-2026'!E:E) -> XL-FTTH | G38: M1 | H38: =_xlfn.XLOOKUP(J38,'Master Data 14-9-2026'!C:C,'Master Data 14-9-2026'!H:H) -> 2026-04-01 - 2026-04-30 | I38: =TEXT(DATEVALUE(LEFT(H38,10)),"mmmm") -> April | J38: DC-Document_Controller-034-M1 | K38: DC-Document_Controller-034-M1 | L38: Jabodetabek | M38: 200003103307020 | N38: FPA1091IDN26031710640667 | O38: 1.0912026e+17 | P38: 1091HG3728823-4 | Q38: 1 | R38: 1 | S38: 8828132633 | T38: Project Delivery Monitoring Services - Document Control | U38: 28881900 | V38: 1 | W38: =_xlfn.XLOOKUP(J38,'Master Data 14-9-2026'!C:C,'Master Data 14-9-2026'!L:L) -> 1.5 | X38: 28881900 | Y38: 2026-05-11 | Z38: Ended | AA38: Approved | AD38: Invoice | AE38: =_xlfn.XLOOKUP(L38,'[1]ID PROJECT'!E:E,'[1]ID PROJECT'!F:F) -> PRJ-KUT-KPU-TPED-2026-04-00071 | AF38: SSO-KUT-KPU-NIUT-2026-08-04128 | AG38: 341/INV/KUT-PST/VIII/2026 | AH38: 46221 | AI38: Juli
A39: DC-Document_Controller-022 | B39: =_xlfn.XLOOKUP(J39,'Master Data 14-9-2026'!C:C,'Master Data 14-9-2026'!D:D) -> Alifya Rahma Asy Syaffa wx1504637 | D39: =_xlfn.XLOOKUP(J39,'Master Data 14-9-2026'!C:C,'Master Data 14-9-2026'!E:E) -> Surge | G39: M1 | H39: =_xlfn.XLOOKUP(J39,'Master Data 14-9-2026'!C:C,'Master Data 14-9-2026'!H:H) -> 2026-04-01 - 2026-04-30 | I39: =TEXT(DATEVALUE(LEFT(H39,10)),"mmmm") -> April | J39: DC-Document_Controller-022-M1 | K39: DC-Document_Controller-022-M1 | L39: Jabodetabek | M39: 200003106222020 | N39: FPA1091IDN26031710640667 | O39: 1.0912026e+17 | P39: 1091HG3728823-5 | Q39: 1 | R39: 1 | S39: 8828132633 | T39: Project Delivery Monitoring Services - Document Control | U39: 28881900 | V39: 1 | W39: =_xlfn.XLOOKUP(J39,'Master Data 14-9-2026'!C:C,'Master Data 14-9-2026'!L:L) -> 1.01 | X39: 28881900 | Y39: 2026-05-18 | Z39: Ended | AA39: Approved | AD39: Invoice | AE39: =_xlfn.XLOOKUP(L39,'[1]ID PROJECT'!E:E,'[1]ID PROJECT'!F:F) -> PRJ-KUT-KPU-TPED-2026-04-00071 | AF39: SSO-KUT-KPU-NIUT-2026-07-03352 | AG39: 287/INV/KUT-PST/VII/2026 | AH39: 46216 | AI39: Juli
A40: QC-Quality_Control-021 | B40: =_xlfn.XLOOKUP(J40,'Master Data 14-9-2026'!C:C,'Master Data 14-9-2026'!D:D) -> Kamiludin Hartanto wx1517183 | D40: =_xlfn.XLOOKUP(J40,'Master Data 14-9-2026'!C:C,'Master Data 14-9-2026'!E:E) -> Surge | G40: M1 | H40: =_xlfn.XLOOKUP(J40,'Master Data 14-9-2026'!C:C,'Master Data 14-9-2026'!H:H) -> 2026-05-05 - 2026-06-04 | I40: =TEXT(DATEVALUE(LEFT(H40,10)),"mmmm") -> May | J40: QC-Quality_Control-021-M1 | K40: QC-Quality_Control-021-M1 | L40: East Java | M40: 200003106224020 | N40: FPA1091IDN26031710640667 | O40: 1.0912026e+17 | P40: 1091HG3728823-5 | Q40: 2 | R40: 1 | S40: 8828132636 | T40: QEHS Onsite Monitoring and Inspection - QC | U40: 36992000 | V40: 1 | W40: =_xlfn.XLOOKUP(J40,'Master Data 14-9-2026'!C:C,'Master Data 14-9-2026'!L:L) -> 1.5 | X40: 36992000 | Y40: 2026-05-18 | Z40: Ended | AA40: Approved | AD40: Invoice | AE40: =_xlfn.XLOOKUP(L40,'[1]ID PROJECT'!E:E,'[1]ID PROJECT'!F:F) -> PRJ-KUT-KPU-TPED-2026-04-00076 | AF40: SSO-KUT-KPU-NIUT-2026-07-03352 | AG40: 287/INV/KUT-PST/VII/2026 | AH40: 46216 | AI40: Juli
A41: PE-Project_Engineer-025 | B41: =_xlfn.XLOOKUP(J41,'Master Data 14-9-2026'!C:C,'Master Data 14-9-2026'!D:D) -> Wayan Gde Krisna wx1516087 | D41: =_xlfn.XLOOKUP(J41,'Master Data 14-9-2026'!C:C,'Master Data 14-9-2026'!E:E) -> Surge | G41: M1 | H41: =_xlfn.XLOOKUP(J41,'Master Data 14-9-2026'!C:C,'Master Data 14-9-2026'!H:H) -> 2026-04-27 - 2026-05-26 | I41: =TEXT(DATEVALUE(LEFT(H41,10)),"mmmm") -> April | J41: PE-Project_Engineer-025-M1 | K41: PE-Project_Engineer-025-M1 | L41: Jabodetabek | M41: 200003106223020 | N41: FPA1091IDN26031710640667 | O41: 1.0912026e+17 | P41: 1091HG3728823-5 | Q41: 3 | R41: 1 | S41: 8828132635 | T41: Project Delivery Monitoring Services - Project Engineer | U41: 34220600 | V41: 1 | W41: =_xlfn.XLOOKUP(J41,'Master Data 14-9-2026'!C:C,'Master Data 14-9-2026'!L:L) -> 0.5 | X41: 34220600 | Y41: 2026-05-18 | Z41: Ended | AA41: Approved | AD41: Invoice | AE41: =_xlfn.XLOOKUP(L41,'[1]ID PROJECT'!E:E,'[1]ID PROJECT'!F:F) -> PRJ-KUT-KPU-TPED-2026-04-00071 | AF41: SSO-KUT-KPU-NIUT-2026-07-03352 | AG41: 287/INV/KUT-PST/VII/2026 | AH41: 46216 | AI41: Juli
A42: PE-Project_Engineer-011 | B42: =_xlfn.XLOOKUP(J42,'Master Data 14-9-2026'!C:C,'Master Data 14-9-2026'!D:D) -> Robby Awaludin wx1503642 | D42: =_xlfn.XLOOKUP(J42,'Master Data 14-9-2026'!C:C,'Master Data 14-9-2026'!E:E) -> XLSMART-NWL | G42: M1 | H42: =_xlfn.XLOOKUP(J42,'Master Data 14-9-2026'!C:C,'Master Data 14-9-2026'!H:H) -> 2026-03-30 - 2026-04-29 | I42: =TEXT(DATEVALUE(LEFT(H42,10)),"mmmm") -> March | J42: PE-Project_Engineer-011-M1 | K42: Huawei ASEAN Academy | L42: East Java | M42: 200003103271020 | N42: FPA1091IDN26031710640667 | O42: 1.0912026e+17 | P42: 1091HG3728823-6 | Q42: 2 | R42: 1 | S42: 8828132635 | T42: Project Delivery Monitoring Services - Project Engineer | U42: 34220600 | V42: 1 | W42: =_xlfn.XLOOKUP(J42,'Master Data 14-9-2026'!C:C,'Master Data 14-9-2026'!L:L) -> 1 | X42: 34220600 | Y42: 2026-05-18 | Z42: =_xlfn.XLOOKUP(J42,'Master Data 14-9-2026'!C:C,'Master Data 14-9-2026'!I:I) -> Ended | AA42: Approved | AD42: Invoice | AE42: =_xlfn.XLOOKUP(L42,'[1]ID PROJECT'!E:E,'[1]ID PROJECT'!F:F) -> PRJ-KUT-KPU-TPED-2026-04-00076 | AF42: SSO-KUT-KPU-NIUT-2026-06-03245 | AG42: 270/INV/KUT-PST/VI/2026 | AH42: 46202 | AI42: Juni
A43: SE-Site_Engineer-008 | B43: =_xlfn.XLOOKUP(J43,'Master Data 14-9-2026'!C:C,'Master Data 14-9-2026'!D:D) -> Aktortifan Ridno Prabu Pratama wx1507287 | D43: =_xlfn.XLOOKUP(J43,'Master Data 14-9-2026'!C:C,'Master Data 14-9-2026'!E:E) -> XLSMART-NWL | G43: M1 | H43: =_xlfn.XLOOKUP(J43,'Master Data 14-9-2026'!C:C,'Master Data 14-9-2026'!H:H) -> 2026-04-01 - 2026-04-30 | I43: =TEXT(DATEVALUE(LEFT(H43,10)),"mmmm") -> April | J43: SE-Site_Engineer-008-M1 | K43: Huawei ASEAN Academy | L43: West Java | M43: 200003103272020 | N43: FPA1091IDN26031710640667 | O43: 1.0912026e+17 | P43: 1091HG3728823-6 | Q43: 3 | R43: 1 | S43: 8828132634 | T43: Project Delivery Monitoring Services - Site Engineer | U43: 32542400 | V43: 1 | W43: =_xlfn.XLOOKUP(J43,'Master Data 14-9-2026'!C:C,'Master Data 14-9-2026'!L:L) -> 0 | X43: 32542400 | Y43: 2026-05-18 | Z43: Ended | AA43: Approved | AD43: Invoice | AE43: =_xlfn.XLOOKUP(L43,'[1]ID PROJECT'!E:E,'[1]ID PROJECT'!F:F) -> PRJ-KUT-KPU-TPED-2026-04-00074 | AF43: SSO-KUT-KPU-NIUT-2026-06-03245 | AG43: 270/INV/KUT-PST/VI/2026 | AH43: 46202 | AI43: Juni
A44: SE-Site_Engineer-011 | B44: =_xlfn.XLOOKUP(J44,'Master Data 14-9-2026'!C:C,'Master Data 14-9-2026'!D:D) -> Ahmad Faqih wx1507096 | D44: =_xlfn.XLOOKUP(J44,'Master Data 14-9-2026'!C:C,'Master Data 14-9-2026'!E:E) -> XLSMART | G44: M1 | H44: =_xlfn.XLOOKUP(J44,'Master Data 14-9-2026'!C:C,'Master Data 14-9-2026'!H:H) -> 2026-04-01 - 2026-04-30 | I44: =TEXT(DATEVALUE(LEFT(H44,10)),"mmmm") -> April | J44: SE-Site_Engineer-011-M1 | K44: Huawei ASEAN Academy | L44: Jabodetabek | M44: 200003103273020 | N44: FPA1091IDN26031710640667 | O44: 1.0912026e+17 | P44: 1091HG3728823-6 | Q44: 4 | R44: 1 | S44: 8828132634 | T44: Project Delivery Monitoring Services - Site Engineer | U44: 32542400 | V44: 1 | W44: =_xlfn.XLOOKUP(J44,'Master Data 14-9-2026'!C:C,'Master Data 14-9-2026'!L:L) -> 0 | X44: 32542400 | Y44: 2026-05-18 | Z44: Ended | AA44: Eror | AB44: Gagal submit | AE44: =_xlfn.XLOOKUP(L44,'[1]ID PROJECT'!E:E,'[1]ID PROJECT'!F:F) -> PRJ-KUT-KPU-TPED-2026-04-00071
A45: SE-Site_Engineer-013 | B45: =_xlfn.XLOOKUP(J45,'Master Data 14-9-2026'!C:C,'Master Data 14-9-2026'!D:D) -> #N/A | D45: =_xlfn.XLOOKUP(J45,'Master Data 14-9-2026'!C:C,'Master Data 14-9-2026'!E:E) -> #N/A | G45: M1 | H45: =_xlfn.XLOOKUP(J45,'Master Data 14-9-2026'!C:C,'Master Data 14-9-2026'!H:H) -> #N/A | I45: =TEXT(DATEVALUE(LEFT(H45,10)),"mmmm") -> #N/A | J45: SE-Site_Engineer-013-M1 | K45: Huawei ASEAN Academy | L45: Jabodetabek | M45: 200003103274020 | N45: FPA1091IDN26031710640667 | O45: 1.0912026e+17 | P45: 1091HG3728823-6 | Q45: 5 | R45: 1 | S45: 8828132634 | T45: Project Delivery Monitoring Services - Site Engineer | U45: 32542400 | V45: 1 | W45: =_xlfn.XLOOKUP(J45,'Master Data 14-9-2026'!C:C,'Master Data 14-9-2026'!L:L) -> #N/A | X45: 32542400 | Y45: 2026-05-18 | Z45: Ended | AA45: Approved | AD45: Invoice | AE45: =_xlfn.XLOOKUP(L45,'[1]ID PROJECT'!E:E,'[1]ID PROJECT'!F:F) -> PRJ-KUT-KPU-TPED-2026-04-00071 | AF45: SSO-KUT-KPU-NIUT-2026-06-03245 | AG45: 270/INV/KUT-PST/VI/2026 | AH45: 46202 | AI45: Juni
A46: SE-Site_Engineer-014 | B46: =_xlfn.XLOOKUP(J46,'Master Data 14-9-2026'!C:C,'Master Data 14-9-2026'!D:D) -> #N/A | D46: =_xlfn.XLOOKUP(J46,'Master Data 14-9-2026'!C:C,'Master Data 14-9-2026'!E:E) -> #N/A | G46: M1 | H46: =_xlfn.XLOOKUP(J46,'Master Data 14-9-2026'!C:C,'Master Data 14-9-2026'!H:H) -> #N/A | I46: =TEXT(DATEVALUE(LEFT(H46,10)),"mmmm") -> #N/A | J46: SE-Site_Engineer-014-M1 | K46: Huawei ASEAN Academy | L46: Jabodetabek | M46: 200003103275020 | N46: FPA1091IDN26031710640667 | O46: 1.0912026e+17 | P46: 1091HG3728823-6 | Q46: 6 | R46: 1 | S46: 8828132634 | T46: Project Delivery Monitoring Services - Site Engineer | U46: 32542400 | V46: 1 | W46: =_xlfn.XLOOKUP(J46,'Master Data 14-9-2026'!C:C,'Master Data 14-9-2026'!L:L) -> #N/A | X46: 32542400 | Y46: 2026-05-18 | Z46: Ended | AA46: Approved | AD46: Invoice | AE46: =_xlfn.XLOOKUP(L46,'[1]ID PROJECT'!E:E,'[1]ID PROJECT'!F:F) -> PRJ-KUT-KPU-TPED-2026-04-00071 | AF46: SSO-KUT-KPU-NIUT-2026-06-03245 | AG46: 270/INV/KUT-PST/VI/2026 | AH46: 46202 | AI46: Juni
A47: PE-Project_Engineer-023 | B47: =_xlfn.XLOOKUP(J47,'Master Data 14-9-2026'!C:C,'Master Data 14-9-2026'!D:D) -> Slamet Riyanto wx1503652 | C47: from SE-012 | D47: =_xlfn.XLOOKUP(J47,'Master Data 14-9-2026'!C:C,'Master Data 14-9-2026'!E:E) -> TELKOMSEL | E47: TSEL - PE023 | G47: M1 | H47: =_xlfn.XLOOKUP(J47,'Master Data 14-9-2026'!C:C,'Master Data 14-9-2026'!H:H) -> 2026-04-01 - 2026-04-30 | I47: =TEXT(DATEVALUE(LEFT(H47,10)),"mmmm") -> April | J47: PE-Project_Engineer-023-M1 | K47: Huawei ASEAN Academy | L47: Central Java | M47: 200003106221020 | N47: FPA1091IDN26031710640667 | O47: 1.0912026e+17 | P47: 1091HG3728823-6 | Q47: 7 | R47: 1 | S47: 8828132635 | T47: Project Delivery Monitoring Services - Project Engineer | U47: 34220600 | V47: 1 | W47: =_xlfn.XLOOKUP(J47,'Master Data 14-9-2026'!C:C,'Master Data 14-9-2026'!L:L) -> 1 | X47: 34220600 | Y47: 2026-05-18 | Z47: =_xlfn.XLOOKUP(J47,'Master Data 14-9-2026'!C:C,'Master Data 14-9-2026'!I:I) -> Ended | AA47: Approved | AB47: Cancel PO | AE47: =_xlfn.XLOOKUP(L47,'[1]ID PROJECT'!E:E,'[1]ID PROJECT'!F:F) -> PRJ-KUT-KPU-TPED-2026-04-00075 | AF47: SSO-KUT-KPU-NIUT-2026-08-04009 | AJ47: move to PO 1091HG3728823-67
A48: DC-Document_Controller-031 | B48: =_xlfn.XLOOKUP(J48,'Master Data 14-9-2026'!C:C,'Master Data 14-9-2026'!D:D) -> Youlanda wx1506944 | D48: =_xlfn.XLOOKUP(J48,'Master Data 14-9-2026'!C:C,'Master Data 14-9-2026'!E:E) -> TELKOM | G48: M1 | H48: =_xlfn.XLOOKUP(J48,'Master Data 14-9-2026'!C:C,'Master Data 14-9-2026'!H:H) -> 2026-04-01 - 2026-04-30 | I48: =TEXT(DATEVALUE(LEFT(H48,10)),"mmmm") -> April | J48: DC-Document_Controller-031-M1 | K48: STO Jatinegara | L48: Jabodetabek | M48: 200003106348020 | N48: FPA1091IDN26031710640667 | O48: 1.0912026e+17 | P48: 1091HG3728823-7 | Q48: 1 | R48: 1 | S48: 8828132633 | T48: Project Delivery Monitoring Services - Document Control | U48: 28881900 | V48: 1 | W48: =_xlfn.XLOOKUP(J48,'Master Data 14-9-2026'!C:C,'Master Data 14-9-2026'!L:L) -> 0 | X48: 28881900 | Y48: 2026-05-18 | Z48: Ended | AA48: Approved | AD48: Invoice | AE48: =_xlfn.XLOOKUP(L48,'[1]ID PROJECT'!E:E,'[1]ID PROJECT'!F:F) -> PRJ-KUT-KPU-TPED-2026-04-00071 | AF48: SSO-KUT-KPU-NIUT-2026-06-03265 | AG48: 256/INV/KUT-PST/VI/2026 | AH48: 46197 | AI48: Juni
A49: DC-Document_Controller-016 | B49: =_xlfn.XLOOKUP(J49,'Master Data 14-9-2026'!C:C,'Master Data 14-9-2026'!D:D) -> Fasya Fatimma Azzhra wx1504711 | D49: =_xlfn.XLOOKUP(J49,'Master Data 14-9-2026'!C:C,'Master Data 14-9-2026'!E:E) -> IOH | G49: M1 | H49: =_xlfn.XLOOKUP(J49,'Master Data 14-9-2026'!C:C,'Master Data 14-9-2026'!H:H) -> 2026-03-31 - 2026-04-29 | I49: =TEXT(DATEVALUE(LEFT(H49,10)),"mmmm") -> March | J49: DC-Document_Controller-016-M1 | K49: DC-Document_Controller-016-M1 | L49: Jabodetabek | M49: 200003102317020 | N49: FPA1091IDN26031710640667 | O49: 1.0912026e+17 | P49: 1091HG3728823-8 | Q49: 1 | R49: 1 | S49: 8828132633 | T49: Project Delivery Monitoring Services - Document Control | U49: 28881900 | V49: 1 | W49: =_xlfn.XLOOKUP(J49,'Master Data 14-9-2026'!C:C,'Master Data 14-9-2026'!L:L) -> 0 | X49: 28881900 | Y49: 2026-05-20 | Z49: Ended | AA49: Approved | AD49: Invoice | AE49: =_xlfn.XLOOKUP(L49,'[1]ID PROJECT'!E:E,'[1]ID PROJECT'!F:F) -> PRJ-KUT-KPU-TPED-2026-04-00071 | AF49: SSO-KUT-KPU-NIUT-2026-06-03066 | AG49: 257/INV/KUT-PST/VI/2026 | AH49: 46197 | AI49: Juni
A50: PE-Project_Engineer-003 | B50: =_xlfn.XLOOKUP(J50,'Master Data 14-9-2026'!C:C,'Master Data 14-9-2026'!D:D) -> Chaerul Oky Suryatin wx1503975 | D50: =_xlfn.XLOOKUP(J50,'Master Data 14-9-2026'!C:C,'Master Data 14-9-2026'!E:E) -> IOH | G50: M1 | H50: =_xlfn.XLOOKUP(J50,'Master Data 14-9-2026'!C:C,'Master Data 14-9-2026'!H:H) -> 2026-03-23 - 2026-04-22 | I50: =TEXT(DATEVALUE(LEFT(H50,10)),"mmmm") -> March | J50: PE-Project_Engineer-003-M1 | K50: PE-Project_Engineer-003-M1 | L50: West Java | M50: 200003102323020 | N50: FPA1091IDN26031710640667 | O50: 1.0912026e+17 | P50: 1091HG3728823-8 | Q50: 2 | R50: 1 | S50: 8828132635 | T50: Project Delivery Monitoring Services - Project Engineer | U50: 34220600 | V50: 1 | W50: =_xlfn.XLOOKUP(J50,'Master Data 14-9-2026'!C:C,'Master Data 14-9-2026'!L:L) -> 1 | X50: 34220600 | Y50: 2026-05-20 | Z50: =_xlfn.XLOOKUP(J50,'Master Data 14-9-2026'!C:C,'Master Data 14-9-2026'!I:I) -> Ended | AA50: Approved | AD50: Invoice | AE50: =_xlfn.XLOOKUP(L50,'[1]ID PROJECT'!E:E,'[1]ID PROJECT'!F:F) -> PRJ-KUT-KPU-TPED-2026-04-00074 | AF50: SSO-KUT-KPU-NIUT-2026-06-03066 | AG50: 257/INV/KUT-PST/VI/2026 | AH50: 46197 | AI50: Juni
A51: SE-Site_Engineer-018 | B51: =_xlfn.XLOOKUP(J51,'Master Data 14-9-2026'!C:C,'Master Data 14-9-2026'!D:D) -> Amar Aditia Wilujeng wx1520521 | D51: =_xlfn.XLOOKUP(J51,'Master Data 14-9-2026'!C:C,'Master Data 14-9-2026'!E:E) -> IOH | G51: M1 | H51: =_xlfn.XLOOKUP(J51,'Master Data 14-9-2026'!C:C,'Master Data 14-9-2026'!H:H) -> 2026-05-15 - 2026-06-14 | I51: =TEXT(DATEVALUE(LEFT(H51,10)),"mmmm") -> May | J51: SE-Site_Engineer-018-M1 | K51: SE-Site_Engineer-018-M1 | L51: Jabodetabek | M51: 200003120936020 | N51: FPA1091IDN26031710640667 | O51: 1.0912026e+17 | P51: 1091HG3728823-8 | Q51: 3 | R51: 1 | S51: 8828132634 | T51: Project Delivery Monitoring Services - Site Engineer | U51: 32542400 | V51: 1 | W51: =_xlfn.XLOOKUP(J51,'Master Data 14-9-2026'!C:C,'Master Data 14-9-2026'!L:L) -> 0 | X51: 32542400 | Y51: 2026-05-20 | Z51: Ended | AA51: Approved | AD51: Invoice | AE51: =_xlfn.XLOOKUP(L51,'[1]ID PROJECT'!E:E,'[1]ID PROJECT'!F:F) -> PRJ-KUT-KPU-TPED-2026-04-00071 | AF51: SSO-KUT-KPU-NIUT-2026-06-03066 | AG51: 257/INV/KUT-PST/VI/2026 | AH51: 46197 | AI51: Juni
A52: DC-Document_Controller-004 | B52: =_xlfn.XLOOKUP(J52,'Master Data 14-9-2026'!C:C,'Master Data 14-9-2026'!D:D) -> Hyang Iman Kinasih Gusti wx1503650 | D52: =_xlfn.XLOOKUP(J52,'Master Data 14-9-2026'!C:C,'Master Data 14-9-2026'!E:E) -> IOH | E52: IOH - DC004 | G52: M1 | H52: =_xlfn.XLOOKUP(J52,'Master Data 14-9-2026'!C:C,'Master Data 14-9-2026'!H:H) -> 2026-03-23 - 2026-04-22 | I52: =TEXT(DATEVALUE(LEFT(H52,10)),"mmmm") -> March | J52: DC-Document_Controller-004-M1 | K52: DC-Document_Controller-004-M1 | L52: East Java | M52: 200003102331020 | N52: FPA1091IDN26031710640667 | O52: 1.0912026e+17 | P52: 1091HG3728823-8 | Q52: 4 | R52: 1 | S52: 8828132633 | T52: Project Delivery Monitoring Services - Document Control | U52: 28881900 | V52: 1 | W52: =_xlfn.XLOOKUP(J52,'Master Data 14-9-2026'!C:C,'Master Data 14-9-2026'!L:L) -> 1.5 | X52: 28881900 | Y52: 2026-05-20 | Z52: Ended | AB52: Up baseline | AC52: Confirm dean | AE52: =_xlfn.XLOOKUP(L52,'[1]ID PROJECT'!E:E,'[1]ID PROJECT'!F:F) -> PRJ-KUT-KPU-TPED-2026-04-00076
A53: PE-Project_Engineer-002 | B53: =_xlfn.XLOOKUP(J53,'Master Data 14-9-2026'!C:C,'Master Data 14-9-2026'!D:D) -> Johannes Julfery Damanik wx1504705 | D53: =_xlfn.XLOOKUP(J53,'Master Data 14-9-2026'!C:C,'Master Data 14-9-2026'!E:E) -> IOH | G53: M1 | H53: =_xlfn.XLOOKUP(J53,'Master Data 14-9-2026'!C:C,'Master Data 14-9-2026'!H:H) -> 2026-03-23 - 2026-04-22 | I53: =TEXT(DATEVALUE(LEFT(H53,10)),"mmmm") -> March | J53: PE-Project_Engineer-002-M1 | K53: PE-Project_Engineer-002-M1 | L53: Kalimantan | M53: 200003102322020 | N53: FPA1091IDN26031710640667 | O53: 1.0912026e+17 | P53: 1091HG3728823-8 | Q53: 5 | R53: 1 | S53: 8828132635 | T53: Project Delivery Monitoring Services - Project Engineer | U53: 34220600 | V53: 1 | W53: =_xlfn.XLOOKUP(J53,'Master Data 14-9-2026'!C:C,'Master Data 14-9-2026'!L:L) -> 1.5 | X53: 34220600 | Y53: 2026-05-20 | Z53: Ended | AA53: Approved | AD53: Invoice | AE53: =_xlfn.XLOOKUP(L53,'[1]ID PROJECT'!E:E,'[1]ID PROJECT'!F:F) -> PRJ-KUT-KPU-TPED-2026-04-00079 | AF53: SSO-KUT-KPU-NIUT-2026-06-03066 | AG53: 257/INV/KUT-PST/VI/2026 | AH53: 46197 | AI53: Juni
A54: DC-Document_Controller-010 | B54: =_xlfn.XLOOKUP(J54,'Master Data 14-9-2026'!C:C,'Master Data 14-9-2026'!D:D) -> Wahyuni wx1504701 | D54: =_xlfn.XLOOKUP(J54,'Master Data 14-9-2026'!C:C,'Master Data 14-9-2026'!E:E) -> Platform Region | G54: M1 | H54: =_xlfn.XLOOKUP(J54,'Master Data 14-9-2026'!C:C,'Master Data 14-9-2026'!H:H) -> 2026-03-30 - 2026-04-29 | I54: =TEXT(DATEVALUE(LEFT(H54,10)),"mmmm") -> March | J54: DC-Document_Controller-010-M1 | K54: DC-Document_Controller-010-M1 | L54: Sulawesi | M54: 200003102332020 | N54: FPA1091IDN26031710640667 | O54: 1.0912026e+17 | P54: 1091HG3728823-8 | Q54: 6 | R54: 1 | S54: 8828132633 | T54: Project Delivery Monitoring Services - Document Control | U54: 28881900 | V54: 1 | W54: =_xlfn.XLOOKUP(J54,'Master Data 14-9-2026'!C:C,'Master Data 14-9-2026'!L:L) -> 0.5 | X54: 28881900 | Y54: 2026-05-20 | Z54: Ended | AA54: Approved | AD54: Invoice | AE54: =_xlfn.XLOOKUP(L54,'[1]ID PROJECT'!E:E,'[1]ID PROJECT'!F:F) -> PRJ-KUT-KPU-TPED-2026-04-00080 | AF54: SSO-KUT-KPU-NIUT-2026-06-03066 | AG54: 257/INV/KUT-PST/VI/2026 | AH54: 46197 | AI54: Juni
A55: SE-Site_Engineer-017 | B55: =_xlfn.XLOOKUP(J55,'Master Data 14-9-2026'!C:C,'Master Data 14-9-2026'!D:D) -> Sergius Paulus Sinaga wx1520524 | D55: =_xlfn.XLOOKUP(J55,'Master Data 14-9-2026'!C:C,'Master Data 14-9-2026'!E:E) -> IOH | G55: M1 | H55: =_xlfn.XLOOKUP(J55,'Master Data 14-9-2026'!C:C,'Master Data 14-9-2026'!H:H) -> 2026-05-15 - 2026-06-14 | I55: =TEXT(DATEVALUE(LEFT(H55,10)),"mmmm") -> May | J55: SE-Site_Engineer-017-M1 | K55: SE-Site_Engineer-017-M1 | L55: Jabodetabek | M55: 200003120935020 | N55: FPA1091IDN26031710640667 | O55: 1.0912026e+17 | P55: 1091HG3728823-8 | Q55: 7 | R55: 1 | S55: 8828132634 | T55: Project Delivery Monitoring Services - Site Engineer | U55: 32542400 | V55: 1 | W55: =_xlfn.XLOOKUP(J55,'Master Data 14-9-2026'!C:C,'Master Data 14-9-2026'!L:L) -> 0 | X55: 32542400 | Y55: 2026-05-20 | Z55: Ended | AA55: Approved | AD55: Invoice | AE55: =_xlfn.XLOOKUP(L55,'[1]ID PROJECT'!E:E,'[1]ID PROJECT'!F:F) -> PRJ-KUT-KPU-TPED-2026-04-00071 | AF55: SSO-KUT-KPU-NIUT-2026-06-03066 | AG55: 257/INV/KUT-PST/VI/2026 | AH55: 46197 | AI55: Juni
A56: DC-Document_Controller-011 | B56: =_xlfn.XLOOKUP(J56,'Master Data 14-9-2026'!C:C,'Master Data 14-9-2026'!D:D) -> Fitra Faradilla wx1504702 | D56: =_xlfn.XLOOKUP(J56,'Master Data 14-9-2026'!C:C,'Master Data 14-9-2026'!E:E) -> IOH | G56: M1 | H56: =_xlfn.XLOOKUP(J56,'Master Data 14-9-2026'!C:C,'Master Data 14-9-2026'!H:H) -> 2026-03-30 - 2026-04-29 | I56: =TEXT(DATEVALUE(LEFT(H56,10)),"mmmm") -> March | J56: DC-Document_Controller-011-M1 | K56: DC-Document_Controller-011-M1 | L56: Sulawesi | M56: 200003102314020 | N56: FPA1091IDN26031710640667 | O56: 1.0912026e+17 | P56: 1091HG3728823-8 | Q56: 8 | R56: 1 | S56: 8828132633 | T56: Project Delivery Monitoring Services - Document Control | U56: 28881900 | V56: 1 | W56: =_xlfn.XLOOKUP(J56,'Master Data 14-9-2026'!C:C,'Master Data 14-9-2026'!L:L) -> 1 | X56: 28881900 | Y56: 2026-05-20 | Z56: =_xlfn.XLOOKUP(J56,'Master Data 14-9-2026'!C:C,'Master Data 14-9-2026'!I:I) -> Ended | AA56: Approved | AD56: Invoice | AE56: =_xlfn.XLOOKUP(L56,'[1]ID PROJECT'!E:E,'[1]ID PROJECT'!F:F) -> PRJ-KUT-KPU-TPED-2026-04-00080 | AF56: SSO-KUT-KPU-NIUT-2026-06-03066 | AG56: 257/INV/KUT-PST/VI/2026 | AH56: 46197 | AI56: Juni
A57: DC-Document_Controller-013 | B57: =_xlfn.XLOOKUP(J57,'Master Data 14-9-2026'!C:C,'Master Data 14-9-2026'!D:D) -> Eka Maudyna Isdyanti wx1504640 | D57: =_xlfn.XLOOKUP(J57,'Master Data 14-9-2026'!C:C,'Master Data 14-9-2026'!E:E) -> IOH | G57: M1 | H57: =_xlfn.XLOOKUP(J57,'Master Data 14-9-2026'!C:C,'Master Data 14-9-2026'!H:H) -> 2026-03-30 - 2026-04-29 | I57: =TEXT(DATEVALUE(LEFT(H57,10)),"mmmm") -> March | J57: DC-Document_Controller-013-M1 | K57: DC-Document_Controller-013-M1 | L57: Jabodetabek | M57: 200003102315020 | N57: FPA1091IDN26031710640667 | O57: 1.0912026e+17 | P57: 1091HG3728823-8 | Q57: 9 | R57: 1 | S57: 8828132633 | T57: Project Delivery Monitoring Services - Document Control | U57: 28881900 | V57: 1 | W57: =_xlfn.XLOOKUP(J57,'Master Data 14-9-2026'!C:C,'Master Data 14-9-2026'!L:L) -> 0 | X57: 28881900 | Y57: 2026-05-20 | Z57: Ended | AA57: Approved | AD57: Invoice | AE57: =_xlfn.XLOOKUP(L57,'[1]ID PROJECT'!E:E,'[1]ID PROJECT'!F:F) -> PRJ-KUT-KPU-TPED-2026-04-00071 | AF57: SSO-KUT-KPU-NIUT-2026-06-03066 | AG57: 257/INV/KUT-PST/VI/2026 | AH57: 46197 | AI57: Juni
A58: DC-Document_Controller-015 | B58: =_xlfn.XLOOKUP(J58,'Master Data 14-9-2026'!C:C,'Master Data 14-9-2026'!D:D) -> Silvana Anindya wx1504712 | D58: =_xlfn.XLOOKUP(J58,'Master Data 14-9-2026'!C:C,'Master Data 14-9-2026'!E:E) -> IOH | G58: M1 | H58: =_xlfn.XLOOKUP(J58,'Master Data 14-9-2026'!C:C,'Master Data 14-9-2026'!H:H) -> 2026-03-31 - 2026-04-29 | I58: =TEXT(DATEVALUE(LEFT(H58,10)),"mmmm") -> March | J58: DC-Document_Controller-015-M1 | K58: DC-Document_Controller-015-M1 | L58: Jabodetabek | M58: 200003102316020 | N58: FPA1091IDN26031710640667 | O58: 1.0912026e+17 | P58: 1091HG3728823-8 | Q58: 10 | R58: 1 | S58: 8828132633 | T58: Project Delivery Monitoring Services - Document Control | U58: 28881900 | V58: 1 | W58: =_xlfn.XLOOKUP(J58,'Master Data 14-9-2026'!C:C,'Master Data 14-9-2026'!L:L) -> 1 | X58: 28881900 | Y58: 2026-05-20 | Z58: =_xlfn.XLOOKUP(J58,'Master Data 14-9-2026'!C:C,'Master Data 14-9-2026'!I:I) -> Ended | AA58: Approved | AD58: Invoice | AE58: =_xlfn.XLOOKUP(L58,'[1]ID PROJECT'!E:E,'[1]ID PROJECT'!F:F) -> PRJ-KUT-KPU-TPED-2026-04-00071 | AF58: SSO-KUT-KPU-NIUT-2026-06-03066 | AG58: 257/INV/KUT-PST/VI/2026 | AH58: 46197 | AI58: Juni
A59: PE-Project_Engineer-005 | B59: =_xlfn.XLOOKUP(J59,'Master Data 14-9-2026'!C:C,'Master Data 14-9-2026'!D:D) -> Yusup wx1504641 | D59: =_xlfn.XLOOKUP(J59,'Master Data 14-9-2026'!C:C,'Master Data 14-9-2026'!E:E) -> IOH | G59: M1 | H59: =_xlfn.XLOOKUP(J59,'Master Data 14-9-2026'!C:C,'Master Data 14-9-2026'!H:H) -> 2026-03-24 - 2026-04-23 | I59: =TEXT(DATEVALUE(LEFT(H59,10)),"mmmm") -> March | J59: PE-Project_Engineer-005-M1 | K59: PE-Project_Engineer-005-M1 | L59: Jabodetabek | M59: 200003102324020 | N59: FPA1091IDN26031710640667 | O59: 1.0912026e+17 | P59: 1091HG3728823-8 | Q59: 11 | R59: 1 | S59: 8828132635 | T59: Project Delivery Monitoring Services - Project Engineer | U59: 34220600 | V59: 1 | W59: =_xlfn.XLOOKUP(J59,'Master Data 14-9-2026'!C:C,'Master Data 14-9-2026'!L:L) -> 0 | X59: 34220600 | Y59: 2026-05-20 | Z59: Ended | AA59: Approved | AD59: Invoice | AE59: =_xlfn.XLOOKUP(L59,'[1]ID PROJECT'!E:E,'[1]ID PROJECT'!F:F) -> PRJ-KUT-KPU-TPED-2026-04-00071 | AF59: SSO-KUT-KPU-NIUT-2026-06-03066 | AG59: 257/INV/KUT-PST/VI/2026 | AH59: 46197 | AI59: Juni
A60: SE-Site_Engineer-019 | B60: =_xlfn.XLOOKUP(J60,'Master Data 14-9-2026'!C:C,'Master Data 14-9-2026'!D:D) -> DENI MUHAMMAD ARIF FRIMALDI WX1521787 | D60: =_xlfn.XLOOKUP(J60,'Master Data 14-9-2026'!C:C,'Master Data 14-9-2026'!E:E) -> XLSMART | G60: M1 | H60: =_xlfn.XLOOKUP(J60,'Master Data 14-9-2026'!C:C,'Master Data 14-9-2026'!H:H) -> 2026-05-20 - 2026-06-19 | I60: =TEXT(DATEVALUE(LEFT(H60,10)),"mmmm") -> May | J60: SE-Site_Engineer-019-M1 | K60: SE-Site_Engineer-019-M1 | L60: Jabodetabek | M60: 200003120937020 | N60: FPA1091IDN26031710640667 | O60: 1.0912026e+17 | P60: 1091HG3728823-8 | Q60: 12 | R60: 1 | S60: 8828132634 | T60: Project Delivery Monitoring Services - Site Engineer | U60: 32542400 | V60: 1 | W60: =_xlfn.XLOOKUP(J60,'Master Data 14-9-2026'!C:C,'Master Data 14-9-2026'!L:L) -> 0.5 | X60: 32542400 | Y60: 2026-05-20 | Z60: Ended | AD60: Cancel invoice | AE60: =_xlfn.XLOOKUP(L60,'[1]ID PROJECT'!E:E,'[1]ID PROJECT'!F:F) -> PRJ-KUT-KPU-TPED-2026-04-00071 | AF60: SSO-KUT-KPU-NIUT-2026-07-03362 | AG60: 276/INV/KUT-PST/VII/2026 | AH60: 46205 | AI60: Juli
A61: QC-Quality_Control-014 | B61: =_xlfn.XLOOKUP(J61,'Master Data 14-9-2026'!C:C,'Master Data 14-9-2026'!D:D) -> Moch Andi Afriansyah wx1503654 | D61: =_xlfn.XLOOKUP(J61,'Master Data 14-9-2026'!C:C,'Master Data 14-9-2026'!E:E) -> IOH | G61: M1 | H61: =_xlfn.XLOOKUP(J61,'Master Data 14-9-2026'!C:C,'Master Data 14-9-2026'!H:H) -> 2026-04-01 - 2026-04-30 | I61: =TEXT(DATEVALUE(LEFT(H61,10)),"mmmm") -> April | J61: QC-Quality_Control-014-M1 | K61: QC-Quality_Control-014-M1 | L61: East Java | M61: 200003102329020 | N61: FPA1091IDN26031710640667 | O61: 1.0912026e+17 | P61: 1091HG3728823-8 | Q61: 13 | R61: 1 | S61: 8828132636 | T61: QEHS Onsite Monitoring and Inspection - QC | U61: 36992000 | V61: 1 | W61: =_xlfn.XLOOKUP(J61,'Master Data 14-9-2026'!C:C,'Master Data 14-9-2026'!L:L) -> 1.35 | X61: 36992000 | Y61: 2026-05-20 | Z61: Ended | AA61: Approved | AD61: Invoice | AE61: =_xlfn.XLOOKUP(L61,'[1]ID PROJECT'!E:E,'[1]ID PROJECT'!F:F) -> PRJ-KUT-KPU-TPED-2026-04-00076 | AF61: SSO-KUT-KPU-NIUT-2026-06-03066 | AG61: 257/INV/KUT-PST/VI/2026 | AH61: 46197 | AI61: Juni
A62: SE-Site_Engineer-015 | B62: =_xlfn.XLOOKUP(J62,'Master Data 14-9-2026'!C:C,'Master Data 14-9-2026'!D:D) -> Boy Frahansah Berutu wx1520523 | D62: =_xlfn.XLOOKUP(J62,'Master Data 14-9-2026'!C:C,'Master Data 14-9-2026'!E:E) -> IOH | G62: M1 | H62: =_xlfn.XLOOKUP(J62,'Master Data 14-9-2026'!C:C,'Master Data 14-9-2026'!H:H) -> 2026-05-15 - 2026-06-14 | I62: =TEXT(DATEVALUE(LEFT(H62,10)),"mmmm") -> May | J62: SE-Site_Engineer-015-M1 | K62: SE-Site_Engineer-015-M1 | L62: Jabodetabek | M62: 200003120933020 | N62: FPA1091IDN26031710640667 | O62: 1.0912026e+17 | P62: 1091HG3728823-8 | Q62: 14 | R62: 1 | S62: 8828132634 | T62: Project Delivery Monitoring Services - Site Engineer | U62: 32542400 | V62: 1 | W62: =_xlfn.XLOOKUP(J62,'Master Data 14-9-2026'!C:C,'Master Data 14-9-2026'!L:L) -> 0 | X62: 32542400 | Y62: 2026-05-20 | Z62: Ended | AA62: Approved | AD62: Invoice | AE62: =_xlfn.XLOOKUP(L62,'[1]ID PROJECT'!E:E,'[1]ID PROJECT'!F:F) -> PRJ-KUT-KPU-TPED-2026-04-00071 | AF62: SSO-KUT-KPU-NIUT-2026-06-03066 | AG62: 257/INV/KUT-PST/VI/2026 | AH62: 46197 | AI62: Juni
A63: SE-Site_Engineer-016 | B63: =_xlfn.XLOOKUP(J63,'Master Data 14-9-2026'!C:C,'Master Data 14-9-2026'!D:D) -> Muhammad Hafid Aqil Siroj wx1520522 | D63: =_xlfn.XLOOKUP(J63,'Master Data 14-9-2026'!C:C,'Master Data 14-9-2026'!E:E) -> IOH | G63: M1 | H63: =_xlfn.XLOOKUP(J63,'Master Data 14-9-2026'!C:C,'Master Data 14-9-2026'!H:H) -> 2026-05-15 - 2026-06-14 | I63: =TEXT(DATEVALUE(LEFT(H63,10)),"mmmm") -> May | J63: SE-Site_Engineer-016-M1 | K63: SE-Site_Engineer-016-M1 | L63: Jabodetabek | M63: 200003120934020 | N63: FPA1091IDN26031710640667 | O63: 1.0912026e+17 | P63: 1091HG3728823-8 | Q63: 15 | R63: 1 | S63: 8828132634 | T63: Project Delivery Monitoring Services - Site Engineer | U63: 32542400 | V63: 1 | W63: =_xlfn.XLOOKUP(J63,'Master Data 14-9-2026'!C:C,'Master Data 14-9-2026'!L:L) -> 0 | X63: 32542400 | Y63: 2026-05-20 | Z63: Ended | AA63: Approved | AD63: Invoice | AE63: =_xlfn.XLOOKUP(L63,'[1]ID PROJECT'!E:E,'[1]ID PROJECT'!F:F) -> PRJ-KUT-KPU-TPED-2026-04-00071 | AF63: SSO-KUT-KPU-NIUT-2026-06-03066 | AG63: 257/INV/KUT-PST/VI/2026 | AH63: 46197 | AI63: Juni
A64: PE-Project_Engineer-028 | B64: =_xlfn.XLOOKUP(J64,'Master Data 14-9-2026'!C:C,'Master Data 14-9-2026'!D:D) -> Kristina Tambunan wx1517408 | D64: =_xlfn.XLOOKUP(J64,'Master Data 14-9-2026'!C:C,'Master Data 14-9-2026'!E:E) -> TELKOMSEL | E64: TSEL - PE028 | G64: M1 | H64: =_xlfn.XLOOKUP(J64,'Master Data 14-9-2026'!C:C,'Master Data 14-9-2026'!H:H) -> 2026-05-05 - 2026-06-04 | I64: =TEXT(DATEVALUE(LEFT(H64,10)),"mmmm") -> May | J64: PE-Project_Engineer-028-M1 | K64: PE-Project_Engineer-028 | L64: Jabodetabek | M64: 200003120955020 | N64: FPA1091IDN26031710640667 | O64: 1.0912026e+17 | P64: 1091HG3728823-9 | Q64: 1 | R64: 1 | S64: 8828132635 | T64: Project Delivery Monitoring Services - Project Engineer | U64: 34220600 | V64: 1 | W64: =_xlfn.XLOOKUP(J64,'Master Data 14-9-2026'!C:C,'Master Data 14-9-2026'!L:L) -> 1 | X64: 34220600 | Y64: 2026-05-20 | Z64: =_xlfn.XLOOKUP(J64,'Master Data 14-9-2026'!C:C,'Master Data 14-9-2026'!I:I) -> Ended | AA64: Approved | AC64: Confirm dean | AD64: Invoice | AE64: =_xlfn.XLOOKUP(L64,'[1]ID PROJECT'!E:E,'[1]ID PROJECT'!F:F) -> PRJ-KUT-KPU-TPED-2026-04-00071 | AF64: SSO-KUT-KPU-NIUT-2026-09-04627 | AG64: 398/INV/KUT-PST/IX/2026 | AH64: 46269 | AI64: September
A65: PE-Project_Engineer-029 | B65: =_xlfn.XLOOKUP(J65,'Master Data 14-9-2026'!C:C,'Master Data 14-9-2026'!D:D) -> Fikri Tirta Kusuma Atmaja wx1507714 | C65: DC-027 | D65: =_xlfn.XLOOKUP(J65,'Master Data 14-9-2026'!C:C,'Master Data 14-9-2026'!E:E) -> XLSMART | E65: TSEL - PE029 | G65: M1 | H65: =_xlfn.XLOOKUP(J65,'Master Data 14-9-2026'!C:C,'Master Data 14-9-2026'!H:H) -> 2026-04-01 - 2026-04-30 | I65: =TEXT(DATEVALUE(LEFT(H65,10)),"mmmm") -> April | J65: PE-Project_Engineer-029-M1 | K65: PE-Project_Engineer-029 | L65: West Java | M65: 200003120956020 | N65: FPA1091IDN26031710640667 | O65: 1.0912026e+17 | P65: 1091HG3728823-9 | Q65: 2 | R65: 1 | S65: 8828132635 | T65: Project Delivery Monitoring Services - Project Engineer | U65: 34220600 | V65: 1 | W65: =_xlfn.XLOOKUP(J65,'Master Data 14-9-2026'!C:C,'Master Data 14-9-2026'!L:L) -> 0 | X65: 34220600 | Y65: 2026-05-20 | Z65: Ended | AA65: Approved | AD65: Invoice | AE65: =_xlfn.XLOOKUP(L65,'[1]ID PROJECT'!E:E,'[1]ID PROJECT'!F:F) -> PRJ-KUT-KPU-TPED-2026-04-00074 | AF65: SSO-KUT-KPU-NIUT-2026-09-04628 | AG65: 272/INV/KUT-PST/VI/2026 | AH65: 46203 | AI65: Juni
A66: QC-Quality_Control-003 | B66: =_xlfn.XLOOKUP(J66,'Master Data 14-9-2026'!C:C,'Master Data 14-9-2026'!D:D) -> Risky Septiadi Hartono wx1503496 | D66: =_xlfn.XLOOKUP(J66,'Master Data 14-9-2026'!C:C,'Master Data 14-9-2026'!E:E) -> TELKOMSEL | G66: M1 | H66: =_xlfn.XLOOKUP(J66,'Master Data 14-9-2026'!C:C,'Master Data 14-9-2026'!H:H) -> 2026-03-23 - 2026-04-22 | I66: =TEXT(DATEVALUE(LEFT(H66,10)),"mmmm") -> March | J66: QC-Quality_Control-003-M1 | K66: QC-Quality_Control-003-M1 | L66: East Java | M66: 200003103089020 | N66: FPA1091IDN26031710640667 | O66: 1.0912026e+17 | P66: 1091HG3728823-10 | Q66: 1 | R66: 1 | S66: 8828132636 | T66: QEHS Onsite Monitoring and Inspection - QC | U66: 36992000 | V66: 1 | W66: =_xlfn.XLOOKUP(J66,'Master Data 14-9-2026'!C:C,'Master Data 14-9-2026'!L:L) -> 0.5 | X66: 36992000 | Y66: 2026-05-20 | Z66: Ended | AA66: Approved | AD66: Invoice | AE66: =_xlfn.XLOOKUP(L66,'[1]ID PROJECT'!E:E,'[1]ID PROJECT'!F:F) -> PRJ-KUT-KPU-TPED-2026-04-00076 | AF66: SSO-KUT-KPU-NIUT-2026-09-04629 | AG66: 289/INV/KUT-PST/VII/2026 | AH66: 46216 | AI66: Juli
A67: QC-Quality_Control-008 | B67: =_xlfn.XLOOKUP(J67,'Master Data 14-9-2026'!C:C,'Master Data 14-9-2026'!D:D) -> Farizqi Anisah Nudhar wx1503972 | D67: =_xlfn.XLOOKUP(J67,'Master Data 14-9-2026'!C:C,'Master Data 14-9-2026'!E:E) -> TELKOMSEL | G67: M1 | H67: =_xlfn.XLOOKUP(J67,'Master Data 14-9-2026'!C:C,'Master Data 14-9-2026'!H:H) -> 2026-03-30 - 2026-04-29 | I67: =TEXT(DATEVALUE(LEFT(H67,10)),"mmmm") -> March | J67: QC-Quality_Control-008-M1 | K67: QC-Quality_Control-008-M1 | L67: Jabodetabek | M67: 200003103090020 | N67: FPA1091IDN26031710640667 | O67: 1.0912026e+17 | P67: 1091HG3728823-10 | Q67: 2 | R67: 1 | S67: 8828132636 | T67: QEHS Onsite Monitoring and Inspection - QC | U67: 36992000 | V67: 1 | W67: =_xlfn.XLOOKUP(J67,'Master Data 14-9-2026'!C:C,'Master Data 14-9-2026'!L:L) -> 1.2 | X67: 36992000 | Y67: 2026-05-20 | Z67: Ended | AA67: Approved | AD67: Invoice | AE67: =_xlfn.XLOOKUP(L67,'[1]ID PROJECT'!E:E,'[1]ID PROJECT'!F:F) -> PRJ-KUT-KPU-TPED-2026-04-00071 | AF67: SSO-KUT-KPU-NIUT-2026-09-04629 | AG67: 273/INV/KUT-PST/VI/2026 | AH67: 46203 | AI67: Juni
A68: QC-Quality_Control-010 | B68: =_xlfn.XLOOKUP(J68,'Master Data 14-9-2026'!C:C,'Master Data 14-9-2026'!D:D) -> Adhelina Zulfiana wx1505386 | D68: =_xlfn.XLOOKUP(J68,'Master Data 14-9-2026'!C:C,'Master Data 14-9-2026'!E:E) -> Platform DMD | G68: M1 | H68: =_xlfn.XLOOKUP(J68,'Master Data 14-9-2026'!C:C,'Master Data 14-9-2026'!H:H) -> 2026-03-30 - 2026-04-29 | I68: =TEXT(DATEVALUE(LEFT(H68,10)),"mmmm") -> March | J68: QC-Quality_Control-010-M1 | K68: QC-Quality_Control-010-M1 | L68: Jabodetabek | M68: 200003103091020 | N68: FPA1091IDN26031710640667 | O68: 1.0912026e+17 | P68: 1091HG3728823-10 | Q68: 3 | R68: 1 | S68: 8828132636 | T68: QEHS Onsite Monitoring and Inspection - QC | U68: 36992000 | V68: 1 | W68: =_xlfn.XLOOKUP(J68,'Master Data 14-9-2026'!C:C,'Master Data 14-9-2026'!L:L) -> 1 | X68: 36992000 | Y68: 2026-05-20 | Z68: =_xlfn.XLOOKUP(J68,'Master Data 14-9-2026'!C:C,'Master Data 14-9-2026'!I:I) -> Ended | AA68: Approved | AD68: Invoice | AE68: =_xlfn.XLOOKUP(L68,'[1]ID PROJECT'!E:E,'[1]ID PROJECT'!F:F) -> PRJ-KUT-KPU-TPED-2026-04-00071 | AF68: SSO-KUT-KPU-NIUT-2026-09-04630 | AG68: 273/INV/KUT-PST/VI/2026 | AH68: 46203 | AI68: Juni
A69: QC-Quality_Control-013 | B69: =_xlfn.XLOOKUP(J69,'Master Data 14-9-2026'!C:C,'Master Data 14-9-2026'!D:D) -> Alvin Ramadhan wx1507288 | D69: =_xlfn.XLOOKUP(J69,'Master Data 14-9-2026'!C:C,'Master Data 14-9-2026'!E:E) -> TELKOMSEL | G69: M1 | H69: =_xlfn.XLOOKUP(J69,'Master Data 14-9-2026'!C:C,'Master Data 14-9-2026'!H:H) -> 2026-04-01 - 2026-04-30 | I69: =TEXT(DATEVALUE(LEFT(H69,10)),"mmmm") -> April | J69: QC-Quality_Control-013-M1 | K69: QC-Quality_Control-013-M1 | L69: West Java | M69: 200003103092020 | N69: FPA1091IDN26031710640667 | O69: 1.0912026e+17 | P69: 1091HG3728823-10 | Q69: 4 | R69: 1 | S69: 8828132636 | T69: QEHS Onsite Monitoring and Inspection - QC | U69: 36992000 | V69: 1 | W69: =_xlfn.XLOOKUP(J69,'Master Data 14-9-2026'!C:C,'Master Data 14-9-2026'!L:L) -> 1.5 | X69: 36992000 | Y69: 2026-05-20 | Z69: Ended | AA69: Approved | AD69: Invoice | AE69: =_xlfn.XLOOKUP(L69,'[1]ID PROJECT'!E:E,'[1]ID PROJECT'!F:F) -> PRJ-KUT-KPU-TPED-2026-04-00074 | AF69: SSO-KUT-KPU-NIUT-2026-09-04631 | AG69: 273/INV/KUT-PST/VI/2026 | AH69: 46203 | AI69: Juni
A70: QC-Quality_Control-015 | B70: =_xlfn.XLOOKUP(J70,'Master Data 14-9-2026'!C:C,'Master Data 14-9-2026'!D:D) -> Makarias Lindon Sihombing wx1503643 | D70: =_xlfn.XLOOKUP(J70,'Master Data 14-9-2026'!C:C,'Master Data 14-9-2026'!E:E) -> TELKOMSEL | G70: M1 | H70: =_xlfn.XLOOKUP(J70,'Master Data 14-9-2026'!C:C,'Master Data 14-9-2026'!H:H) -> 2026-04-01 - 2026-04-30 | I70: =TEXT(DATEVALUE(LEFT(H70,10)),"mmmm") -> April | J70: QC-Quality_Control-015-M1 | K70: QC-Quality_Control-015-M1 | L70: Central Java | M70: 200003103093020 | N70: FPA1091IDN26031710640667 | O70: 1.0912026e+17 | P70: 1091HG3728823-10 | Q70: 5 | R70: 1 | S70: 8828132636 | T70: QEHS Onsite Monitoring and Inspection - QC | U70: 36992000 | V70: 1 | W70: =_xlfn.XLOOKUP(J70,'Master Data 14-9-2026'!C:C,'Master Data 14-9-2026'!L:L) -> 1.33 | X70: 36992000 | Y70: 2026-05-20 | Z70: Ended | AA70: Approved | AD70: Invoice | AE70: =_xlfn.XLOOKUP(L70,'[1]ID PROJECT'!E:E,'[1]ID PROJECT'!F:F) -> PRJ-KUT-KPU-TPED-2026-04-00075 | AF70: SSO-KUT-KPU-NIUT-2026-06-03300 | AG70: 273/INV/KUT-PST/VI/2026 | AH70: 46203 | AI70: Juni
A71: SE-Site_Engineer-004 | B71: =_xlfn.XLOOKUP(J71,'Master Data 14-9-2026'!C:C,'Master Data 14-9-2026'!D:D) -> #N/A | C71: SE004 XL FTHH CANCEL | D71: =_xlfn.XLOOKUP(J71,'Master Data 14-9-2026'!C:C,'Master Data 14-9-2026'!E:E) -> #N/A | E71: TSEL - PE071 | G71: M1 | H71: =_xlfn.XLOOKUP(J71,'Master Data 14-9-2026'!C:C,'Master Data 14-9-2026'!H:H) -> #N/A | I71: =TEXT(DATEVALUE(LEFT(H71,10)),"mmmm") -> #N/A | J71: SE-Site_Engineer-004-M1 | K71: SE-Site_Engineer-004-M1 | L71: Jabodetabek | M71: 200003103096020 | N71: FPA1091IDN26031710640667 | O71: 1.0912026e+17 | P71: 1091HG3728823-10 | Q71: 6 | R71: 1 | S71: 8828132635 | T71: Project Delivery Monitoring Services - Project Engineer | U71: 34220600 | V71: 1 | W71: =_xlfn.XLOOKUP(J71,'Master Data 14-9-2026'!C:C,'Master Data 14-9-2026'!L:L) -> #N/A | X71: 34220600 | Y71: 2026-05-20 | Z71: Tidak ditemukan | AA71: Eror | AB71: Tidak ada di dashboard | AC71: Confirm dean | AE71: =_xlfn.XLOOKUP(L71,'[1]ID PROJECT'!E:E,'[1]ID PROJECT'!F:F) -> PRJ-KUT-KPU-TPED-2026-04-00071
A72: SE-Site_Engineer-005 | B72: =_xlfn.XLOOKUP(J72,'Master Data 14-9-2026'!C:C,'Master Data 14-9-2026'!D:D) -> Muhammad Yusuf wx1503989 | D72: =_xlfn.XLOOKUP(J72,'Master Data 14-9-2026'!C:C,'Master Data 14-9-2026'!E:E) -> IOH | E72: TSEL - SE005 | G72: M1 | H72: =_xlfn.XLOOKUP(J72,'Master Data 14-9-2026'!C:C,'Master Data 14-9-2026'!H:H) -> 2026-03-30 - 2026-04-29 | I72: =TEXT(DATEVALUE(LEFT(H72,10)),"mmmm") -> March | J72: SE-Site_Engineer-005-M1 | K72: SE-Site_Engineer-005-M1 | L72: Sumatera | M72: 200003103094020 | N72: FPA1091IDN26031710640667 | O72: 1.0912026e+17 | P72: 1091HG3728823-10 | Q72: 7 | R72: 1 | S72: 8828132635 | T72: Project Delivery Monitoring Services - Project Engineer | U72: 34220600 | V72: 1 | W72: =_xlfn.XLOOKUP(J72,'Master Data 14-9-2026'!C:C,'Master Data 14-9-2026'!L:L) -> 0 | X72: 34220600 | Y72: 2026-05-20 | Z72: Ended | AB72: Project assign tidak update ( IOH to Tsel ) | AC72: resubmit M1 M2 (Tsel) , M3 keatas IOH | AE72: =_xlfn.XLOOKUP(L72,'[1]ID PROJECT'!E:E,'[1]ID PROJECT'!F:F) -> PRJ-KUT-KPU-TPED-2026-04-00078
A73: SE-Site_Engineer-012 | B73: =_xlfn.XLOOKUP(J73,'Master Data 14-9-2026'!C:C,'Master Data 14-9-2026'!D:D) -> #N/A | D73: =_xlfn.XLOOKUP(J73,'Master Data 14-9-2026'!C:C,'Master Data 14-9-2026'!E:E) -> #N/A | G73: M1 | H73: =_xlfn.XLOOKUP(J73,'Master Data 14-9-2026'!C:C,'Master Data 14-9-2026'!H:H) -> #N/A | I73: =TEXT(DATEVALUE(LEFT(H73,10)),"mmmm") -> #N/A | J73: SE-Site_Engineer-012-M1 | K73: SE-Site_Engineer-012-M1 | M73: 200003103095020 | N73: FPA1091IDN26031710640667 | O73: 1.0912026e+17 | P73: 1091HG3728823-10 | Q73: 8 | R73: 1 | S73: 8828132635 | T73: Project Delivery Monitoring Services - Project Engineer | U73: 34220600 | V73: 1 | W73: =_xlfn.XLOOKUP(J73,'Master Data 14-9-2026'!C:C,'Master Data 14-9-2026'!L:L) -> #N/A | X73: 34220600 | Y73: 2026-05-20 | Z73: Tidak ditemukan | AA73: Eror | AB73: Line tidak ada di Dashboard (email open task dashboard) | AC73: Email to fesa pak martin | AE73: =_xlfn.XLOOKUP(L73,'[1]ID PROJECT'!E:E,'[1]ID PROJECT'!F:F) -> #N/A
A74: DC-Document_Controller-001 | B74: =_xlfn.XLOOKUP(J74,'Master Data 14-9-2026'!C:C,'Master Data 14-9-2026'!D:D) -> Sri Hardianti Purnamasari wx1503627 | D74: =_xlfn.XLOOKUP(J74,'Master Data 14-9-2026'!C:C,'Master Data 14-9-2026'!E:E) -> TELKOMSEL | G74: M1 | H74: =_xlfn.XLOOKUP(J74,'Master Data 14-9-2026'!C:C,'Master Data 14-9-2026'!H:H) -> 2026-03-23 - 2026-04-22 | I74: =TEXT(DATEVALUE(LEFT(H74,10)),"mmmm") -> March | J74: DC-Document_Controller-001-M1 | K74: DC-Document_Controller-001-M1 | L74: Sumbagsel | M74: 200003103079020 | N74: FPA1091IDN26031710640667 | O74: 1.0912026e+17 | P74: 1091HG3728823-10 | Q74: 9 | R74: 1 | S74: 8828132633 | T74: Project Delivery Monitoring Services - Document Control | U74: 28881900 | V74: 1 | W74: =_xlfn.XLOOKUP(J74,'Master Data 14-9-2026'!C:C,'Master Data 14-9-2026'!L:L) -> 1.05 | X74: 28881900 | Y74: 2026-05-20 | Z74: Ended | AA74: Approved | AD74: Invoice | AE74: =_xlfn.XLOOKUP(L74,'[1]ID PROJECT'!E:E,'[1]ID PROJECT'!F:F) -> PRJ-KUT-KPU-TPED-2026-04-00078 | AF74: SSO-KUT-KPU-NIUT-2026-07-03363 | AG74: 279/INV/KUT-PST/VII/2026 | AH74: 46210 | AI74: Juli
A75: DC-Document_Controller-003 | B75: =_xlfn.XLOOKUP(J75,'Master Data 14-9-2026'!C:C,'Master Data 14-9-2026'!D:D) -> Gigih Dharma Sulistya wx1503511 | D75: =_xlfn.XLOOKUP(J75,'Master Data 14-9-2026'!C:C,'Master Data 14-9-2026'!E:E) -> TELKOMSEL | G75: M1 | H75: =_xlfn.XLOOKUP(J75,'Master Data 14-9-2026'!C:C,'Master Data 14-9-2026'!H:H) -> 2026-03-23 - 2026-04-22 | I75: =TEXT(DATEVALUE(LEFT(H75,10)),"mmmm") -> March | J75: DC-Document_Controller-003-M1 | K75: DC-Document_Controller-003-M1 | L75: East Java | M75: 200003103080020 | N75: FPA1091IDN26031710640667 | O75: 1.0912026e+17 | P75: 1091HG3728823-10 | Q75: 10 | R75: 1 | S75: 8828132633 | T75: Project Delivery Monitoring Services - Document Control | U75: 28881900 | V75: 1 | W75: =_xlfn.XLOOKUP(J75,'Master Data 14-9-2026'!C:C,'Master Data 14-9-2026'!L:L) -> 1 | X75: 28881900 | Y75: 2026-05-20 | Z75: =_xlfn.XLOOKUP(J75,'Master Data 14-9-2026'!C:C,'Master Data 14-9-2026'!I:I) -> Ended | AA75: Approved | AD75: Invoice | AE75: =_xlfn.XLOOKUP(L75,'[1]ID PROJECT'!E:E,'[1]ID PROJECT'!F:F) -> PRJ-KUT-KPU-TPED-2026-04-00076 | AF75: SSO-KUT-KPU-NIUT-2026-06-03300 | AG75: 273/INV/KUT-PST/VI/2026 | AH75: 46203 | AI75: Juni
A76: DC-Document_Controller-005 | B76: =_xlfn.XLOOKUP(J76,'Master Data 14-9-2026'!C:C,'Master Data 14-9-2026'!D:D) -> F Albert Jacob wx1504717 | D76: =_xlfn.XLOOKUP(J76,'Master Data 14-9-2026'!C:C,'Master Data 14-9-2026'!E:E) -> TELKOMSEL | G76: M1 | H76: =_xlfn.XLOOKUP(J76,'Master Data 14-9-2026'!C:C,'Master Data 14-9-2026'!H:H) -> 2026-03-23 - 2026-04-22 | I76: =TEXT(DATEVALUE(LEFT(H76,10)),"mmmm") -> March | J76: DC-Document_Controller-005-M1 | K76: DC-Document_Controller-005-M1 | L76: Bali Nusra | M76: 200003103081020 | N76: FPA1091IDN26031710640667 | O76: 1.0912026e+17 | P76: 1091HG3728823-10 | Q76: 11 | R76: 1 | S76: 8828132633 | T76: Project Delivery Monitoring Services - Document Control | U76: 28881900 | V76: 1 | W76: =_xlfn.XLOOKUP(J76,'Master Data 14-9-2026'!C:C,'Master Data 14-9-2026'!L:L) -> 1 | X76: 28881900 | Y76: 2026-05-20 | Z76: =_xlfn.XLOOKUP(J76,'Master Data 14-9-2026'!C:C,'Master Data 14-9-2026'!I:I) -> Ended | AA76: Approved | AD76: Invoice | AE76: =_xlfn.XLOOKUP(L76,'[1]ID PROJECT'!E:E,'[1]ID PROJECT'!F:F) -> PRJ-KUT-KPU-TPED-2026-04-00077 | AF76: SSO-KUT-KPU-NIUT-2026-06-03300 | AG76: 273/INV/KUT-PST/VI/2026 | AH76: 46203 | AI76: Juni
A77: DC-Document_Controller-009 | B77: =_xlfn.XLOOKUP(J77,'Master Data 14-9-2026'!C:C,'Master Data 14-9-2026'!D:D) -> Febryyanti Nawang Wulan wx1503626 | D77: =_xlfn.XLOOKUP(J77,'Master Data 14-9-2026'!C:C,'Master Data 14-9-2026'!E:E) -> TELKOMSEL | G77: M1 | H77: =_xlfn.XLOOKUP(J77,'Master Data 14-9-2026'!C:C,'Master Data 14-9-2026'!H:H) -> 2026-03-30 - 2026-04-29 | I77: =TEXT(DATEVALUE(LEFT(H77,10)),"mmmm") -> March | J77: DC-Document_Controller-009-M1 | K77: DC-Document_Controller-009-M1 | L77: Sumbagsel | M77: 200003103082020 | N77: FPA1091IDN26031710640667 | O77: 1.0912026e+17 | P77: 1091HG3728823-10 | Q77: 12 | R77: 1 | S77: 8828132633 | T77: Project Delivery Monitoring Services - Document Control | U77: 28881900 | V77: 1 | W77: =_xlfn.XLOOKUP(J77,'Master Data 14-9-2026'!C:C,'Master Data 14-9-2026'!L:L) -> 1.43 | X77: 28881900 | Y77: 2026-05-20 | Z77: Ended | AA77: Approved | AD77: Invoice | AE77: =_xlfn.XLOOKUP(L77,'[1]ID PROJECT'!E:E,'[1]ID PROJECT'!F:F) -> PRJ-KUT-KPU-TPED-2026-04-00078 | AF77: SSO-KUT-KPU-NIUT-2026-06-03300 | AG77: 273/INV/KUT-PST/VI/2026 | AH77: 46203 | AI77: Juni
A78: DC-Document_Controller-012 | B78: =_xlfn.XLOOKUP(J78,'Master Data 14-9-2026'!C:C,'Master Data 14-9-2026'!D:D) -> Yosephine Yudianto wx1503656 | D78: =_xlfn.XLOOKUP(J78,'Master Data 14-9-2026'!C:C,'Master Data 14-9-2026'!E:E) -> TELKOMSEL | G78: M1 | H78: =_xlfn.XLOOKUP(J78,'Master Data 14-9-2026'!C:C,'Master Data 14-9-2026'!H:H) -> 2026-03-30 - 2026-04-29 | I78: =TEXT(DATEVALUE(LEFT(H78,10)),"mmmm") -> March | J78: DC-Document_Controller-012-M1 | K78: DC-Document_Controller-012-M1 | L78: Central Java | M78: 200003103083020 | N78: FPA1091IDN26031710640667 | O78: 1.0912026e+17 | P78: 1091HG3728823-10 | Q78: 13 | R78: 1 | S78: 8828132633 | T78: Project Delivery Monitoring Services - Document Control | U78: 28881900 | V78: 1 | W78: =_xlfn.XLOOKUP(J78,'Master Data 14-9-2026'!C:C,'Master Data 14-9-2026'!L:L) -> 1.15 | X78: 28881900 | Y78: 2026-05-20 | Z78: Ended | AA78: Approved | AD78: Invoice | AE78: =_xlfn.XLOOKUP(L78,'[1]ID PROJECT'!E:E,'[1]ID PROJECT'!F:F) -> PRJ-KUT-KPU-TPED-2026-04-00075 | AF78: SSO-KUT-KPU-NIUT-2026-06-03300 | AG78: 273/INV/KUT-PST/VI/2026 | AH78: 46203 | AI78: Juni
A79: DC-Document_Controller-021 | B79: =_xlfn.XLOOKUP(J79,'Master Data 14-9-2026'!C:C,'Master Data 14-9-2026'!D:D) -> Winarsih wx1503649 | D79: =_xlfn.XLOOKUP(J79,'Master Data 14-9-2026'!C:C,'Master Data 14-9-2026'!E:E) -> TELKOMSEL | G79: M1 | H79: =_xlfn.XLOOKUP(J79,'Master Data 14-9-2026'!C:C,'Master Data 14-9-2026'!H:H) -> 2026-04-01 - 2026-04-30 | I79: =TEXT(DATEVALUE(LEFT(H79,10)),"mmmm") -> April | J79: DC-Document_Controller-021-M1 | K79: DC-Document_Controller-021-M1 | L79: Central Java | M79: 200003103084020 | N79: FPA1091IDN26031710640667 | O79: 1.0912026e+17 | P79: 1091HG3728823-10 | Q79: 14 | R79: 1 | S79: 8828132633 | T79: Project Delivery Monitoring Services - Document Control | U79: 28881900 | V79: 1 | W79: =_xlfn.XLOOKUP(J79,'Master Data 14-9-2026'!C:C,'Master Data 14-9-2026'!L:L) -> 1.36 | X79: 28881900 | Y79: 2026-05-20 | Z79: Ended | AA79: Approved | AD79: Invoice | AE79: =_xlfn.XLOOKUP(L79,'[1]ID PROJECT'!E:E,'[1]ID PROJECT'!F:F) -> PRJ-KUT-KPU-TPED-2026-04-00075 | AF79: SSO-KUT-KPU-NIUT-2026-06-03300 | AG79: 273/INV/KUT-PST/VI/2026 | AH79: 46203 | AI79: Juni
A80: DC-Document_Controller-027 | B80: =_xlfn.XLOOKUP(J80,'Master Data 14-9-2026'!C:C,'Master Data 14-9-2026'!D:D) -> #N/A | D80: =_xlfn.XLOOKUP(J80,'Master Data 14-9-2026'!C:C,'Master Data 14-9-2026'!E:E) -> #N/A | G80: M1 | H80: =_xlfn.XLOOKUP(J80,'Master Data 14-9-2026'!C:C,'Master Data 14-9-2026'!H:H) -> #N/A | I80: =TEXT(DATEVALUE(LEFT(H80,10)),"mmmm") -> #N/A | J80: DC-Document_Controller-027-M1 | K80: DC-Document_Controller-027-M1 | L80: Jabodetabek | M80: 200003103085020 | N80: FPA1091IDN26031710640667 | O80: 1.0912026e+17 | P80: 1091HG3728823-10 | Q80: 15 | R80: 1 | S80: 8828132633 | T80: Project Delivery Monitoring Services - Document Control | U80: 28881900 | V80: 1 | W80: =_xlfn.XLOOKUP(J80,'Master Data 14-9-2026'!C:C,'Master Data 14-9-2026'!L:L) -> #N/A | X80: 28881900 | Y80: 2026-05-20 | Z80: Tidak ditemukan | AA80: Eror | AB80: Line tidak ada di Dashboard (email open task dashboard) | AC80: Email to fesa pak martin | AE80: =_xlfn.XLOOKUP(L80,'[1]ID PROJECT'!E:E,'[1]ID PROJECT'!F:F) -> PRJ-KUT-KPU-TPED-2026-04-00071
A81: DC-Document_Controller-029 | B81: =_xlfn.XLOOKUP(J81,'Master Data 14-9-2026'!C:C,'Master Data 14-9-2026'!D:D) -> Mona Margaretha Tobing wx1507282 | D81: =_xlfn.XLOOKUP(J81,'Master Data 14-9-2026'!C:C,'Master Data 14-9-2026'!E:E) -> TELKOMSEL | G81: M1 | H81: =_xlfn.XLOOKUP(J81,'Master Data 14-9-2026'!C:C,'Master Data 14-9-2026'!H:H) -> 2026-04-01 - 2026-04-30 | I81: =TEXT(DATEVALUE(LEFT(H81,10)),"mmmm") -> April | J81: DC-Document_Controller-029-M1 | K81: DC-Document_Controller-029-M1 | L81: Jabodetabek | M81: 200003103086020 | N81: FPA1091IDN26031710640667 | O81: 1.0912026e+17 | P81: 1091HG3728823-10 | Q81: 16 | R81: 1 | S81: 8828132633 | T81: Project Delivery Monitoring Services - Document Control | U81: 28881900 | V81: 1 | W81: =_xlfn.XLOOKUP(J81,'Master Data 14-9-2026'!C:C,'Master Data 14-9-2026'!L:L) -> 1.5 | X81: 28881900 | Y81: 2026-05-20 | Z81: Ended | AA81: Approved | AD81: Invoice | AE81: =_xlfn.XLOOKUP(L81,'[1]ID PROJECT'!E:E,'[1]ID PROJECT'!F:F) -> PRJ-KUT-KPU-TPED-2026-04-00071 | AF81: SSO-KUT-KPU-NIUT-2026-06-03300 | AG81: 273/INV/KUT-PST/VI/2026 | AH81: 46203 | AI81: Juni
A82: PE-Project_Engineer-007 | B82: =_xlfn.XLOOKUP(J82,'Master Data 14-9-2026'!C:C,'Master Data 14-9-2026'!D:D) -> Triana Sukeci wx1503625 | D82: =_xlfn.XLOOKUP(J82,'Master Data 14-9-2026'!C:C,'Master Data 14-9-2026'!E:E) -> TELKOMSEL | G82: M1 | H82: =_xlfn.XLOOKUP(J82,'Master Data 14-9-2026'!C:C,'Master Data 14-9-2026'!H:H) -> 2026-03-27 - 2026-04-26 | I82: =TEXT(DATEVALUE(LEFT(H82,10)),"mmmm") -> March | J82: PE-Project_Engineer-007-M1 | K82: PE-Project_Engineer-007-M1 | L82: Sumatera | M82: 200003103087020 | N82: FPA1091IDN26031710640667 | O82: 1.0912026e+17 | P82: 1091HG3728823-10 | Q82: 17 | R82: 1 | S82: 8828132635 | T82: Project Delivery Monitoring Services - Project Engineer | U82: 34220600 | V82: 1 | W82: =_xlfn.XLOOKUP(J82,'Master Data 14-9-2026'!C:C,'Master Data 14-9-2026'!L:L) -> 1 | X82: 34220600 | Y82: 2026-05-20 | Z82: =_xlfn.XLOOKUP(J82,'Master Data 14-9-2026'!C:C,'Master Data 14-9-2026'!I:I) -> Ended | AA82: Approved | AD82: Invoice | AE82: =_xlfn.XLOOKUP(L82,'[1]ID PROJECT'!E:E,'[1]ID PROJECT'!F:F) -> PRJ-KUT-KPU-TPED-2026-04-00078 | AF82: SSO-KUT-KPU-NIUT-2026-06-03300 | AG82: 273/INV/KUT-PST/VI/2026 | AH82: 46203 | AI82: Juni
A83: PE-Project_Engineer-013 | B83: =_xlfn.XLOOKUP(J83,'Master Data 14-9-2026'!C:C,'Master Data 14-9-2026'!D:D) -> Vina Putri Saffanah wx1503974 | D83: =_xlfn.XLOOKUP(J83,'Master Data 14-9-2026'!C:C,'Master Data 14-9-2026'!E:E) -> TELKOMSEL | G83: M1 | H83: =_xlfn.XLOOKUP(J83,'Master Data 14-9-2026'!C:C,'Master Data 14-9-2026'!H:H) -> 2026-03-31 - 2026-04-29 | I83: =TEXT(DATEVALUE(LEFT(H83,10)),"mmmm") -> March | J83: PE-Project_Engineer-013-M1 | K83: PE-Project_Engineer-013-M1 | L83: Jabodetabek | M83: 200003103088020 | N83: FPA1091IDN26031710640667 | O83: 1.0912026e+17 | P83: 1091HG3728823-10 | Q83: 18 | R83: 1 | S83: 8828132635 | T83: Project Delivery Monitoring Services - Project Engineer | U83: 34220600 | V83: 1 | W83: =_xlfn.XLOOKUP(J83,'Master Data 14-9-2026'!C:C,'Master Data 14-9-2026'!L:L) -> 1.04 | X83: 34220600 | Y83: 2026-05-20 | Z83: Ended | AA83: Approved | AD83: Invoice | AE83: =_xlfn.XLOOKUP(L83,'[1]ID PROJECT'!E:E,'[1]ID PROJECT'!F:F) -> PRJ-KUT-KPU-TPED-2026-04-00071 | AF83: SSO-KUT-KPU-NIUT-2026-06-03300 | AG83: 273/INV/KUT-PST/VI/2026 | AH83: 46203 | AI83: Juni
A84: PE-Project_Engineer-024 | B84: =_xlfn.XLOOKUP(J84,'Master Data 14-9-2026'!C:C,'Master Data 14-9-2026'!D:D) -> Anda Pribadi Sembada wx1503646 | D84: =_xlfn.XLOOKUP(J84,'Master Data 14-9-2026'!C:C,'Master Data 14-9-2026'!E:E) -> XLSMART-NWL | G84: M1 | H84: =_xlfn.XLOOKUP(J84,'Master Data 14-9-2026'!C:C,'Master Data 14-9-2026'!H:H) -> 2026-03-30 - 2026-04-29 | I84: =TEXT(DATEVALUE(LEFT(H84,10)),"mmmm") -> March | J84: PE-Project_Engineer-024-M1 | K84: PE-Project_Engineer-024-M1 | L84: Bali Nusra | M84: 200003106214020 | N84: FPA1091IDN26031710640667 | O84: 1.0912026e+17 | P84: 1091HG3728823-53 | Q84: 1 | R84: 1 | S84: 8828132635 | T84: Project Delivery Monitoring Services - Project Engineer | U84: 34220600 | V84: 1 | W84: =_xlfn.XLOOKUP(J84,'Master Data 14-9-2026'!C:C,'Master Data 14-9-2026'!L:L) -> 1.46 | X84: =V84*U84 -> 34220600 | Y84: 2026-05-20 | Z84: Ended | AA84: Approved | AD84: Invoice | AE84: =_xlfn.XLOOKUP(L84,'[1]ID PROJECT'!E:E,'[1]ID PROJECT'!F:F) -> PRJ-KUT-KPU-TPED-2026-04-00077 | AF84: SSO-KUT-KPU-NIUT-2026-08-04337 | AG84: 375/INV/KUT-PST/VIII/2026 | AH84: 46262 | AI84: Agustus | AJ84: Move from PO 1091HG3728823-10
A85: PE-Project_Engineer-034 | B85: =_xlfn.XLOOKUP(J85,'Master Data 14-9-2026'!C:C,'Master Data 14-9-2026'!D:D) -> Anan Agrani wx1524133 | D85: =_xlfn.XLOOKUP(J85,'Master Data 14-9-2026'!C:C,'Master Data 14-9-2026'!E:E) -> XLSMART | G85: M1 | H85: =_xlfn.XLOOKUP(J85,'Master Data 14-9-2026'!C:C,'Master Data 14-9-2026'!H:H) -> 2026-06-16 - 2026-07-15 | I85: =TEXT(DATEVALUE(LEFT(H85,10)),"mmmm") -> June | J85: PE-Project_Engineer-034-M1 | K85: Wisma Mulia | L85: Jabodetabek | M85: 200003118945020 | N85: FPA1091IDN26031710640667 | O85: 1.0912026e+17 | P85: 1091HG3728823-11 | Q85: 1 | R85: 1 | S85: 8828132635 | T85: Project Delivery Monitoring Services - Project Engineer | U85: 34220600 | V85: 1 | W85: =_xlfn.XLOOKUP(J85,'Master Data 14-9-2026'!C:C,'Master Data 14-9-2026'!L:L) -> 0.5 | X85: 34220600 | Y85: 2026-05-22 | Z85: =_xlfn.XLOOKUP(J85,'Master Data 14-9-2026'!C:C,'Master Data 14-9-2026'!I:I) -> Ended | AA85: Reject | AB85: Poor | AE85: =_xlfn.XLOOKUP(L85,'[1]ID PROJECT'!E:E,'[1]ID PROJECT'!F:F) -> PRJ-KUT-KPU-TPED-2026-04-00071
A86: DC-Document_Controller-035 | B86: =_xlfn.XLOOKUP(J86,'Master Data 14-9-2026'!C:C,'Master Data 14-9-2026'!D:D) -> Ajeng Meylani wx1521189 | D86: =_xlfn.XLOOKUP(J86,'Master Data 14-9-2026'!C:C,'Master Data 14-9-2026'!E:E) -> XLSMART | G86: M1 | H86: =_xlfn.XLOOKUP(J86,'Master Data 14-9-2026'!C:C,'Master Data 14-9-2026'!H:H) -> 2026-05-20 - 2026-06-19 | I86: =TEXT(DATEVALUE(LEFT(H86,10)),"mmmm") -> May | J86: DC-Document_Controller-035-M1 | K86: Wisma Mulia | L86: Jabodetabek | M86: 200003118946020 | N86: FPA1091IDN26031710640667 | O86: 1.0912026e+17 | P86: 1091HG3728823-11 | Q86: 2 | R86: 1 | S86: 8828132633 | T86: Project Delivery Monitoring Services - Document Control | U86: 28881900 | V86: 1 | W86: =_xlfn.XLOOKUP(J86,'Master Data 14-9-2026'!C:C,'Master Data 14-9-2026'!L:L) -> 0 | X86: 28881900 | Y86: 2026-05-22 | Z86: Ended | AA86: Approved | AD86: Invoice | AE86: =_xlfn.XLOOKUP(L86,'[1]ID PROJECT'!E:E,'[1]ID PROJECT'!F:F) -> PRJ-KUT-KPU-TPED-2026-04-00071 | AF86: SSO-KUT-KPU-NIUT-2026-07-03354 | AG86: 278/INV/KUT-PST/VII/2026 | AH86: 46206 | AI86: Juli
A87: QC-Quality_Control-020 | B87: =_xlfn.XLOOKUP(J87,'Master Data 14-9-2026'!C:C,'Master Data 14-9-2026'!D:D) -> Benny Prio Utomo wx1513406 | D87: =_xlfn.XLOOKUP(J87,'Master Data 14-9-2026'!C:C,'Master Data 14-9-2026'!E:E) -> XLSMART | G87: M1 | H87: =_xlfn.XLOOKUP(J87,'Master Data 14-9-2026'!C:C,'Master Data 14-9-2026'!H:H) -> 2026-04-21 - 2026-05-20 | I87: =TEXT(DATEVALUE(LEFT(H87,10)),"mmmm") -> April | J87: QC-Quality_Control-020-M1 | K87: Wisma Mulia | L87: Jabodetabek | M87: 200003122177020 | N87: FPA1091IDN26031710640667 | O87: 1.0912026e+17 | P87: 1091HG3728823-11 | Q87: 3 | R87: 1 | S87: 8828132636 | T87: QEHS Onsite Monitoring and Inspection - QC | U87: 36992000 | V87: 1 | W87: =_xlfn.XLOOKUP(J87,'Master Data 14-9-2026'!C:C,'Master Data 14-9-2026'!L:L) -> 1.5 | X87: 36992000 | Y87: 2026-05-22 | Z87: Ended | AA87: Approved | AD87: Invoice | AE87: =_xlfn.XLOOKUP(L87,'[1]ID PROJECT'!E:E,'[1]ID PROJECT'!F:F) -> PRJ-KUT-KPU-TPED-2026-04-00071 | AF87: SSO-KUT-KPU-NIUT-2026-06-03067 | AG87: 258/INV/KUT-PST/VI/2026 | AH87: 46197 | AI87: Juni
A88: PE-Project_Engineer-026 | B88: =_xlfn.XLOOKUP(J88,'Master Data 14-9-2026'!C:C,'Master Data 14-9-2026'!D:D) -> Zulfan Arrofi wx1517184 | D88: =_xlfn.XLOOKUP(J88,'Master Data 14-9-2026'!C:C,'Master Data 14-9-2026'!E:E) -> XLSMART | G88: M1 | H88: =_xlfn.XLOOKUP(J88,'Master Data 14-9-2026'!C:C,'Master Data 14-9-2026'!H:H) -> 2026-05-05 - 2026-06-04 | I88: =TEXT(DATEVALUE(LEFT(H88,10)),"mmmm") -> May | J88: PE-Project_Engineer-026-M1 | K88: Wisma Mulia | L88: Jabodetabek | M88: 200003122178020 | N88: FPA1091IDN26031710640667 | O88: 1.0912026e+17 | P88: 1091HG3728823-11 | Q88: 4 | R88: 1 | S88: 8828132635 | T88: Project Delivery Monitoring Services - Project Engineer | U88: 34220600 | V88: 1 | W88: =_xlfn.XLOOKUP(J88,'Master Data 14-9-2026'!C:C,'Master Data 14-9-2026'!L:L) -> 0 | X88: 34220600 | Y88: 2026-05-22 | Z88: Ended | AA88: Approved | AD88: Invoice | AE88: =_xlfn.XLOOKUP(L88,'[1]ID PROJECT'!E:E,'[1]ID PROJECT'!F:F) -> PRJ-KUT-KPU-TPED-2026-04-00071 | AF88: SSO-KUT-KPU-NIUT-2026-06-03106 | AG88: 263/INV/KUT-PST/VI/2026 | AH88: 46198 | AI88: Juni
A89: DC-Document_Controller-041 | B89: =_xlfn.XLOOKUP(J89,'Master Data 14-9-2026'!C:C,'Master Data 14-9-2026'!D:D) -> Alda Rania Nawawi wx1522941 | D89: =_xlfn.XLOOKUP(J89,'Master Data 14-9-2026'!C:C,'Master Data 14-9-2026'!E:E) -> XLSMART | G89: M1 | H89: =_xlfn.XLOOKUP(J89,'Master Data 14-9-2026'!C:C,'Master Data 14-9-2026'!H:H) -> 2026-06-02 - 2026-07-01 | I89: =TEXT(DATEVALUE(LEFT(H89,10)),"mmmm") -> June | J89: DC-Document_Controller-041-M1 | K89: Wisma Mulia | L89: Jabodetabek | M89: 200003119150020 | N89: FPA1091IDN26031710640667 | O89: 1.0912026e+17 | P89: 1091HG3728823-12 | Q89: 1 | R89: 1 | S89: 8828132633 | T89: Project Delivery Monitoring Services - Document Control | U89: 28881900 | V89: 1 | W89: =_xlfn.XLOOKUP(J89,'Master Data 14-9-2026'!C:C,'Master Data 14-9-2026'!L:L) -> 0 | X89: 28881900 | Y89: 2026-05-22 | Z89: =_xlfn.XLOOKUP(J89,'Master Data 14-9-2026'!C:C,'Master Data 14-9-2026'!I:I) -> Ended | AB89: Poor | AC89: KUT FU | AE89: =_xlfn.XLOOKUP(L89,'[1]ID PROJECT'!E:E,'[1]ID PROJECT'!F:F) -> PRJ-KUT-KPU-TPED-2026-04-00071
A90: DC-Document_Controller-042 | B90: =_xlfn.XLOOKUP(J90,'Master Data 14-9-2026'!C:C,'Master Data 14-9-2026'!D:D) -> #N/A | D90: =_xlfn.XLOOKUP(J90,'Master Data 14-9-2026'!C:C,'Master Data 14-9-2026'!E:E) -> #N/A | G90: M1 | H90: =_xlfn.XLOOKUP(J90,'Master Data 14-9-2026'!C:C,'Master Data 14-9-2026'!H:H) -> #N/A | I90: =TEXT(DATEVALUE(LEFT(H90,10)),"mmmm") -> #N/A | J90: DC-Document_Controller-042-M1 | K90: Wisma Mulia | L90: Jabodetabek | M90: 200003119151020 | N90: FPA1091IDN26031710640667 | O90: 1.0912026e+17 | P90: 1091HG3728823-12 | Q90: 2 | R90: 1 | S90: 8828132633 | T90: Project Delivery Monitoring Services - Document Control | U90: 28881900 | V90: 1 | W90: =_xlfn.XLOOKUP(J90,'Master Data 14-9-2026'!C:C,'Master Data 14-9-2026'!L:L) -> #N/A | X90: 28881900 | Y90: 2026-05-22 | Z90: Tidak ditemukan | AB90: not join | AC90: request cancel by email | AE90: =_xlfn.XLOOKUP(L90,'[1]ID PROJECT'!E:E,'[1]ID PROJECT'!F:F) -> PRJ-KUT-KPU-TPED-2026-04-00071
A91: DC-Document_Controller-040 | B91: =_xlfn.XLOOKUP(J91,'Master Data 14-9-2026'!C:C,'Master Data 14-9-2026'!D:D) -> #N/A | D91: =_xlfn.XLOOKUP(J91,'Master Data 14-9-2026'!C:C,'Master Data 14-9-2026'!E:E) -> #N/A | G91: M1 | H91: =_xlfn.XLOOKUP(J91,'Master Data 14-9-2026'!C:C,'Master Data 14-9-2026'!H:H) -> #N/A | I91: =TEXT(DATEVALUE(LEFT(H91,10)),"mmmm") -> #N/A | J91: DC-Document_Controller-040-M1 | K91: Wisma Mulia | L91: Jabodetabek | M91: 200003119149020 | N91: FPA1091IDN26031710640667 | O91: 1.0912026e+17 | P91: 1091HG3728823-12 | Q91: 3 | R91: 1 | S91: 8828132633 | T91: Project Delivery Monitoring Services - Document Control | U91: 28881900 | V91: 1 | W91: =_xlfn.XLOOKUP(J91,'Master Data 14-9-2026'!C:C,'Master Data 14-9-2026'!L:L) -> #N/A | X91: 28881900 | Y91: 2026-05-22 | Z91: Tidak ditemukan | AB91: not join | AC91: request cancel by email | AE91: =_xlfn.XLOOKUP(L91,'[1]ID PROJECT'!E:E,'[1]ID PROJECT'!F:F) -> PRJ-KUT-KPU-TPED-2026-04-00071
A92: DC-Document_Controller-043 | B92: =_xlfn.XLOOKUP(J92,'Master Data 14-9-2026'!C:C,'Master Data 14-9-2026'!D:D) -> #N/A | D92: =_xlfn.XLOOKUP(J92,'Master Data 14-9-2026'!C:C,'Master Data 14-9-2026'!E:E) -> #N/A | G92: M1 | H92: =_xlfn.XLOOKUP(J92,'Master Data 14-9-2026'!C:C,'Master Data 14-9-2026'!H:H) -> #N/A | I92: =TEXT(DATEVALUE(LEFT(H92,10)),"mmmm") -> #N/A | J92: DC-Document_Controller-043-M1 | K92: Wisma Mulia | L92: Jabodetabek | M92: 200003119152020 | N92: FPA1091IDN26031710640667 | O92: 1.0912026e+17 | P92: 1091HG3728823-12 | Q92: 4 | R92: 1 | S92: 8828132633 | T92: Project Delivery Monitoring Services - Document Control | U92: 28881900 | V92: 1 | W92: =_xlfn.XLOOKUP(J92,'Master Data 14-9-2026'!C:C,'Master Data 14-9-2026'!L:L) -> #N/A | X92: 28881900 | Y92: 2026-05-22 | Z92: Tidak ditemukan | AB92: not join | AC92: request cancel by email | AE92: =_xlfn.XLOOKUP(L92,'[1]ID PROJECT'!E:E,'[1]ID PROJECT'!F:F) -> PRJ-KUT-KPU-TPED-2026-04-00071
A93: DC-Document_Controller-038 | B93: =_xlfn.XLOOKUP(J93,'Master Data 14-9-2026'!C:C,'Master Data 14-9-2026'!D:D) -> #N/A | D93: =_xlfn.XLOOKUP(J93,'Master Data 14-9-2026'!C:C,'Master Data 14-9-2026'!E:E) -> #N/A | G93: M1 | H93: =_xlfn.XLOOKUP(J93,'Master Data 14-9-2026'!C:C,'Master Data 14-9-2026'!H:H) -> #N/A | I93: =TEXT(DATEVALUE(LEFT(H93,10)),"mmmm") -> #N/A | J93: DC-Document_Controller-038-M1 | K93: DC-Document_Controller-038-M1 | L93: Jabodetabek | M93: 200003122508020 | N93: FPA1091IDN26031710640667 | O93: 1.0912026e+17 | P93: 1091HG3728823-13 | Q93: 1 | R93: 1 | S93: 8828132633 | T93: Project Delivery Monitoring Services - Document Control | U93: 28881900 | V93: 1 | W93: =_xlfn.XLOOKUP(J93,'Master Data 14-9-2026'!C:C,'Master Data 14-9-2026'!L:L) -> #N/A | X93: 28881900 | Y93: 2026-05-25 | Z93: Tidak ditemukan | AB93: Cancel PO | AE93: =_xlfn.XLOOKUP(L93,'[1]ID PROJECT'!E:E,'[1]ID PROJECT'!F:F) -> PRJ-KUT-KPU-TPED-2026-04-00071
A94: DC-Document_Controller-039 | B94: =_xlfn.XLOOKUP(J94,'Master Data 14-9-2026'!C:C,'Master Data 14-9-2026'!D:D) -> Rahma Nihayatul Nur M WX1524121 | D94: =_xlfn.XLOOKUP(J94,'Master Data 14-9-2026'!C:C,'Master Data 14-9-2026'!E:E) -> IOH | G94: M1 | H94: =_xlfn.XLOOKUP(J94,'Master Data 14-9-2026'!C:C,'Master Data 14-9-2026'!H:H) -> 2026-06-01 - 2026-06-30 | I94: =TEXT(DATEVALUE(LEFT(H94,10)),"mmmm") -> June | J94: DC-Document_Controller-039-M1 | K94: DC-Document_Controller-039-M1 | L94: Jabodetabek | M94: 200003122509020 | N94: FPA1091IDN26031710640667 | O94: 1.0912026e+17 | P94: 1091HG3728823-13 | Q94: 2 | R94: 1 | S94: 8828132633 | T94: Project Delivery Monitoring Services - Document Control | U94: 28881900 | V94: 1 | W94: =_xlfn.XLOOKUP(J94,'Master Data 14-9-2026'!C:C,'Master Data 14-9-2026'!L:L) -> 0 | X94: 28881900 | Y94: 2026-05-25 | Z94: =_xlfn.XLOOKUP(J94,'Master Data 14-9-2026'!C:C,'Master Data 14-9-2026'!I:I) -> Ended | AE94: =_xlfn.XLOOKUP(L94,'[1]ID PROJECT'!E:E,'[1]ID PROJECT'!F:F) -> PRJ-KUT-KPU-TPED-2026-04-00071
A95: PE-Project_Engineer-035 | B95: =_xlfn.XLOOKUP(J95,'Master Data 14-9-2026'!C:C,'Master Data 14-9-2026'!D:D) -> Abdul Dedi Halik wx1522830 | D95: =_xlfn.XLOOKUP(J95,'Master Data 14-9-2026'!C:C,'Master Data 14-9-2026'!E:E) -> IOH | G95: M1 | H95: =_xlfn.XLOOKUP(J95,'Master Data 14-9-2026'!C:C,'Master Data 14-9-2026'!H:H) -> 2026-05-25 - 2026-06-24 | I95: =TEXT(DATEVALUE(LEFT(H95,10)),"mmmm") -> May | J95: PE-Project_Engineer-035-M1 | K95: PE-Project_Engineer-035-M1 | L95: Jabodetabek | M95: 200003122510020 | N95: FPA1091IDN26031710640667 | O95: 1.0912026e+17 | P95: 1091HG3728823-14 | Q95: 1 | R95: 1 | S95: 8828132635 | T95: Project Delivery Monitoring Services - Project Engineer | U95: 34220600 | V95: 1 | W95: =_xlfn.XLOOKUP(J95,'Master Data 14-9-2026'!C:C,'Master Data 14-9-2026'!L:L) -> 0 | X95: 34220600 | Y95: 2026-05-26 | Z95: Ended | AE95: =_xlfn.XLOOKUP(L95,'[1]ID PROJECT'!E:E,'[1]ID PROJECT'!F:F) -> PRJ-KUT-KPU-TPED-2026-04-00071
A96: PE-Project_Engineer-036 | B96: =_xlfn.XLOOKUP(J96,'Master Data 14-9-2026'!C:C,'Master Data 14-9-2026'!D:D) -> Dian Rahmanda wx1522831 | D96: =_xlfn.XLOOKUP(J96,'Master Data 14-9-2026'!C:C,'Master Data 14-9-2026'!E:E) -> IOH | G96: M1 | H96: =_xlfn.XLOOKUP(J96,'Master Data 14-9-2026'!C:C,'Master Data 14-9-2026'!H:H) -> 2026-06-02 - 2026-07-01 | I96: =TEXT(DATEVALUE(LEFT(H96,10)),"mmmm") -> June | J96: PE-Project_Engineer-036-M1 | K96: PE-Project_Engineer-036-M1 | L96: Jabodetabek | M96: 200003122511020 | N96: FPA1091IDN26031710640667 | O96: 1.0912026e+17 | P96: 1091HG3728823-14 | Q96: 2 | R96: 1 | S96: 8828132635 | T96: Project Delivery Monitoring Services - Project Engineer | U96: 34220600 | V96: 1 | W96: =_xlfn.XLOOKUP(J96,'Master Data 14-9-2026'!C:C,'Master Data 14-9-2026'!L:L) -> 0 | X96: 34220600 | Y96: 2026-05-26 | Z96: =_xlfn.XLOOKUP(J96,'Master Data 14-9-2026'!C:C,'Master Data 14-9-2026'!I:I) -> Ended | AE96: =_xlfn.XLOOKUP(L96,'[1]ID PROJECT'!E:E,'[1]ID PROJECT'!F:F) -> PRJ-KUT-KPU-TPED-2026-04-00071
A97: PE-Project_Engineer-037 | B97: =_xlfn.XLOOKUP(J97,'Master Data 14-9-2026'!C:C,'Master Data 14-9-2026'!D:D) -> Muh Riefqi Ferdhana Alhamdi WX1522829 | D97: =_xlfn.XLOOKUP(J97,'Master Data 14-9-2026'!C:C,'Master Data 14-9-2026'!E:E) -> IOH | G97: M1 | H97: =_xlfn.XLOOKUP(J97,'Master Data 14-9-2026'!C:C,'Master Data 14-9-2026'!H:H) -> 2026-05-25 - 2026-06-24 | I97: =TEXT(DATEVALUE(LEFT(H97,10)),"mmmm") -> May | J97: PE-Project_Engineer-037-M1 | K97: PE-Project_Engineer-037-M1 | L97: Jabodetabek | M97: 200003122512020 | N97: FPA1091IDN26031710640667 | O97: 1.0912026e+17 | P97: 1091HG3728823-14 | Q97: 3 | R97: 1 | S97: 8828132635 | T97: Project Delivery Monitoring Services - Project Engineer | U97: 34220600 | V97: 1 | W97: =_xlfn.XLOOKUP(J97,'Master Data 14-9-2026'!C:C,'Master Data 14-9-2026'!L:L) -> 0 | X97: 34220600 | Y97: 2026-05-26 | Z97: Ended | AB97: Cancel PO | AE97: =_xlfn.XLOOKUP(L97,'[1]ID PROJECT'!E:E,'[1]ID PROJECT'!F:F) -> PRJ-KUT-KPU-TPED-2026-04-00071
A98: DC-Document_Controller-007 | B98: =_xlfn.XLOOKUP(J98,'Master Data 14-9-2026'!C:C,'Master Data 14-9-2026'!D:D) -> Mauli Rizki Amelia wx1504666 | D98: =_xlfn.XLOOKUP(J98,'Master Data 14-9-2026'!C:C,'Master Data 14-9-2026'!E:E) -> XLSMART | G98: M3 | H98: =_xlfn.XLOOKUP(J98,'Master Data 14-9-2026'!C:C,'Master Data 14-9-2026'!H:H) -> 2026-05-26 - 2026-06-25 | I98: =TEXT(DATEVALUE(LEFT(H98,10)),"mmmm") -> May | J98: DC-Document_Controller-007-M3 | K98: Huawei ASEAN Academy | L98: Sumatera | M98: 200003134868020 | N98: FPA1091IDN26031710640667 | O98: 1.0912026e+17 | P98: 1091HG3728823-15 | Q98: 1 | R98: 1 | S98: 8828132633 | T98: Project Delivery Monitoring Services - Document Control | U98: 28881900 | V98: 1 | W98: =_xlfn.XLOOKUP(J98,'Master Data 14-9-2026'!C:C,'Master Data 14-9-2026'!L:L) -> 0 | X98: 28881900 | Y98: 2026-05-29 | Z98: Tidak ditemukan | AE98: =_xlfn.XLOOKUP(L98,'[1]ID PROJECT'!E:E,'[1]ID PROJECT'!F:F) -> PRJ-KUT-KPU-TPED-2026-04-00078
A99: QC-Quality_Control-020 | B99: =_xlfn.XLOOKUP(J99,'Master Data 14-9-2026'!C:C,'Master Data 14-9-2026'!D:D) -> Benny Prio Utomo wx1513406 | D99: =_xlfn.XLOOKUP(J99,'Master Data 14-9-2026'!C:C,'Master Data 14-9-2026'!E:E) -> XLSMART | G99: M3 | H99: =_xlfn.XLOOKUP(J99,'Master Data 14-9-2026'!C:C,'Master Data 14-9-2026'!H:H) -> 2026-06-21 - 2026-07-20 | I99: =TEXT(DATEVALUE(LEFT(H99,10)),"mmmm") -> June | J99: QC-Quality_Control-020-M3 | K99: Huawei ASEAN Academy | L99: Jabodetabek | M99: 200003134895020 | N99: FPA1091IDN26031710640667 | O99: 1.0912026e+17 | P99: 1091HG3728823-15 | Q99: 2 | R99: 1 | S99: 8828132636 | T99: QEHS Onsite Monitoring and Inspection - QC | U99: 36992000 | V99: 1 | W99: =_xlfn.XLOOKUP(J99,'Master Data 14-9-2026'!C:C,'Master Data 14-9-2026'!L:L) -> 1.5 | X99: 36992000 | Y99: 2026-05-29 | Z99: =_xlfn.XLOOKUP(J99,'Master Data 14-9-2026'!C:C,'Master Data 14-9-2026'!I:I) -> Ended | AE99: =_xlfn.XLOOKUP(L99,'[1]ID PROJECT'!E:E,'[1]ID PROJECT'!F:F) -> PRJ-KUT-KPU-TPED-2026-04-00071
A100: PE-Project_Engineer-026 | B100: =_xlfn.XLOOKUP(J100,'Master Data 14-9-2026'!C:C,'Master Data 14-9-2026'!D:D) -> Zulfan Arrofi wx1517184 | D100: =_xlfn.XLOOKUP(J100,'Master Data 14-9-2026'!C:C,'Master Data 14-9-2026'!E:E) -> XLSMART | G100: M2 | H100: =_xlfn.XLOOKUP(J100,'Master Data 14-9-2026'!C:C,'Master Data 14-9-2026'!H:H) -> 2026-06-05 - 2026-07-04 | I100: =TEXT(DATEVALUE(LEFT(H100,10)),"mmmm") -> June | J100: PE-Project_Engineer-026-M2 | K100: Huawei ASEAN Academy | L100: Jabodetabek | M100: 200003134850020 | N100: FPA1091IDN26031710640667 | O100: 1.0912026e+17 | P100: 1091HG3728823-15 | Q100: 3 | R100: 1 | S100: 8828132635 | T100: Project Delivery Monitoring Services - Project Engineer | U100: 34220600 | V100: 1 | W100: =_xlfn.XLOOKUP(J100,'Master Data 14-9-2026'!C:C,'Master Data 14-9-2026'!L:L) -> 0 | X100: 34220600 | Y100: 2026-05-29 | Z100: =_xlfn.XLOOKUP(J100,'Master Data 14-9-2026'!C:C,'Master Data 14-9-2026'!I:I) -> Ended | AB100: Poor | AC100: KUT FU | AE100: =_xlfn.XLOOKUP(L100,'[1]ID PROJECT'!E:E,'[1]ID PROJECT'!F:F) -> PRJ-KUT-KPU-TPED-2026-04-00071
...

Sheet ID Project
B3: M2 | D3: NO | E3: REGIONAL | F3: ID PROJECT
B4: > 23 Juni | D4: 1 | E4: Jabodetabek | F4: PRJ-KUT-KPU-TPED-2026-04-00071
D5: 2 | E5: West Java | F5: PRJ-KUT-KPU-TPED-2026-04-00074 | H5: PO NO. | I5: PO Line NO.
B6: Enterprise | C6: Indodata | D6: 3 | E6: Central Java | F6: PRJ-KUT-KPU-TPED-2026-04-00075 | H6: 1091HG3728823-49 | I6: 22
B7: Platform DMD | C7: Tsel | D7: 4 | E7: East Java | F7: PRJ-KUT-KPU-TPED-2026-04-00076
B8: Platform REGION | C8: IOH - W | D8: 5 | E8: Bali Nusra | F8: PRJ-KUT-KPU-TPED-2026-04-00077
D9: 6 | E9: Sumbagsel | F9: PRJ-KUT-KPU-TPED-2026-04-00078
D10: 7 | E10: Kalimantan | F10: PRJ-KUT-KPU-TPED-2026-04-00079
D11: 8 | E11: Sulawesi | F11: PRJ-KUT-KPU-TPED-2026-04-00080
D12: 9 | E12: Sumatera | F12: PRJ-KUT-KPU-TPED-2026-04-00078
E17: PE-Project_Engineer-002-M3
E18: PE-Project_Engineer-076-M2
G25: De | H25: 8 | I25: 294800 | J25: =I25*H25 -> 2358400
G26: lan | H26: 2 | I26: 228800 | J26: =I26*H26 -> 457600
J27: =SUM(J25:J26) -> 2816000
F31: sup mala | G31: 1 | H31: 76 | I31: =H31*G31 -> 76
F32: sup xx | G32: 1 | H32: 65 | I32: =H32*G32 -> 65
F33: daging 1 | G33: 1 | H33: 85 | I33: =H33*G33 -> 85
F34: daging 2 | G34: 1 | H34: 69 | I34: =H34*G34 -> 69
F35: daging 3 | G35: 1 | H35: 74 | I35: =H35*G35 -> 74
F36: platter | G36: 1 | H36: 63 | I36: =H36*G36 -> 63
F37: gyoza | G37: 1 | H37: 30 | I37: =H37*G37 -> 30
F38: crab | G38: 1 | H38: 28 | I38: =H38*G38 -> 28
F39: tahu jepang | G39: 1 | H39: 30 | I39: =H39*G39 -> 30
F40: odeng | G40: 1 | H40: 28 | I40: =H40*G40 -> 28
F41: mie tarik | G41: 1 | H41: 41 | I41: =H41*G41 -> 41
F42: udon | G42: 1 | H42: 28 | I42: =H42*G42 -> 28
... F44: es the | G44: 10 | H44: 19 | I44: =H44*G44 -> 190
I45: =SUM(I31:I44) -> 861
F48: mangkok 1 | G48: 250 | H48: 3280 | I48: =H48*G48 -> 820000
F49: mangkok 2 | G49: 600 | H49: 32800
F50: mangkok 3 | G50: 250 | H50: 32800

Sheet Sheet1
C4: Site Code | D4: Project assign by PO | E4: Project Code | F4: Project assign by dashboard | G4: Project Code | I4: Site Code.1 | J4: Name | K4: Region | L4: PO NO. | M4: Project Assign | N4: Project Code
C5: PE-Project_Engineer-029-M2 | D5: XLSMART | E5: 56A0R9P | F5: Tsel | G5: 56A0ECJ | I5: PE-Project_Engineer-008-M3 | J5: Rahmana Gautama | K5: Jabodetabek | L5: 1091HG3728823-111 | M5: IOH | N5: 56A0QEJ
C6: PE-Project_Engineer-002-M3 | D6: IOH | E6: 56A0QEJ | F6: XLSmart | G6: 56A0R9P | I6: PE-Project_Engineer-008-M4 | J6: Rahmana Gautama | K6: Jabodetabek | L6: 1091HG3728823-111 | M6: IOH | N6: 56A0QEJ
C7: PE-Project_Engineer-002-M5 | D7: IOH | E7: 56A0QEJ | F7: XLSmart | G7: 56A0R9P | I7: DC-Document_Controller-020-M2 | J7: Lidya Leoni Mutiara | K7: Jabodetabek | L7: 1091HG3728823-111 | M7: IOH | N7: 56A0QEJ
C8: DC-Document_Controller-020-M5 | D8: IOH | E8: 56A0QEJ | F8: IOH NWL | G8: 56A0H56

Sheet DC_Detail
A1: Uniq-ID | B1: Name ID | C1: Account | D1: Period | E1: Period Date | F1: Period Status | G1: Productivity Range | H1: Total % Ach. | I1: Payment Coef. | J1: Document Category | K1: Document Type | L1: Source Data | M1: Baseline/Cycle | N1: Total Doc. | O1: % Achievement
A2: DC-Document_Controller-021 | B2: Winarsih wx1503649 | C2: TELKOMSEL | D2: M-01 | E2: 2026-04-01 - 2026-04-30 | F2: Ended | G2: Excellent | H2: 272.3 % | I2: 1.36 | J2: Implementation | K2: Tagging Dismantle Material | L2: ISDP | M2: 35 | N2: 2 | O2: 5.71 %
A3: DC-Document_Controller-021 | B3: Winarsih wx1503649 | C3: TELKOMSEL | D3: M-01 | E3: 2026-04-01 - 2026-04-30 | F3: Ended | G3: Excellent | H3: 272.3 % | I3: 1.36 | J3: Implementation | K3: M-08 Dismantle | L3: ISDP | M3: 36 | N3: 2 | O3: 5.56 %
A4: DC-Document_Controller-021 | B4: Winarsih wx1503649 | C4: TELKOMSEL | D4: M-01 | E4: 2026-04-01 - 2026-04-30 | F4: Ended | G4: Excellent | H4: 272.3 % | I4: 1.36 | J4: Implementation | K4: Tagging Installation | L4: ISDP | M4: 32 | N4: 54 | O4: 168.75 %
A5: DC-Document_Controller-021 | B5: Winarsih wx1503649 | C5: TELKOMSEL | D5: M-01 | E5: 2026-04-01 - 2026-04-30 | F5: Ended | G5: Excellent | H5: 272.3 % | I5: 1.36 | J5: Pre-implementation | K5: Tenant Installation Report | L5: ISDP | M5: 13 | N5: 12 | O5: 92.31 %
A6: DC-Document_Controller-021 | B6: Winarsih wx1503649 | C6: TELKOMSEL | D6: M-02 | E6: 2026-05-01 - 2026-05-31 | F6: Ended | G6: Normal | H6: 195.1 % | I6: 1 | J6: Implementation | K6: Tagging Installation | L6: ISDP | M6: 32 | N6: 30 | O6: 93.75 %
A7: DC-Document_Controller-021 | B7: Winarsih wx1503649 | C7: TELKOMSEL | D7: M-02 | E7: 2026-05-01 - 2026-05-31 | F7: Ended | G7: Normal | H7: 195.1 % | I7: 1 | J7: Implementation | K7: Tagging Dismantle Material | L7: ISDP | M7: 35 | N7: 17 | O7: 48.57 %
A8: DC-Document_Controller-021 | B8: Winarsih wx1503649 | C8: TELKOMSEL | D8: M-02 | E8: 2026-05-01 - 2026-05-31 | F8: Ended | G8: Normal | H8: 195.1 % | I8: 1 | J8: Implementation | K8: M-08 Dismantle | L8: ISDP | M8: 36 | N8: 19 | O8: 52.78 %
A9: DC-Document_Controller-021 | B9: Winarsih wx1503649 | C9: TELKOMSEL | D9: M-03 | E9: 2026-06-01 - 2026-06-30 | F9: Ended | G9: Excellent | H9: 887.9 % | I9: 1.5 | J9: Acceptance | K9: BAST (AC1) | L9: ISDP | M9: 205 | N9: 537 | O9: 261.95 %
A10: DC-Document_Controller-021 | B10: Winarsih wx1503649 | C10: TELKOMSEL | D10: M-03 | E10: 2026-06-01 - 2026-06-30 | F10: Ended | G10: Excellent | H10: 887.9 % | I10: 1.5 | J10: Acceptance | K10: BAUT (AC1) | L10: ISDP | M10: 205 | N10: 537 | O10: 261.95 %
A11: DC-Document_Controller-021 | B11: Winarsih wx1503649 | C11: TELKOMSEL | D11: M-03 | E11: 2026-06-01 - 2026-06-30 | F11: Ended | G11: Excellent | H11: 887.9 % | I11: 1.5 | J11: Implementation | K11: M-08 Dismantle | L11: ISDP | M11: 36 | N11: 9 | O11: 25.00 %
A12: DC-Document_Controller-021 | B12: Winarsih wx1503649 | C12: TELKOMSEL | D12: M-03 | E12: 2026-06-01 - 2026-06-30 | F12: Ended | G12: Excellent | H12: 887.9 % | I12: 1.5 | J12: Implementation | K12: Tagging Dismantle Material | L12: ISDP | M12: 35 | N12: 14 | O12: 40.00 %
A13: DC-Document_Controller-021 | B13: Winarsih wx1503649 | C13: TELKOMSEL | D13: M-03 | E13: 2026-06-01 - 2026-06-30 | F13: Ended | G13: Excellent | H13: 887.9 % | I13: 1.5 | J13: Implementation | K13: Tagging Installation | L13: ISDP | M13: 32 | N13: 92 | O13: 287.50 %
... A34: DC-Document_Controller-058 | B34: Nancy Febrila Eko wx1524066 | C34: TELKOMSEL | D34: M-03 | E34: 2026-08-02 - 2026-09-01 | F34: Ended | G34: Normal | H34: 183.7 % | I34: 1 | J34: Implementation | K34: Tagging Dismantle Material | L34: ISDP | M34: 35 | N34: 4 | O34: 11.43 %
A35: DC-Document_Controller-058 | B35: Nancy Febrila Eko wx1524066 | C35: TELKOMSEL | D35: M-04 | E35: 2026-09-02 - 2026-10-01 | F35: Ongoing | G35: Poor | H35: 0.0 %
A36: DC-Document_Controller-004 | B36: Hyang Iman Kinasih Gusti wx1503650 | C36: IOH | D36: M-01 | E36: 2026-03-23 - 2026-04-22 | F36: Ended | G36: Excellent | H36: 917.1 % | I36: 1.5 | J36: Pre-implementation | K36: Site Permit | L36: Datalink | M36: 20 | N36: 100 | O36: 500.00 %
A37: DC-Document_Controller-004 | B37: Hyang Iman Kinasih Gusti wx1503650 | C37: IOH | D37: M-01 | E37: 2026-03-23 - 2026-04-22 | F37: Ended | G37: Excellent | H37: 917.1 % | I37: 1.5 | J37: Pre-implementation | K37: Site Permit | L37: Datalink | M37: 26 | N37: 100 | O37: 384.62 %
A38: DC-Document_Controller-004 | B38: Hyang Iman Kinasih Gusti wx1503650 | C38: IOH | D38: M-01 | E38: 2026-03-23 - 2026-04-22 | F38: Ended | G38: Excellent | H38: 917.1 % | I38: 1.5 | J38: Pre-implementation | K38: Site Permit | L38: Datalink | M38: 308 | N38: 100 | O38: 32.47 %
A39: DC-Document_Controller-004 | B39: Hyang Iman Kinasih Gusti wx1503650 | C39: IOH | D39: M-02 | E39: 2026-04-23 - 2026-05-22 | F39: Ended | G39: Excellent | H39: 917.1 % | I39: 1.5 | J39: Pre-implementation | K39: Site Permit | L39: Datalink | M39: 20 | N39: 100 | O39: 500.00 %
A40: DC-Document_Controller-004 | B40: Hyang Iman Kinasih Gusti wx1503650 | C40: IOH | D40: M-02 | E40: 2026-04-23 - 2026-05-22 | F40: Ended | G40: Excellent | H40: 917.1 % | I40: 1.5 | J40: Pre-implementation | K40: Site Permit | L40: Datalink | M40: 26 | N40: 100 | O40: 384.62 %
A41: DC-Document_Controller-004 | B41: Hyang Iman Kinasih Gusti wx1503650 | C41: IOH | D41: M-02 | E41: 2026-04-23 - 2026-05-22 | F41: Ended | G41: Excellent | H41: 917.1 % | I41: 1.5 | J41: Pre-implementation | K41: Site Permit | L41: Datalink | M41: 308 | N41: 100 | O41: 32.47 %
A42: DC-Document_Controller-004 | B42: Hyang Iman Kinasih Gusti wx1503650 | C42: IOH | D42: M-03 | E42: 2026-05-23 - 2026-06-22 | F42: Ended | G42: Excellent | H42: 1614.1 % | I42: 1.5 | J42: Pre-implementation | K42: Site Permit | L42: Datalink | M42: 308 | N42: 176 | O42: 57.14 %
A43: DC-Document_Controller-004 | B43: Hyang Iman Kinasih Gusti wx1503650 | C43: IOH | D43: M-03 | E43: 2026-05-23 - 2026-06-22 | F43: Ended | G43: Excellent | H43: 1614.1 % | I43: 1.5 | J43: Pre-implementation | K43: Site Permit | L43: Datalink | M43: 26 | N43: 176 | O43: 676.92 %
A44: DC-Document_Controller-004 | B44: Hyang Iman Kinasih Gusti wx1503650 | C44: IOH | D44: M-03 | E44: 2026-05-23 - 2026-06-22 | F44: Ended | G44: Excellent | H44: 1614.1 % | I44: 1.5 | J44: Pre-implementation | K44: Site Permit | L44: Datalink | M44: 20 | N44: 176 | O44: 880.00 %
A45: DC-Document_Controller-004 | B45: Hyang Iman Kinasih Gusti wx1503650 | C45: IOH | D45: M-04 | E45: 2026-06-23 - 2026-07-22 | F45: Ended | G45: Excellent | H45: 1045.5 % | I45: 1.5 | J45: Pre-implementation | K45: Site Permit | L45: Datalink | M45: 308 | N45: 114 | O45: 37.01 %
A46: DC-Document_Controller-004 | B46: Hyang Iman Kinasih Gusti wx1503650 | C46: IOH | D46: M-04 | E46: 2026-06-23 - 2026-07-22 | F46: Ended | G46: Excellent | H46: 1045.5 % | I46: 1.5 | J46: Pre-implementation | K46: Site Permit | L46: Datalink | M46: 26 | N46: 114 | O46: 438.46 %
A47: DC-Document_Controller-004 | B47: Hyang Iman Kinasih Gusti wx1503650 | C47: IOH | D47: M-04 | E47: 2026-06-23 - 2026-07-22 | F47: Ended | G47: Excellent | H47: 1045.5 % | I47: 1.5 | J47: Pre-implementation | K47: Site Permit | L47: Datalink | M47: 20 | N47: 114 | O47: 570.00 %
... A50: DC-Document_Controller-004 | B50: Hyang Iman Kinasih Gusti wx1503650 | C50: IOH | D50: M-05 | E50: 2026-07-23 - 2026-08-22 | F50: Ended | G50: Excellent | H50: 917.1 % | I50: 1.5 | J50: Pre-implementation | K50: Site Permit | L50: Datalink | M50: 20 | N50: 100 | O50: 500.00 %
A51: DC-Document_Controller-004 | B51: Hyang Iman Kinasih Gusti wx1503650 | C51: IOH | D51: M-06 | E51: 2026-08-23 - 2026-09-22 | F51: Ongoing | G51: Poor | H51: 0.0 %
A52: DC-Document_Controller-001 | B52: Sri Hardianti Purnamasari wx1503627 | C52: TELKOMSEL | D52: M-01 | E52: 2026-03-23 - 2026-04-22 | F52: Ended | G52: Excellent | H52: 210.9 % | I52: 1.05 | J52: Implementation | K52: Tagging Dismantle Material | L52: ISDP | M52: 35 | N52: 28 | O52: 80.00 %
A53: DC-Document_Controller-001 | B53: Sri Hardianti Purnamasari wx1503627 | C53: TELKOMSEL | D53: M-01 | E53: 2026-03-23 - 2026-04-22 | F53: Ended | G53: Excellent | H53: 210.9 % | I53: 1.05 | J53: Implementation | K53: Tagging Installation | L53: ISDP | M53: 32 | N53: 41 | O53: 128.13 %
A54: DC-Document_Controller-001 | B54: Sri Hardianti Purnamasari wx1503627 | C54: TELKOMSEL | D54: M-01 | E54: 2026-03-23 - 2026-04-22 | F54: Ended | G54: Excellent | H54: 210.9 % | I54: 1.05 | J54: Implementation | K54: M-08 Dismantle | L54: ISDP | M54: 36 | N54: 1 | O54: 2.78 %
A55: DC-Document_Controller-001 | B55: Sri Hardianti Purnamasari wx1503627 | C55: TELKOMSEL | D55: M-02 | E55: 2026-04-23 - 2026-05-22 | F55: Ended | G55: Excellent | H55: 217.9 % | I55: 1.09 | J55: Implementation | K55: M-08 Dismantle | L55: ISDP | M55: 36 | N55: 12 | O55: 33.33 %
A56: DC-Document_Controller-001 | B56: Sri Hardianti Purnamasari wx1503627 | C56: TELKOMSEL | D56: M-02 | E56: 2026-04-23 - 2026-05-22 | F56: Ended | G56: Excellent | H56: 217.9 % | I56: 1.09 | J56: Implementation | K56: Tagging Dismantle Material | L56: ISDP | M56: 35 | N56: 18 | O56: 51.43 %
A57: DC-Document_Controller-001 | B57: Sri Hardianti Purnamasari wx1503627 | C57: TELKOMSEL | D57: M-02 | E57: 2026-04-23 - 2026-05-22 | F57: Ended | G57: Excellent | H57: 217.9 % | I57: 1.09 | J57: Implementation | K57: Tagging Installation | L57: ISDP | M57: 32 | N57: 18 | O57: 56.25 %
A58: DC-Document_Controller-001 | B58: Sri Hardianti Purnamasari wx1503627 | C58: TELKOMSEL | D58: M-02 | E58: 2026-04-23 - 2026-05-22 | F58: Ended | G58: Excellent | H58: 217.9 % | I58: 1.09 | J58: Pre-implementation | K58: CAF Application | L58: ISDP | M58: 26 | N58: 20 | O58: 76.92 %
A59: DC-Document_Controller-001 | B59: Sri Hardianti Purnamasari wx1503627 | C59: TELKOMSEL | D59: M-03 | E59: 2026-05-23 - 2026-06-22 | F59: Ended | G59: Normal | H59: 188.8 % | I59: 1 | J59: Implementation | K59: Tagging Installation | L59: ISDP | M59: 32 | N59: 44 | O59: 137.50 %
A60: DC-Document_Controller-001 | B60: Sri Hardianti Purnamasari wx1503627 | C60: TELKOMSEL | D60: M-03 | E60: 2026-05-23 - 2026-06-22 | F60: Ended | G60: Normal | H60: 188.8 % | I60: 1 | J60: Implementation | K60: Tagging Dismantle Material | L60: ISDP | M60: 35 | N60: 16 | O60: 45.71 %
A61: DC-Document_Controller-001 | B61: Sri Hardianti Purnamasari wx1503627 | C61: TELKOMSEL | D61: M-03 | E61: 2026-05-23 - 2026-06-22 | F61: Ended | G61: Normal | H61: 188.8 % | I61: 1 | J61: Implementation | K61: M-08 Dismantle | L61: ISDP | M61: 36 | N61: 2 | O61: 5.56 %
A62: DC-Document_Controller-001 | B62: Sri Hardianti Purnamasari wx1503627 | C62: TELKOMSEL | D62: M-04 | E62: 2026-06-23 - 2026-07-22 | F62: Ended | G62: Excellent | H62: 380.0 % | I62: 1.5 | J62: Implementation | K62: Tagging Dismantle Material | L62: ISDP | M62: 35 | N62: 63 | O62: 180.00 %
A63: DC-Document_Controller-001 | B63: Sri Hardianti Purnamasari wx1503627 | C63: TELKOMSEL | D63: M-04 | E63: 2026-06-23 - 2026-07-22 | F63: Ended | G63: Excellent | H63: 380.0 % | I63: 1.5 | J63: Implementation | K63: M-08 Dismantle | L63: ISDP | M63: 36 | N63: 36 | O63: 100.00 %
... A67: DC-Document_Controller-001 | B67: Sri Hardianti Purnamasari wx1503627 | C67: TELKOMSEL | D67: M-05 | E67: 2026-07-23 - 2026-08-22 | F67: Ended | G67: Excellent | H67: 491.1 % | I67: 1.5 | J67: Implementation | K67: M-08 Dismantle | L67: ISDP | M67: 36 | N67: 38 | O67: 105.56 %
A68: DC-Document_Controller-001 | B68: Sri Hardianti Purnamasari wx1503627 | C68: TELKOMSEL | D68: M-06 | E68: 2026-08-23 - 2026-09-22 | F68: Ongoing | G68: Poor | H68: 0.0 %
A69: DC-Document_Controller-054 | B69: Dwi Nofianti wx1524844 | C69: IOH | D69: M-01 | E69: 2026-06-03 - 2026-07-02 | F69: Ended | G69: Excellent | H69: 1008.8 % | I69: 1.5 | J69: Pre-implementation | K69: Site Permit | L69: Datalink | N69: 110
